Workbook
Name \0: #REF!
Name \a: #REF!
Name __MO1: #REF!
Name _MO1: #REF!
Name ACR: #REF!
Name AR: #REF!
Name AZU: #REF!
Name BAI: #REF!
Name BDI: 1.43344312465585
Name BLE: #REF!
Name BLQ: #REF!
Name CAL: #REF!
Name CATO: #REF!
Name CER: #REF!
Name CIM: #REF!
Name CIMB: #REF!
Name CIMC: #REF!
Name CINC: #REF!
Name CMA: #REF!
Name CMO: #REF!
Name DEZ: #REF!
Name DEZN: #REF!
Name DEZO: #REF!
Name DEZS: #REF!
Name DEZT: #REF!
Name DOIS: #REF!
Name DOZE: #REF!
Name EE: #REF!
Name EMA: #REF!
Name EMO: #REF!
Name ENC: #REF!
Name erd: #REF!
Name ESM: #REF!
Name FE: #REF!
Name FXD: #REF!
Name FXU: #REF!
Name LIQB: #REF!
Name LS: '[4]M.O.'!#REF!
Name luiuz: #REF!
Name luiz: #REF!
Name LX: #REF!
Name MACR: #REF!
Name MCOR: #REF!
Name MFI: #REF!
Name MO: #REF!
Name NOVE: #REF!
Name OF: #REF!
Name OITO: #REF!
Name ONZE: #REF!
Name PE: #REF!
Name PRE: #REF!
Name Print_Area_MI: #REF!
Name PVA: #REF!
Name QUAT: #REF!
Name QUIN: #REF!
Name RAZ: #REF!
Name RMA: #REF!
Name RMO: #REF!
Name SE: #REF!
Name SEIS: #REF!

Sheet FC Total (6 lotes)
AE1: Total | Previsão | EC1: FIM DAS VENDAS
A2: Ville de Provence | BP2: 24 meses pós obra | CN2: 48 meses pós obra | CZ2: 60 meses pós obra
C3: 1 | D3: 2 | E3: 3 | F3: 4 | G3: 5 | H3: 6 | I3: 7 | J3: 8 | K3: 9 | L3: 10 | M3: 11 | N3: 12 | O3: 13 | P3: 14 | Q3: 15 | R3: 16 | S3: 17 | T3: 18 | U3: 19 | V3: 20 | W3: 21 | X3: 22 | Y3: 23 | Z3: 24 | AA3: 25 | AB3: 26 | AC3: 27 | AG3: 28 | AH3: 29 | AI3: 30 | AJ3: 31 | AK3: 32 | AL3: 33 | AM3: 34 | AN3: 35 | AO3: 36 | AP3: 37 | AQ3: 38 | AR3: 39 | AS3: 40 | AT3: 41 | AU3: 42 | AV3: 43 | AW3: 44 | AX3: 45 | AY3: 46 | AZ3: 47 | BA3: 48 | BB3: 49 | BC3: 50 | BD3: 51 | BE3: 52 | BF3: 53 | BG3: 54 | BH3: 55 | BI3: 56 | BJ3: 57 | BK3: 58 | BL3: 59 | BM3: 60 | BN3: 61 | BO3: 62 | BP3: 63 | BQ3: 64 | BR3: 65 | BS3: 66 | BT3: 67 | BU3: 68 | BV3: 69 | BW3: 70 | BX3: 71 | BY3: 72 | BZ3: 73 | CA3: 74 | CB3: 75 | CC3: 76 | CD3: 77 | CE3: 78 | CF3: 79 | CG3: 80 | CH3: 81 | CI3: 82 | CJ3: 83 | CK3: 84 | CL3: 85 | CM3: 86 | CN3: 87 | CO3: 88 | CP3: 89 | CQ3: 90 | CR3: 91 | CS3: 92 | CT3: 93 | CU3: 94 | CV3: 95 | CW3: 96 | CX3: 97 | CY3: 98 | CZ3: 99 | DA3: 100 | DB3: 101 | DC3: 102 | DD3: 103 | DE3: 104 | DF3: 105 | DG3: 106 | DH3: 107 | DI3: 108 | DJ3: 109 | DK3: 110 | DL3: 111 | DM3: 112 | DN3: 113 | DO3: 114 | DP3: 115 | DQ3: 116 | DR3: 117 | DS3: 118 | DT3: 119 | DU3: 120 | DV3: 121 | DW3: 122 | DX3: 123 | DY3: 124 | DZ3: 125 | EA3: 126 | EB3: 127 | EC3: 128 | ED3: 129 | EE3: 130 | EF3: 131 | EG3: 132 | EH3: 133 | EI3: 134 | EJ3: 135 | EK3: 136 | EL3: 137 | EM3: 138 | EN3: 139 | EO3: 140 | EP3: 141 | EQ3: 142 | ER3: 143 | ES3: 144 | ET3: 145 | EU3: 146 | EV3: 147 | EW3: 148 | EX3: 149 | EY3: 150 | EZ3: 151 | FA3: 152 | FB3: 153 | FC3: 154 | FD3: 155 | FE3: 156 | FF3: 157 | FG3: 158 | FH3: 159 | FI3: 160 | FJ3: 161 | FK3: 162 | FL3: 163 | FM3: 164 | FN3: 165 | FO3: 166 | FP3: 167 | FQ3: 168 | FR3: 169 | FS3: 170 | FT3: 171 | FU3: 172 | FV3: 173 | FW3: 174 | FX3: 175 | FY3: 176 | FZ3: 177 | GA3: 178 | GB3: 179 | GC3: 180 | GD3: 181 | GE3: 182 | GF3: 183 | GG3: 184 | GH3: 185 | GI3: 186 | GJ3: 187 | GK3: 188 | GL3: 189 | GM3: 190 | GN3: 191 | GO3: 192 | GP3: 193 | GQ3: 194 | GR3: 195 | GS3: 196 | GT3: 197 | GU3: 198 | GV3: 199 | GW3: 200 | GX3: 201 | GY3: 202 | GZ3: 203 | HA3: 204 | HB3: 205 | HC3: 206 | HD3: 207 | HE3: 208 | HF3: 209 | HG3: 210 | HH3: 211 | HI3: 212 | HJ3: 213 | HK3: 214 | HL3: 215 | HM3: 216 | HN3: 217 | HO3: 218 | HP3: 219 | HQ3: 220 | HR3: 221 | HS3: 222 | HT3: 223 | HU3: 224
A4: Fluxo de Caixa | B4: REALIZADO | M4: REALIZADO
C5: 44958 | D5: 44986 | E5: 45017 | F5: 45047 | G5: 45078 | H5: 45108 | I5: 45139 | J5: 45170 | K5: 45200 | L5: 45231 | M5: 45261 | N5: 45292 | O5: 45323 | P5: 45352 | Q5: 45383 | R5: 45413 | S5: 45444 | T5: 45474 | U5: 45505 | V5: 45536 | W5: 45566 | X5: 45597 | Y5: 45627 | Z5: 45658 | AA5: 45689 | AB5: 45717 | AC5: 45748 | AE5: Total | Previsão | AG5: 45778 | AH5: 45809 | AI5: 45839 | AJ5: 45870 | AK5: 45901 | AL5: 45931 | AM5: 45962 | AN5: 45992 | AO5: 46023 | AP5: 46054 | AQ5: 46082 | AR5: 46113 | AS5: 46143 | AT5: 46174 | AU5: 46204 | AV5: 46235 | AW5: 46266 | AX5: 46296 | AY5: 46327 | AZ5: 46357 | BA5: 46388 | BB5: 46419 | BC5: 46447 | BD5: 46478 | BE5: 46508 | BF5: 46539 | BG5: 46569 | BH5: 46600 | BI5: 46631 | BJ5: 46661 | BK5: 46692 | BL5: 46722 | BM5: 46753 | BN5: 46784 | BO5: 46813 | BP5: 46844 | BQ5: 46874 | BR5: 46905 | BS5: 46935 | BT5: 46966 | BU5: 46997 | BV5: 47027 | BW5: 47058 | BX5: 47088 | BY5: 47119 | BZ5: 47150 | CA5: 47178 | CB5: 47209 | CC5: 47239 | CD5: 47270 | CE5: 47300 | CF5: 47331 | CG5: 47362 | CH5: 47392 | CI5: 47423 | CJ5: 47453 | CK5: 47484 | CL5: 47515 | CM5: 47543 | CN5: 47574 | CO5: 47604 | CP5: 47635 | CQ5: 47665 | CR5: 47696 | CS5: 47727 | CT5: 47757 | CU5: 47788 | CV5: 47818 | CW5: 47849 | CX5: 47880 | CY5: 47908 | CZ5: 47939 | DA5: 47969 | DB5: 48000 | DC5: 48030 | DD5: 48061 | DE5: 48092 | DF5: 48122 | DG5: 48153 | DH5: 48183 | DI5: 48214 | DJ5: 48245 | DK5: 48274 | DL5: 48305 | DM5: 48335 | DN5: 48366 | DO5: 48396 | DP5: 48427 | DQ5: 48458 | DR5: 48488 | DS5: 48519 | DT5: 48549 | DU5: 48580 | DV5: 48611 | DW5: 48639 | DX5: 48670 | DY5: 48700 | DZ5: 48731 | EA5: 48761 | EB5: 48792 | EC5: 48823 | ED5: 48853 | EE5: 48884 | EF5: 48914 | EG5: 48945 | EH5: 48976 | EI5: 49004 | EJ5: 49035 | EK5: 49065 | EL5: 49096 | EM5: 49126 | EN5: 49157 | EO5: 49188 | EP5: 49218 | EQ5: 49249 | ER5: 49279 | ES5: 49310 | ET5: 49341 | EU5: 49369 | EV5: 49400 | EW5: 49430 | EX5: 49461 | EY5: 49491 | EZ5: 49522 | FA5: 49553 | FB5: 49583 | FC5: 49614 | FD5: 49644 | FE5: 49675 | FF5: 49706 | FG5: 49735 | FH5: 49766 | FI5: 49796 | FJ5: 49827 | FK5: 49857 | FL5: 49888 | FM5: 49919 | FN5: 49949 | FO5: 49980 | FP5: 50010 | FQ5: 50041 | FR5: 50072 | FS5: 50100 | FT5: 50131 | FU5: 50161 | FV5: 50192 | FW5: 50222 | FX5: 50253 | FY5: 50284 | FZ5: 50314 | GA5: 50345 | GB5: 50375 | GC5: 50406 | GD5: 50437 | GE5: 50465 | GF5: 50496 | GG5: 50526 | GH5: 50557 | GI5: 50587 | GJ5: 50618 | GK5: 50649 | GL5: 50679 | GM5: 50710 | GN5: 50740 | GO5: 50771 | GP5: 50802 | GQ5: 50830 | GR5: 50861 | GS5: 50891 | GT5: 50922 | GU5: 50952 | GV5: 50983 | GW5: 51014 | GX5: 51044 | GY5: 51075 | GZ5: 51105 | HA5: 51136 | HB5: 51167 | HC5: 51196 | HD5: 51227 | HE5: 51257 | HF5: 51288 | HG5: 51318 | HH5: 51349 | HI5: 51380 | HJ5: 51410 | HK5: 51441 | HL5: 51471 | HM5: 51502 | HN5: 51533 | HO5: 51561 | HP5: 51592 | HQ5: 51622 | HR5: 51653 | HS5: 51683 | HT5: 51714 | HU5: 51745
A7: RECEITAS
A8: ITBI | B8: =SUM(C8:Z8) | AB8: 338614.68 | AC8: 391548.5 | AE8: =SUM(AG8:FN8)
A9: Receitas Contratadas | B9: =SUM(C9:AB9) | AB9: 2857997.7 | AC9: 3156158.3 | AE9: =SUM(AG9:HU9) | AG9: 1198605.4 | AH9: 1028029.6 | AI9: 1028028.6 | AJ9: 1241129.9 | AK9: 1090966.8 | AL9: 1028028.6 | AM9: 1028028.6 | AN9: 1121274.7 | AO9: 994547.37 | AP9: 994547.39 | AQ9: 6631742.8 | AR9: 3022467.8 | AS9: 618470.15 | AT9: 618470.02 | AU9: 1033077.1 | AV9: 618470.02 | AW9: 618470.02 | AX9: 732035 | AY9: 618470.02 | AZ9: 677753.1 | BA9: 619601.51 | BB9: 619601.53 | BC9: 644682.56 | BD9: 1365576.9 | BE9: 289576.23 | BF9: 197087.28 | BG9: 197087.28 | BH9: 197087.28 | BI9: 197087.28 | BJ9: 197087.28 | BK9: 197087.28 | BL9: 255238.85 | BM9: 197960.48 | BN9: 197960.48 | BO9: 223012.69 | BP9: 734638.11 | BQ9: 129621.61 | BR9: 112417.25 | BS9: 112417.25 | BT9: 112417.25 | BU9: 112417.25 | BV9: 112417.25 | BW9: 112417.25 | BX9: 112417.25 | BY9: 112417.25 | BZ9: 112417.25 | CA9: 137477.17 | CB9: 378997.8 | CC9: 100986.26 | CD9: 100986.33 | CE9: 100986.33 | CF9: 100986.33 | CG9: 100986.33 | CH9: 100986.33 | CI9: 100986.33 | CJ9: 100986.33 | CK9: 100986.33 | CL9: 100986.33 | CM9: 126208.8 | CN9: 394315.24 | CO9: 90222.75 | CP9: 90222.81 | CQ9: 90222.81 | CR9: 90222.81 | CS9: 90222.81 | CT9: 90222.81 | CU9: 90222.81 | CV9: 90222.81 | CW9: 90222.81 | CX9: 90222.81 | CY9: 115388.14 | CZ9: 412983.94 | DA9: 70627.87 | DB9: 70627.86 | DC9: 70627.86 | DD9: 70627.86 | DE9: 70627.86 | DF9: 70627.86 | DG9: 70627.86 | DH9: 70627.86 | DI9: 70627.86 | DJ9: 70627.86 | DK9: 95765.25 | DL9: 425774.43 | DM9: 71382.89 | DN9: 71382.92 | DO9: 71382.92 | DP9: 71382.92 | DQ9: 71382.92 | DR9: 71382.92 | DS9: 71382.92 | DT9: 71382.92 | DU9: 71382.92 | DV9: 71382.92 | DW9: 96449.45 | DX9: 324486.21
A11: PREVISÃO DE RECEITAS(ESTOQUE)
A12: Vendas 06 Lotes a.m. | B12: =SUM(C12:W12) | D12: 0 | E12: 0 | F12: 0 | G12: 0 | H12: 0 | I12: 0 | J12: 0 | K12: 0 | L12: 0 | M12: 0 | N12: 0 | O12: 0 | P12: 0 | Q12: 0 | R12: 0 | S12: 0 | T12: 0 | U12: 0 | V12: 0 | AE12: =SUM(AG12:HU12) | AG12: 550415.8 | AH12: 662771.15 | AI12: 775126.49 | AJ12: 887481.83 | AK12: 999837.17 | AL12: 1112192.5 | AM12: 1224547.9 | AN12: 1336903.2 | AO12: 1449258.5 | AP12: 1561613.9 | AQ12: 1673969.2 | AR12: 1786324.6 | AS12: 2363217.6 | AT12: 2446015.3 | AU12: 2528813 | AV12: 2611610.8 | AW12: 2694408.5 | AX12: 2777206.2 | AY12: 2860004 | AZ12: 2942801.7 | BA12: 3025599.4 | BB12: 3108397.2 | BC12: 3207723.9 | BD12: 3293895.7 | BE12: 3380067.4 | BF12: 3406377.9 | BG12: 3432688.4 | BH12: 3458998.9 | BI12: 3485309.4 | BJ12: 3511619.9 | BK12: 3554459.4 | BL12: 3584143.9 | BM12: 3613828.4 | BN12: 3643513 | BO12: 3687147.6 | BP12: 3715944.5 | BQ12: 3744741.4 | BR12: 3773538.3 | BS12: 3802335.2 | BT12: 3847661.1 | BU12: 3879832.1 | BV12: 3912003 | BW12: 3958124.1 | BX12: 3989407.4 | BY12: 4020690.7 | BZ12: 4051974 | CA12: 4083257.4 | CB12: 4129272.1 | CC12: 4162131.8 | CD12: 4177672.6 | CE12: 4193213.4 | CF12: 4222704.3 | CG12: 4237357.5 | CH12: 4252010.7 | CI12: 4266663.9 | CJ12: 4296048.5 | CK12: 4312278.1 | CL12: 4328507.7 | CM12: 4344737.3 | CN12: 4374917 | CO12: 4390258.9 | CP12: 4405600.9 | CQ12: 4420942.9 | CR12: 4452813.9 | CS12: 4469732.3 | CT12: 4486650.6 | CU12: 4503569 | CV12: 4534437.5 | CW12: 4550468.2 | CX12: 4566499 | CY12: 4582529.8 | CZ12: 4598040.4 | DA12: 4628282.5 | DB12: 4645369.6 | DC12: 4662456.6 | DD12: 4693493.8 | DE12: 4709693.3 | DF12: 4725892.7 | DG12: 4742092.2 | DH12: 4757771.5 | DI12: 4788182.3 | DJ12: 4805438 | DK12: 4822693.8 | DL12: 4839949.6 | DM12: 4529831.5 | DN12: 4135202 | DO12: 4012222.5 | DP12: 3889243 | DQ12: 3763945.8 | DR12: 3638648.7 | DS12: 3513351.5 | DT12: 3388054.3 | DU12: 3276707.2 | DV12: 3150522.4 | DW12: 3024337.6 | DX12: 2898152.8 | DY12: 2483378.7 | DZ12: 2079518.8 | EA12: 1982057.2 | EB12: 1884595.7 | EC12: 1787134.2 | ED12: 1689672.6 | EE12: 1592211.1 | EF12: 1494749.6 | EG12: 1396768 | EH12: 1296988.7 | EI12: 1197209.5 | EJ12: 1097430.2 | EK12: 997650.95 | EL12: 934992.87 | EM12: 909455.97 | EN12: 883919.08 | EO12: 857862.09 | EP12: 831805.11 | EQ12: 805748.13 | ER12: 779691.14 | ES12: 753634.16 | ET12: 727577.17 | EU12: 701520.19 | EV12: 675294.51 | EW12: 649068.83 | EX12: 622323.07 | EY12: 595577.3 | EZ12: 568831.53 | FA12: 542085.77 | FB12: 515340 | FC12: 488594.23 | FD12: 461679.77 | FE12: 434765.31 | FF12: 407330.76 | FG12: 379896.21 | FH12: 352461.67 | FI12: 325027.12 | FJ12: 308332.37 | FK12: 302377.44 | FL12: 296422.5 | FM12: 290298.87 | FN12: 284175.24 | FO12: 278051.61 | FP12: 271927.98 | FQ12: 265804.35 | FR12: 259680.72 | FS12: 253557.09 | FT12: 247433.46 | FU12: 241141.14 | FV12: 234848.81 | FW12: 228556.49 | FX12: 222264.16 | FY12: 215971.84 | FZ12: 209679.51 | GA12: 203387.18 | GB12: 197094.86 | GC12: 190633.84 | GD12: 184172.82 | GE12: 177711.8 | GF12: 171250.78 | GG12: 164789.76 | GH12: 158328.74 | GI12: 151867.72 | GJ12: 145406.7 | GK12: 138776.98 | GL12: 132147.27 | GM12: 125517.55 | GN12: 118887.84 | GO12: 112258.12 | GP12: 105628.4 | GQ12: 98998.689 | GR12: 92368.974 | GS12: 85739.258 | GT12: 78940.848 | GU12: 72142.437 | GV12: 65344.027 | GW12: 58545.616 | GX12: 51747.206 | GY12: 44948.796 | GZ12: 38150.385 | HA12: 31351.975 | HB12: 24384.869 | HC12: 17417.764 | HD12: 10450.658 | HE12: 3483.5527 | HF12: 91207.789 | HG12: 85683.027 | HH12: 80017.684 | HI12: 74352.342 | HJ12: 68687 | HK12: 63021.658 | HL12: 57356.316 | HM12: 51690.974 | HN12: 46025.632 | HO12: 40360.29 | HP12: 34694.948 | HQ12: 29029.606 | HR12: 23223.685 | HS12: 17417.764 | HT12: 11611.842 | HU12: 5805.9212
A14: APORTE DE SÓCIOS
A15: Aportes | B15: =SUM(C15:Z15) | C15: 2004788.2 | Y15: 1000000 | Z15: 1000000 | AB15: 1000000 | AE15: =SUM(AG15:HU15) | AG15: 0 | AH15: 0 | AI15: 0 | AJ15: 0 | AK15: 0 | AL15: 0 | AM15: 0 | AN15: 0 | AO15: 0 | AP15: 0 | AQ15: 0 | AR15: 0 | AS15: 0 | AT15: 0 | AU15: 0 | AV15: 0 | AW15: 0 | AX15: 0 | AY15: 0 | AZ15: 0 | BA15: 0 | BB15: 0 | BD15: 0 | BE15: 0 | BF15: 0 | BG15: 0 | BH15: 0 | BI15: 0 | BJ15: 0 | BK15: 0 | BL15: 0 | BM15: 0 | BN15: 0 | BO15: 0 | BP15: 0 | BQ15: 0 | BR15: 0 | BS15: 0 | BT15: 0 | BU15: 0 | BV15: 0 | BW15: 0 | BX15: 0 | BY15: 0 | BZ15: 0 | CA15: 0 | CB15: 0 | CC15: 0 | CD15: 0 | CE15: 0 | CF15: 0 | CG15: 0 | CH15: 0 | CI15: 0 | CJ15: 0 | CK15: 0 | CL15: 0 | CM15: 0 | CN15: 0 | CO15: 0 | CP15: 0 | CQ15: 0 | CR15: 0 | CS15: 0 | CT15: 0 | CU15: 0 | CV15: 0 | CW15: 0 | CX15: 0 | CY15: 0 | CZ15: 0 | DA15: 0 | DB15: 0 | DC15: 0 | DD15: 0 | DE15: 0 | DF15: 0 | DG15: 0 | DH15: 0 | DI15: 0 | DJ15: 0 | DK15: 0 | DL15: 0 | DM15: 0 | DN15: 0 | DO15: 0 | DP15: 0 | DQ15: 0 | DR15: 0 | DS15: 0 | DT15: 0 | DU15: 0 | DV15: 0 | DW15: 0 | DX15: 0 | DY15: 0 | DZ15: 0 | EA15: 0 | EB15: 0 | EC15: 0 | ED15: 0 | EE15: 0 | EF15: 0 | EG15: 0 | EH15: 0 | EI15: 0 | EJ15: 0 | EK15: 0 | EL15: 0 | EM15: 0 | EN15: 0 | EO15: 0 | EP15: 0 | EQ15: 0 | ER15: 0 | ES15: 0 | ET15: 0 | EU15: 0 | EV15: 0 | EW15: 0 | EX15: 0 | EY15: 0 | EZ15: 0 | FA15: 0 | FB15: 0 | FC15: 0 | FD15: 0 | FE15: 0 | FF15: 0 | FG15: 0 | FH15: 0 | FI15: 0 | FJ15: 0 | FK15: 0 | FL15: 0 | FM15: 0 | FN15: 0 | FO15: 0 | FP15: 0 | FQ15: 0 | FR15: 0 | FS15: 0 | FT15: 0 | FU15: 0 | FV15: 0 | FW15: 0 | FX15: 0 | FY15: 0 | FZ15: 0 | GA15: 0 | GB15: 0 | GC15: 0 | GD15: 0 | GE15: 0 | GF15: 0 | GG15: 0 | GH15: 0 | GI15: 0 | GJ15: 0 | GK15: 0 | GL15: 0 | GM15: 0 | GN15: 0 | GO15: 0 | GP15: 0 | GQ15: 0 | GR15: 0 | GS15: 0 | GT15: 0 | GU15: 0 | GV15: 0 | GW15: 0 | GX15: 0 | GY15: 0 | GZ15: 0 | HA15: 0 | HB15: 0 | HC15: 0 | HD15: 0 | HE15: 0 | HF15: 0 | HG15: 0 | HH15: 0 | HI15: 0 | HJ15: 0 | HK15: 0 | HL15: 0 | HM15: 0 | HN15: 0 | HO15: 0 | HP15: 0 | HQ15: 0 | HR15: 0 | HS15: 0 | HT15: 0 | HU15: 0
A17: RECEITA FINANCEIRA (+)
A18: Rendimento Financeiro | B18: =SUM(C18:Z18) | AB18: 12646.02 | AC18: 38113.26 | AE18: =SUM(AG18:HU18) | AG18: =IF(AC74>0, AC74*0.5%,0) | AH18: =IF(AG74>0, AG74*0.5%,0) | AI18: =IF(AH74>0, AH74*0.5%,0) | AJ18: =IF(AI74>0, AI74*0.5%,0) | AK18: =IF(AJ74>0, AJ74*0.5%,0) | AL18: =IF(AK74>0, AK74*0.5%,0) | AM18: =IF(AL74>0, AL74*0.5%,0) | AN18: =IF(AM74>0, AM74*0.5%,0) | AO18: =IF(AN74>0, AN74*0.5%,0) | ... HU18: =IF(HT74>0, HT74*0.5%,0)
A20: TOTAL RECEITAS REAL (+) | B20: =SUM(C20:W20) | C20: =SUM(C8+C9+C15+C18) | D20: =SUM(D8+D9+D15+D18) | E20: =SUM(E8+E9+E15+E18) | F20: =SUM(F8+F9+F12+F15+F18) | G20: =SUM(G8+G9+G12+G15+G18) | H20: =SUM(H8+H9+H12+H15+H18) | I20: =SUM(I8+I9+I12+I15+I18) | J20: =SUM(J8+J9+J15+J18) | K20: =SUM(K8+K9+K15+K18) | L20: =SUM(L8+L9+L15+L18) | M20: =SUM(M8+M9+M15+M18) | N20: =SUM(N8+N9+N15+N18) | O20: =SUM(O8+O9+O15+O18) | P20: =SUM(P8+P9+P15+P18) | Q20: =SUM(Q8+Q9+Q15+Q18) | ... AC20: =SUM(AC8+AC9+AC15+AC18) | AE20: =SUM(AG20:DN20) | AG20: =SUM(AG8+AG9+AG15+AG18) | AH20: =SUM(AH8+AH9+AH15+AH18) | AI20: =SUM(AI8+AI9+AI15+AI18) | AJ20: =SUM(AJ8+AJ9+AJ15+AJ18) | AK20: =SUM(AK8+AK9+AK15+AK18) | AL20: =SUM(AL8+AL9+AL15+AL18) | AM20: =SUM(AM8+AM9+AM15+AM18) | AN20: =SUM(AN8+AN9+AN15+AN18) | ... HU20: =SUM(HU8+HU9+HU15+HU18)
A21: TOTAL DE RECEITAS + PREVISÃO VENDAS | B21: =SUM(C21:W21) | C21: =C12+C20 | D21: =D12+D20 | E21: =E12+E20 | F21: =F12+F20 | G21: =G12+G20 | H21: =H12+H20 | I21: =I12+I20 | J21: =J12+J9+J18+J15+J8 | K21: =K12+K9+K18+K15+K8 | L21: =L12+L9+L18+L15+L8 | M21: =M12+M9+M18+M15+M8 | N21: =N12+N9+N18+N15+N8 | O21: =O12+O9+O18+O15+O8 | P21: =P12+P9+P18+P15+P8 | Q21: =Q12+Q9+Q18+Q15+Q8 | ... AC21: =AC12+AC9+AC18+AC15+AC8 | AE21: =SUM(AG21:DN21) | AG21: =AG12+AG9+AG18+AG15+AG8 | AH21: =AH12+AH9+AH18+AH15+AH8 | AI21: =AI12+AI9+AI18+AI15+AI8 | AJ21: =AJ12+AJ9+AJ18+AJ15+AJ8 | AK21: =AK12+AK9+AK18+AK15+AK8 | AL21: =AL12+AL9+AL18+AL15+AL8 | AM21: =AM12+AM9+AM18+AM15+AM8 | AN21: =AN12+AN9+AN18+AN15+AN8 | ... HU21: =HU12+HU9+HU18+HU15+HU8
A23: DESPESAS OPERACIONAIS
A24: DESPESAS COMERCIAIS(-)
A25: Comissões S/ Venda (Equipe Interna) | B25: =SUM(C25:AA25) | AC25: -128438.23 | AE25: =SUM(AG25:HU25) | AG25: -28685.08 | AH25: -28685.08 | AI25: -28685.08 | AJ25: -28685.08 | AK25: -28685.08 | AL25: -28685.08 | AM25: -28685.08 | AN25: -28685.08 | AO25: -28685.08 | AP25: -28685.08 | AQ25: -28685.08 | AR25: -28685.08 | AS25: -28685.08 | AT25: -28685.08 | AU25: -28685.08 | AV25: -28685.08 | AW25: -28685.08 | AX25: -28685.08 | AY25: -28685.08 | AZ25: -28685.08 | BA25: -28685.08 | BB25: -28685.08 | BC25: -28685.08 | BD25: -28685.08 | BE25: -28685.08 | BF25: -28685.08 | BG25: -28685.08 | BH25: -28685.08 | BI25: -28685.08 | BJ25: -28685.08 | BK25: -28685.08 | BL25: -28685.08 | BM25: -28685.08 | BN25: -28685.08 | BO25: -28685.08 | BP25: -28685.08 | BQ25: -28685.08 | BR25: -28685.08 | BS25: -28685.08 | BT25: -28685.08 | BU25: -28685.08 | BV25: -28685.08 | BW25: -28685.08 | BX25: -28685.08 | BY25: -28685.08 | BZ25: -28685.08 | CA25: -28685.08 | CB25: -28685.08 | CC25: -28685.08 | CD25: -28685.08 | CE25: -28685.08 | CF25: -28685.08 | CG25: -28685.08 | CH25: -28685.08 | CI25: -28685.08 | CJ25: -28685.08 | CK25: -28685.08 | CL25: -28685.08 | CM25: -28685.08 | CN25: -28685.08 | CO25: -28685.08 | CP25: -28685.08 | DL25: 0 | DM25: 0 | DN25: 0 | DO25: 0 | DP25: 0 | DQ25: 0 | DR25: 0 | DS25: 0 | DT25: 0 | DU25: 0 | DV25: 0 | DW25: 0 | DX25: 0 | DY25: 0 | DZ25: 0 | EA25: 0 | EB25: 0 | EC25: 0 | ED25: 0 | EE25: 0 | EF25: 0 | EG25: 0 | EH25: 0 | EI25: 0 | EJ25: 0 | EK25: 0 | EL25: 0 | EM25: 0 | EN25: 0 | EO25: 0 | EP25: 0 | EQ25: 0 | ER25: 0 | ES25: 0 | ET25: 0 | EU25: 0 | EV25: 0 | EW25: 0 | EX25: 0 | EY25: 0 | EZ25: 0 | FA25: 0 | FB25: 0 | FC25: 0 | FD25: 0 | FE25: 0 | FF25: 0 | FG25: 0 | FH25: 0 | FI25: 0 | FJ25: 0 | FK25: 0 | FL25: 0 | FM25: 0 | FN25: 0 | FO25: 0 | FP25: 0 | FQ25: 0 | FR25: 0 | FS25: 0 | FT25: 0 | FU25: 0 | FV25: 0 | FW25: 0 | FX25: 0 | FY25: 0 | FZ25: 0 | GA25: 0 | GB25: 0 | GC25: 0 | GD25: 0 | GE25: 0 | GF25: 0 | GG25: 0 | GH25: 0 | GI25: 0 | GJ25: 0 | GK25: 0 | GL25: 0 | GM25: 0 | GN25: 0 | GO25: 0 | GP25: 0 | GQ25: 0 | GR25: 0 | GS25: 0 | GT25: 0 | GU25: 0 | GV25: 0 | GW25: 0 | GX25: 0 | GY25: 0 | GZ25: 0 | HA25: 0 | HB25: 0 | HC25: 0 | HD25: 0 | HE25: 0 | HF25: 0 | HG25: 0 | HH25: 0 | HI25: 0 | HJ25: 0 | HK25: 0 | HL25: 0 | HM25: 0 | HN25: 0 | HO25: 0 | HP25: 0 | HQ25: 0 | HR25: 0 | HS25: 0 | HT25: 0 | HU25: 0
A26: Stand de Venda - Manutenção | B26: =SUM(C26:AA26) | W26: -34442.6 | X26: -422668.9 | Y26: -260275.15 | Z26: -364851.06 | AA26: -241871.81 | AB26: -456303.01 | AC26: =-66426.55-83395.55 | AE26: =SUM(AG26:HU26) | AG26: -55000 | AH26: -55000 | AI26: -55000 | AJ26: -55000 | AK26: -55000 | AL26: -55000 | AM26: -55000 | AN26: -55000 | AO26: -55000 | AP26: -55000 | AQ26: -55000 | AR26: -55000 | AS26: -55000 | AT26: -55000 | AU26: -55000 | AV26: -55000 | AW26: -55000 | AX26: -55000 | AY26: -55000 | AZ26: -55000 | BA26: -55000 | BB26: -55000 | BC26: -55000 | BD26: -55000 | BE26: -55000 | BF26: -55000 | BG26: -55000 | BH26: -55000 | BI26: -55000 | BJ26: -55000 | BK26: -55000 | BL26: -55000 | BM26: -55000 | BN26: -55000 | BO26: -55000 | BP26: -55000 | BQ26: 0 | BR26: 0 | BS26: 0 | BT26: 0 | BU26: 0 | BV26: 0 | BW26: 0 | BX26: 0 | BY26: 0 | BZ26: 0 | CA26: 0 | CB26: 0 | CC26: 0 | CD26: 0 | CE26: 0 | CF26: 0 | CG26: 0 | CH26: 0 | CI26: 0 | CJ26: 0 | CK26: 0 | CL26: 0 | CM26: 0 | CN26: 0 | CO26: 0 | CP26: 0 | CQ26: 0 | CR26: 0 | CS26: 0 | CT26: 0 | CU26: 0 | CV26: 0 | CW26: 0 | CX26: 0 | CY26: 0 | CZ26: 0 | DA26: 0 | DB26: 0 | DC26: 0 | DD26: 0 | DE26: 0 | DF26: 0 | DG26: 0 | DH26: 0 | DI26: 0 | DJ26: 0 | DK26: 0 | DL26: 0 | DM26: 0 | DN26: 0 | DO26: 0 | DP26: 0 | DQ26: 0 | DR26: 0 | DS26: 0 | DT26: 0 | DU26: 0 | DV26: 0 | DW26: 0 | DX26: 0 | DY26: 0 | DZ26: 0 | EA26: 0 | EB26: 0 | EC26: 0 | ED26: 0 | EE26: 0 | EF26: 0 | EG26: 0 | EH26: 0 | EI26: 0 | EJ26: 0 | EK26: 0 | EL26: 0 | EM26: 0 | EN26: 0 | EO26: 0 | EP26: 0 | EQ26: 0 | ER26: 0 | ES26: 0 | ET26: 0 | EU26: 0 | EV26: 0 | EW26: 0 | EX26: 0 | EY26: 0 | EZ26: 0 | FA26: 0 | FB26: 0 | FC26: 0 | FD26: 0 | FE26: 0 | FF26: 0 | FG26: 0 | FH26: 0 | FI26: 0 | FJ26: 0 | FK26: 0 | FL26: 0 | FM26: 0 | FN26: 0 | FO26: 0 | FP26: 0 | FQ26: 0 | FR26: 0 | FS26: 0 | FT26: 0 | FU26: 0 | FV26: 0 | FW26: 0 | FX26: 0 | FY26: 0 | FZ26: 0 | GA26: 0 | GB26: 0 | GC26: 0 | GD26: 0 | GE26: 0 | GF26: 0 | GG26: 0 | GH26: 0 | GI26: 0 | GJ26: 0 | GK26: 0 | GL26: 0 | GM26: 0 | GN26: 0 | GO26: 0 | GP26: 0 | GQ26: 0 | GR26: 0 | GS26: 0 | GT26: 0 | GU26: 0 | GV26: 0 | GW26: 0 | GX26: 0 | GY26: 0 | GZ26: 0 | HA26: 0 | HB26: 0 | HC26: 0 | HD26: 0 | HE26: 0 | HF26: 0 | HG26: 0 | HH26: 0 | HI26: 0 | HJ26: 0 | HK26: 0 | HL26: 0 | HM26: 0 | HN26: 0 | HO26: 0 | HP26: 0 | HQ26: 0 | HR26: 0 | HS26: 0 | HT26: 0 | HU26: 0
A27: Marketing | B27: =SUM(C27:AA27) | W27: -32159.95 | X27: -30740 | Y27: -18988.62 | Z27: -196816.01 | AA27: -308461.65 | AB27: -387396.3 | AC27: -264220.34 | AE27: =SUM(AG27:HU27) | AG27: -166659.27 | AH27: -166659.27 | AI27: -166659.27 | AJ27: -166659.27 | AK27: -166659.27 | AL27: -166659.27 | AM27: -166659.27 | AN27: -166659.27 | AO27: -166659.27 | AP27: -166659.27 | AQ27: -83329.635 | AR27: -83329.635 | AS27: -83329.635 | AT27: -83329.635 | AU27: -83329.635 | AV27: -83329.635 | AW27: -83329.635 | AX27: -83329.635 | AY27: -83329.635 | AZ27: -83329.635 | BA27: -83329.635 | BB27: -83329.635 | BC27: -83329.635 | BD27: -83329.635 | BE27: -83329.635 | BF27: -83329.635 | BG27: -83329.635 | BH27: -83329.635 | BI27: -83329.635 | BJ27: -83329.635 | BK27: -83329.635 | BL27: -83329.635 | BM27: -83329.635 | BN27: -83329.635 | BO27: -83329.635 | BP27: -83329.635 | BQ27: -83329.635 | BR27: -83329.635 | BS27: -83329.635 | BT27: -83329.635 | BU27: -83329.635 | BV27: -83329.635 | BW27: -83329.635 | BX27: -83329.635 | BY27: -83329.635 | BZ27: -83329.635 | CA27: -83329.635 | CB27: -83329.635 | CC27: -83329.635 | CD27: -83329.635 | CE27: -83329.635 | CF27: -83329.635 | CG27: -83329.635 | CH27: -83329.635 | CI27: -83329.635 | CJ27: -83329.635 | CK27: -83329.635 | CL27: -83329.635 | CM27: -83329.635 | CN27: -83329.635 | CO27: -83329.635 | CP27: -83329.635 | CQ27: -83329.635 | CR27: -83329.635 | CS27: -83329.635 | CT27: -83329.635 | CU27: -83329.635 | CV27: -83329.635 | CW27: -83329.635 | CX27: -83329.635 | CY27: -83329.635 | CZ27: -83329.635 | DA27: -83329.635 | DB27: -83329.635 | DC27: -83329.635 | DD27: -83329.635 | DE27: -83329.635 | DF27: -83329.635 | DG27: -83329.635 | DH27: -83329.635 | DI27: -83329.635 | DJ27: -83329.635 | DK27: -83329.635 | DL27: -83329.635 | DM27: -83329.635 | DN27: -83329.635 | DO27: -83329.635 | DP27: -83329.635 | DQ27: -83329.635 | DR27: -83329.635 | DS27: 0 | DT27: 0 | DU27: 0 | DV27: 0 | DW27: 0 | DX27: 0 | DY27: 0 | DZ27: 0 | EA27: 0 | EC27: 0 | ED27: 0 | EE27: 0 | EF27: 0 | EG27: 0 | EH27: 0 | EI27: 0 | EJ27: 0 | EK27: 0 | EL27: 0 | EM27: 0 | EN27: 0 | EO27: 0 | EP27: 0 | EQ27: 0 | ER27: 0 | ES27: 0 | ET27: 0 | EU27: 0 | EV27: 0 | EW27: 0 | EX27: 0 | EY27: 0 | EZ27: 0 | FA27: 0 | FB27: 0 | FC27: 0 | FD27: 0 | FE27: 0 | FF27: 0 | FG27: 0 | FH27: 0 | FI27: 0 | FJ27: 0 | FK27: 0 | FL27: 0 | FM27: 0 | FN27: 0 | FO27: 0 | FP27: 0 | FQ27: 0 | FR27: 0 | FS27: 0 | FT27: 0 | FU27: 0 | FV27: 0 | FW27: 0 | FX27: 0 | FY27: 0 | FZ27: 0 | GA27: 0 | GB27: 0 | GC27: 0 | GD27: 0 | GE27: 0 | GF27: 0 | GG27: 0 | GH27: 0 | GI27: 0 | GJ27: 0 | GK27: 0 | GL27: 0 | GM27: 0 | GN27: 0 | GO27: 0 | GP27: 0 | GQ27: 0 | GR27: 0 | GS27: 0 | GT27: 0 | GU27: 0 | GV27: 0 | GW27: 0 | GX27: 0 | GY27: 0 | GZ27: 0 | HA27: 0 | HB27: 0 | HC27: 0 | HD27: 0 | HE27: 0 | HF27: 0 | HG27: 0 | HH27: 0 | HI27: 0 | HJ27: 0 | HK27: 0 | HL27: 0 | HM27: 0 | HN27: 0 | HO27: 0 | HP27: 0 | HQ27: 0 | HR27: 0 | HS27: 0 | HT27: 0 | HU27: 0
A28: Salário Fixo | B28: =SUM(C28:AA28) | AC28: -228.84 | AE28: =SUM(AG28:HU28) | DL28: 0 | DM28: 0 | DN28: 0 | DO28: 0 | DP28: 0 | DQ28: 0 | DR28: 0 | DS28: 0 | DT28: 0 | DU28: 0 | DV28: 0 | DW28: 0 | DX28: 0 | DY28: 0 | DZ28: 0 | EA28: 0 | EB28: 0 | EC28: 0 | ED28: 0 | EE28: 0 | EF28: 0 | EG28: 0 | EH28: 0 | EI28: 0 | EJ28: 0 | EK28: 0 | EL28: 0 | EM28: 0 | EN28: 0 | EO28: 0 | EP28: 0 | EQ28: 0 | ER28: 0 | ES28: 0 | ET28: 0 | EU28: 0 | EV28: 0 | EW28: 0 | EX28: 0 | EY28: 0 | EZ28: 0 | FA28: 0 | FB28: 0 | FC28: 0 | FD28: 0 | FE28: 0 | FF28: 0 | FG28: 0 | FH28: 0 | FI28: 0 | FJ28: 0 | FK28: 0 | FL28: 0 | FM28: 0 | FN28: 0 | FO28: 0 | FP28: 0 | FQ28: 0 | FR28: 0 | FS28: 0 | FT28: 0 | FU28: 0 | FV28: 0 | FW28: 0 | FX28: 0 | FY28: 0 | FZ28: 0 | GA28: 0 | GB28: 0 | GC28: 0 | GD28: 0 | GE28: 0 | GF28: 0 | GG28: 0 | GH28: 0 | GI28: 0 | GJ28: 0 | GK28: 0 | GL28: 0 | GM28: 0 | GN28: 0 | GO28: 0 | GP28: 0 | GQ28: 0 | GR28: 0 | GS28: 0 | GT28: 0 | GU28: 0 | GV28: 0 | GW28: 0 | GX28: 0 | GY28: 0 | GZ28: 0 | HA28: 0 | HB28: 0 | HC28: 0 | HD28: 0 | HE28: 0 | HF28: 0 | HG28: 0 | HH28: 0 | HI28: 0 | HJ28: 0 | HK28: 0 | HL28: 0 | HM28: 0 | HN28: 0 | HO28: 0 | HP28: 0 | HQ28: 0 | HR28: 0 | HS28: 0 | HT28: 0 | HU28: 0
A29: Subtotal | B29: =SUM(C29:W29) | C29: =SUM(C25:C28) | D29: =SUM(D25:D28) | E29: =SUM(E25:E28) | F29: =SUM(F25:F28) | G29: =SUM(G25:G28) | H29: =SUM(H25:H28) | I29: =SUM(I25:I28) | J29: =SUM(J25:J28) | ... AC29: =SUM(AC25:AC28) | AE29: =SUM(AG29:DN29) | AG29: =SUM(AG25:AG28) | AH29: =SUM(AH25:AH28) | AI29: =SUM(AI25:AI28) | AJ29: =SUM(AJ25:AJ28) | AK29: =SUM(AK25:AK28) | AL29: =SUM(AL25:AL28) | AM29: =SUM(AM25:AM28) | AN29: =SUM(AN25:AN28) | ... HU29: =SUM(HU25:HU28)
A31: ITBI + IPTU ESTOQUE(-)
A32: ITBI | B32: =SUM(C32:X32) | AE32: =SUM(AG32:HU32) | AG32: 0 | AJ32: 0 | AK32: 0 | AL32: 0 | AM32: 0 | AN32: 0 | AO32: 0 | AP32: 0 | AQ32: 0 | AR32: 0 | AS32: 0 | AT32: 0 | AU32: 0 | AV32: 0 | AW32: 0 | AX32: 0 | AY32: 0 | AZ32: 0 | BA32: 0 | BB32: 0 | BC32: 0 | BD32: 0 | BE32: 0 | BF32: 0 | BG32: 0 | BH32: 0 | BI32: 0 | BJ32: 0 | BK32: 0 | BL32: 0 | BM32: 0 | BN32: 0 | BO32: 0 | BP32: 0 | BQ32: 0 | BR32: 0 | BS32: 0 | BT32: 0 | BU32: 0 | BV32: 0 | BW32: 0 | BX32: 0 | BY32: 0 | BZ32: 0 | CA32: 0 | CB32: 0 | CC32: 0 | CD32: 0 | CE32: 0 | CF32: 0 | CG32: 0 | CH32: 0 | CI32: 0 | CJ32: 0 | CK32: 0 | CL32: 0 | CM32: 0 | CN32: 0 | CO32: 0 | CP32: 0 | CQ32: 0 | CR32: 0 | CS32: 0 | CT32: 0 | CU32: 0 | CV32: 0 | CW32: 0 | CX32: 0 | CY32: 0 | CZ32: 0 | DA32: 0 | DB32: 0 | DC32: 0 | DD32: 0 | DE32: 0 | DF32: 0 | DG32: 0 | DH32: 0 | DI32: 0 | DJ32: 0 | DL32: 0 | DM32: 0 | DN32: 0 | DO32: 0 | DP32: 0 | DQ32: 0 | DR32: 0 | DS32: 0 | DT32: 0 | DU32: 0 | DV32: 0 | DW32: 0 | DX32: 0 | DY32: 0 | DZ32: 0 | EA32: 0 | EB32: 0 | EC32: 0 | ED32: 0 | EE32: 0 | EF32: 0 | EG32: 0 | EH32: 0 | EI32: 0 | EJ32: 0 | EK32: 0 | EL32: 0 | EM32: 0 | EN32: 0 | EO32: 0 | EP32: 0 | EQ32: 0 | ER32: 0 | ES32: 0 | ET32: 0 | EU32: 0 | EV32: 0 | EW32: 0 | EX32: 0 | EY32: 0 | EZ32: 0 | FA32: 0 | FB32: 0 | FC32: 0 | FD32: 0 | FE32: 0 | FF32: 0 | FG32: 0 | FH32: 0 | FI32: 0 | FJ32: 0 | FK32: 0 | FL32: 0 | FM32: 0 | FN32: 0 | FO32: 0 | FP32: 0 | FQ32: 0 | FR32: 0 | FS32: 0 | FT32: 0 | FU32: 0 | FV32: 0 | FW32: 0 | FX32: 0 | FY32: 0 | FZ32: 0 | GA32: 0 | GB32: 0 | GC32: 0 | GD32: 0 | GE32: 0 | GF32: 0 | GG32: 0 | GH32: 0 | GI32: 0 | GJ32: 0 | GK32: 0 | GL32: 0 | GM32: 0 | GN32: 0 | GO32: 0 | GP32: 0 | GQ32: 0 | GR32: 0 | GS32: 0 | GT32: 0 | GU32: 0 | GV32: 0 | GW32: 0 | GX32: 0 | GY32: 0 | GZ32: 0 | HA32: 0 | HB32: 0 | HC32: 0 | HD32: 0 | HE32: 0 | HF32: 0 | HG32: 0 | HH32: 0 | HI32: 0 | HJ32: 0 | HK32: 0 | HL32: 0 | HM32: 0 | HN32: 0 | HO32: 0 | HP32: 0 | HQ32: 0 | HR32: 0 | HS32: 0 | HT32: 0 | HU32: 0
A33: IPTU Estoque | B33: =SUM(C33:X33) | AE33: =SUM(AG33:HU33) | AG33: 0 | AH33: 0 | AI33: 0 | AJ33: 0 | AK33: 0 | AL33: 0 | AM33: 0 | AN33: 0 | AO33: 0 | AP33: 0 | AQ33: 0 | AR33: 0 | AS33: 0 | AT33: 0 | AU33: 0 | AV33: 0 | AW33: 0 | AX33: 0 | AY33: 0 | AZ33: 0 | BA33: 0 | BB33: 0 | BC33: 0 | BD33: 0 | BE33: 0 | BF33: 0 | BG33: 0 | BH33: 0 | BI33: 0 | BJ33: 0 | BK33: 0 | BL33: 0 | BM33: 0 | BN33: 0 | BO33: 0 | BP33: 0 | BQ33: 0 | BR33: 0 | BS33: 0 | BT33: 0 | BU33: 0 | BV33: 0 | BW33: 0 | BX33: 0 | BY33: 0 | BZ33: 0 | CA33: 0 | CB33: 0 | CC33: 0 | CD33: 0 | CE33: 0 | CF33: 0 | CG33: 0 | CH33: 0 | CI33: 0 | CJ33: 0 | CK33: 0 | CL33: 0 | CM33: 0 | CN33: 0 | CO33: 0 | CP33: 0 | CQ33: 0 | CR33: 0 | CS33: 0 | CT33: 0 | CU33: 0 | CV33: 0 | CW33: 0 | CX33: 0 | CY33: 0 | CZ33: 0 | DA33: 0 | DB33: 0 | DC33: 0 | DD33: 0 | DE33: 0 | DF33: 0 | DG33: 0 | DH33: 0 | DI33: 0 | DJ33: 0 | DL33: 0 | DM33: 0 | DN33: 0 | DO33: 0 | DP33: 0 | DQ33: 0 | DR33: 0 | DS33: 0 | DT33: 0 | DU33: 0 | DV33: 0 | DW33: 0 | DX33: 0 | DY33: 0 | DZ33: 0 | EA33: 0 | EB33: 0 | EC33: 0 | ED33: 0 | EE33: 0 | EF33: 0 | EG33: 0 | EH33: 0 | EI33: 0 | EJ33: 0 | EK33: 0 | EL33: 0 | EM33: 0 | EN33: 0 | EO33: 0 | EP33: 0 | EQ33: 0 | ER33: 0 | ES33: 0 | ET33: 0 | EU33: 0 | EV33: 0 | EW33: 0 | EX33: 0 | EY33: 0 | EZ33: 0 | FA33: 0 | FB33: 0 | FC33: 0 | FD33: 0 | FE33: 0 | FF33: 0 | FG33: 0 | FH33: 0 | FI33: 0 | FJ33: 0 | FK33: 0 | FL33: 0 | FM33: 0 | FN33: 0 | FO33: 0 | FP33: 0 | FQ33: 0 | FR33: 0 | FS33: 0 | FT33: 0 | FU33: 0 | FV33: 0 | FW33: 0 | FX33: 0 | FY33: 0 | FZ33: 0 | GA33: 0 | GB33: 0 | GC33: 0 | GD33: 0 | GE33: 0 | GF33: 0 | GG33: 0 | GH33: 0 | GI33: 0 | GJ33: 0 | GK33: 0 | GL33: 0 | GM33: 0 | GN33: 0 | GO33: 0 | GP33: 0 | GQ33: 0 | GR33: 0 | GS33: 0 | GT33: 0 | GU33: 0 | GV33: 0 | GW33: 0 | GX33: 0 | GY33: 0 | GZ33: 0 | HA33: 0 | HB33: 0 | HC33: 0 | HD33: 0 | HE33: 0 | HF33: 0 | HG33: 0 | HH33: 0 | HI33: 0 | HJ33: 0 | HK33: 0 | HL33: 0 | HM33: 0 | HN33: 0 | HO33: 0 | HP33: 0 | HQ33: 0 | HR33: 0 | HS33: 0 | HT33: 0 | HU33: 0
A34: Subtotal | B34: =SUM(C34:W34) | C34: =SUM(C32:C33) | D34: =SUM(D32:D33) | E34: =SUM(E32:E33) | F34: =SUM(F32:F33) | G34: =SUM(G32:G33) | H34: =SUM(H32:H33) | I34: =SUM(I32:I33) | J34: =SUM(J32:J33) | ... R34: =SUM(R32:R33) | T34: =SUM(T32:T33) | U34: =SUM(U32:U33) | V34: =SUM(V32:V33) | W34: =SUM(W32:W33) | X34: =SUM(X32:X33) | Y34: =SUM(Y32:Y33) | Z34: =SUM(Z32:Z33) | AA34: =SUM(AA32:AA33) | ... AC34: =SUM(AC32:AC33) | AE34: =SUM(AG34:DU34) | AG34: =SUM(AG32:AG33) | AH34: =SUM(AH32:AH33) | AI34: =SUM(AI32:AI33) | AJ34: =SUM(AJ32:AJ33) | AK34: =SUM(AK32:AK33) | AL34: =SUM(AL32:AL33) | AM34: =SUM(AM32:AM33) | AN34: =SUM(AN32:AN33) | ... DJ34: =SUM(DJ32:DJ33) | DL34: =SUM(DL32:DL33) | DM34: =SUM(DM32:DM33) | DN34: =SUM(DN32:DN33) | DO34: =SUM(DO32:DO33) | DP34: =SUM(DP32:DP33) | DQ34: =SUM(DQ32:DQ33) | DR34: =SUM(DR32:DR33) | DS34: =SUM(DS32:DS33) | ... HU34: =SUM(HU32:HU33)
A36: DESPESAS DE OBRA (-) | Projeto (-)
A37: OBRA - (PREVISTO VIABIL) | B37: =SUM(C37:AA37) | AC37: -124003.31 | AE37: =SUM(AG37:HU37) | AG37: 0 | AH37: -1100768.2 | AI37: -1273700.1 | AJ37: -1264677.5 | AK37: -1137609.4 | AL37: -1140768.2 | AM37: -1100768.2 | AN37: -1452653.1 | AO37: -1317312.8 | AP37: -2156423 | AQ37: -2409058.3 | AR37: -2950419.7 | AS37: -3103805.5 | AT37: -3076737.4 | AU37: -1578970.8 | AV37: -1227085.9 | AW37: -1001518.6 | AX37: -2769965.9 | AY37: -4015097.2 | AZ37: -6198588.2 | BA37: -5945952.9 | BB37: -5846703.3 | BC37: -5855726 | BD37: -6640700.1 | BE37: -6496337 | BF37: -3717348.4 | BG37: -1046632.1 | BH37: -1046632.1 | BI37: -1046632.1 | BJ37: -1181972.4 | BK37: -1181972.4 | BL37: -1506789.3 | BM37: -1569948.1 | BN37: -2048150.7 | BO37: -2048150.7 | BP37: -1578970.8 | BQ37: -1732356.5 | BR37: -54512.651 | BS37: -54512.651 | BT37: -54512.651 | BU37: -54512.651 | BV37: -54512.651 | BW37: -54512.651 | BX37: -54512.651 | BY37: -54512.651 | BZ37: -54512.651 | CA37: -54512.651 | CB37: -54512.651 | CC37: -54512.651 | CD37: -54512.651 | CE37: -54512.651 | CF37: -54512.651 | CG37: -54512.651 | CH37: -54512.651 | CI37: -54512.651 | CJ37: -54512.651 | CK37: -54512.651 | CL37: -54512.651 | CM37: -54512.651 | CN37: -54512.651 | CO37: -54512.651 | CP37: 0 | CQ37: 0 | CR37: 0 | CS37: 0 | CT37: 0 | CU37: 0 | CV37: 0 | CW37: 0 | CX37: 0 | CY37: 0 | CZ37: 0 | DA37: 0 | DB37: 0 | DC37: 0 | DD37: 0 | DE37: 0 | DF37: 0 | DG37: 0 | DH37: 0 | DI37: 0 | DJ37: 0 | DK37: 0 | DL37: 0 | DM37: 0 | DN37: 0 | DO37: 0 | DP37: 0 | DQ37: 0 | DR37: 0 | DS37: 0 | DT37: 0 | DU37: 0 | DV37: 0 | DW37: 0 | DX37: 0 | DY37: 0 | DZ37: 0 | EA37: 0 | EB37: 0 | EC37: 0 | ED37: 0 | EE37: 0 | EF37: 0 | EG37: 0 | EH37: 0 | EI37: 0 | EJ37: 0 | EK37: 0 | EL37: 0 | EM37: 0 | EN37: 0 | EO37: 0 | EP37: 0 | EQ37: 0 | ER37: 0 | ES37: 0 | ET37: 0 | EU37: 0 | EV37: 0 | EW37: 0 | EX37: 0 | EY37: 0 | EZ37: 0 | FA37: 0 | FB37: 0 | FC37: 0 | FD37: 0 | FE37: 0 | FF37: 0 | FG37: 0 | FH37: 0 | FI37: 0 | FJ37: 0 | FK37: 0 | FL37: 0 | FM37: 0 | FN37: 0 | FO37: 0 | FP37: 0 | FQ37: 0 | FR37: 0 | FS37: 0 | FT37: 0 | FU37: 0 | FV37: 0 | FW37: 0 | FX37: 0 | FY37: 0 | FZ37: 0 | GA37: 0 | GB37: 0 | GC37: 0 | GD37: 0 | GE37: 0 | GF37: 0 | GG37: 0 | GH37: 0 | GI37: 0 | GJ37: 0 | GK37: 0 | GL37: 0 | GM37: 0 | GN37: 0 | GO37: 0 | GP37: 0 | GQ37: 0 | GR37: 0 | GS37: 0 | GT37: 0 | GU37: 0 | GV37: 0 | GW37: 0 | GX37: 0 | GY37: 0 | GZ37: 0 | HA37: 0 | HB37: 0 | HC37: 0 | HD37: 0 | HE37: 0 | HF37: 0 | HG37: 0 | HH37: 0 | HI37: 0 | HJ37: 0 | HK37: 0 | HL37: 0 | HM37: 0 | HN37: 0 | HO37: 0 | HP37: 0 | HQ37: 0 | HR37: 0 | HS37: 0 | HT37: 0 | HU37: 0
A38: CONTRAPARTIDA SAAE | AE38: =SUM(AG38:HU38) | AG38: 0 | AH38: 0 | AI38: 0 | AJ38: 0 | AK38: 0 | AL38: 0 | AM38: 0 | AN38: 0 | AO38: 0 | AP38: 0 | AQ38: 0 | AR38: 0 | AS38: 0 | AT38: 0 | AU38: 0 | AV38: 0 | AW38: 0 | AX38: 0 | AY38: -66666.667 | AZ38: -66666.667 | BA38: -66666.667 | BB38: -66666.667 | BC38: -66666.667 | BD38: -66666.667 | BE38: -66666.667 | BF38: -66666.667 | BG38: -66666.667 | BH38: -66666.667 | BI38: -66666.667 | BJ38: -66666.667 | BK38: -66666.667 | BL38: -66666.667 | BM38: -66666.667 | BN38: -66666.667 | BO38: -66666.667 | BP38: -66666.667 | BQ38: 0 | BR38: 0 | BS38: 0 | BT38: 0 | BU38: 0 | BV38: 0 | BW38: 0 | BX38: 0 | BY38: 0 | BZ38: 0 | CA38: 0 | CB38: 0 | CC38: 0 | CD38: 0 | CE38: 0 | CF38: 0 | CG38: 0 | CH38: 0 | CI38: 0 | CJ38: 0 | CK38: 0 | CL38: 0 | CM38: 0 | CN38: 0 | CO38: 0 | CP38: 0 | CQ38: 0 | CR38: 0 | CS38: 0 | CT38: 0 | CU38: 0 | CV38: 0 | CW38: 0 | CX38: 0 | CY38: 0 | CZ38: 0 | DA38: 0 | DB38: 0 | DC38: 0 | DD38: 0 | DE38: 0 | DF38: 0 | DG38: 0 | DH38: 0 | DI38: 0 | DJ38: 0 | DK38: 0 | DL38: 0 | DM38: 0 | DN38: 0 | DO38: 0 | DP38: 0 | DQ38: 0 | DR38: 0 | DS38: 0 | DT38: 0 | DU38: 0 | DV38: 0 | DW38: 0 | DX38: 0 | DY38: 0 | DZ38: 0 | EA38: 0 | EB38: 0 | EC38: 0 | ED38: 0 | EE38: 0 | EF38: 0 | EG38: 0 | EH38: 0 | EI38: 0 | EJ38: 0 | EK38: 0 | EL38: 0 | EM38: 0 | EN38: 0 | EO38: 0 | EP38: 0 | EQ38: 0 | ER38: 0 | ES38: 0 | ET38: 0 | EU38: 0 | EV38: 0 | EW38: 0 | EX38: 0 | EY38: 0 | EZ38: 0 | FA38: 0 | FB38: 0 | FC38: 0 | FD38: 0 | FE38: 0 | FF38: 0 | FG38: 0 | FH38: 0 | FI38: 0 | FJ38: 0 | FK38: 0 | FL38: 0 | FM38: 0 | FN38: 0 | FO38: 0 | FP38: 0 | FQ38: 0 | FR38: 0 | FS38: 0 | FT38: 0 | FU38: 0 | FV38: 0 | FW38: 0 | FX38: 0 | FY38: 0 | FZ38: 0 | GA38: 0 | GB38: 0 | GC38: 0 | GD38: 0 | GE38: 0 | GF38: 0 | GG38: 0 | GH38: 0 | GI38: 0 | GJ38: 0 | GK38: 0 | GL38: 0 | GM38: 0 | GN38: 0 | GO38: 0 | GP38: 0 | GQ38: 0 | GR38: 0 | GS38: 0 | GT38: 0 | GU38: 0 | GV38: 0 | GW38: 0 | GX38: 0 | GY38: 0 | GZ38: 0 | HA38: 0 | HB38: 0 | HC38: 0 | HD38: 0 | HE38: 0 | HF38: 0 | HG38: 0 | HH38: 0 | HI38: 0 | HJ38: 0 | HK38: 0 | HL38: 0 | HM38: 0 | HN38: 0 | HO38: 0 | HP38: 0 | HQ38: 0 | HR38: 0 | HS38: 0 | HT38: 0 | HU38: 0
A40: INCORPORAÇÃO (-)
A41: Incorporação | B41: =SUM(C41:X41) | C41: -22569.84 | D41: -66761.36 | E41: -22685 | F41: -22753.06 | G41: -22784.91 | H41: -25995.64 | I41: -23082.07 | J41: -23105.15 | K41: -28144.43 | L41: -28223.13 | M41: -28269.57 | N41: -28285.85 | O41: -30358.04 | P41: -28421.11 | Q41: -51733.24 | R41: -57539.95 | S41: -30362.5 | T41: -56077.16 | U41: -30362.5 | V41: -98850 | W41: -36362.5 | X41: -645250.94 | Y41: -280557.39 | Z41: -29760.76 | AA41: =(-184611.43)+-24760.76 | AB41: -90439.16 | AC41: =-49101.24-49521.52 | AE41: =SUM(AG41:HU41) | AG41: -33000 | AH41: -33000 | AI41: -33000 | AJ41: -33000 | AK41: -8000 | AL41: -8000 | AM41: -8000 | AN41: -8000 | AO41: -8000 | AP41: -8000 | AQ41: -8000 | AR41: -8000 | AS41: -8000 | AT41: -8000 | AU41: -8000 | AV41: -8000 | AW41: -8000 | AX41: -8000 | AY41: -8000 | AZ41: -8000 | BA41: -8000 | BB41: -8000 | BC41: -8000 | BD41: -8000 | BE41: -8000 | BF41: -8000 | BG41: -8000 | BH41: -8000 | BI41: -8000 | BJ41: -8000 | BK41: -8000 | BL41: -8000 | BM41: -8000 | BN41: -3000 | BO41: -3000 | BP41: -3000 | BQ41: -3000 | BR41: -3000 | DY41: 0 | DZ41: 0 | EA41: 0 | EB41: 0 | EC41: 0 | ED41: 0 | EE41: 0 | EF41: 0 | EG41: 0 | EH41: 0 | EI41: 0 | EJ41: 0 | EK41: 0 | EL41: 0 | EM41: 0 | EN41: 0 | EO41: 0 | EP41: 0 | EQ41: 0 | ER41: 0 | ES41: 0 | ET41: 0 | EU41: 0 | EV41: 0 | EW41: 0 | EX41: 0 | EY41: 0 | EZ41: 0 | FA41: 0 | FB41: 0 | FC41: 0 | FD41: 0 | FE41: 0 | FF41: 0 | FG41: 0 | FH41: 0 | FI41: 0 | FJ41: 0 | FK41: 0 | FL41: 0 | FM41: 0 | FN41: 0 | FO41: 0 | FP41: 0 | FQ41: 0 | FR41: 0 | FS41: 0 | FT41: 0 | FU41: 0 | FV41: 0 | FW41: 0 | FX41: 0 | FY41: 0 | FZ41: 0 | GA41: 0 | GB41: 0 | GC41: 0 | GD41: 0 | GE41: 0 | GF41: 0 | GG41: 0 | GH41: 0 | GI41: 0 | GJ41: 0 | GK41: 0 | GL41: 0 | GM41: 0 | GN41: 0 | GO41: 0 | GP41: 0 | GQ41: 0 | GR41: 0 | GS41: 0 | GT41: 0 | GU41: 0 | GV41: 0 | GW41: 0 | GX41: 0 | GY41: 0 | GZ41: 0 | HA41: 0 | HB41: 0 | HC41: 0 | HD41: 0 | HE41: 0 | HF41: 0 | HG41: 0 | HH41: 0 | HI41: 0 | HJ41: 0 | HK41: 0 | HL41: 0 | HM41: 0 | HN41: 0 | HO41: 0 | HP41: 0 | HQ41: 0 | HR41: 0 | HS41: 0 | HT41: 0 | HU41: 0
A42: Gerenciamento | AE42: =SUM(AG42:HU42) | AG42: -8000 | AH42: -8000 | AI42: -8000 | AJ42: -8000 | AK42: -8000 | AL42: -8000 | AM42: -8000 | AN42: -8000 | AO42: -8000 | AP42: -8000 | AQ42: -8000 | AR42: -8000 | AS42: -8000 | AT42: -8000 | AU42: -8000 | AV42: -8000 | AW42: -8000 | AX42: -8000 | AY42: -8000 | AZ42: -8000 | BA42: -8000 | BB42: -8000 | BC42: -8000 | BD42: -8000 | BE42: -8000 | BF42: -8000 | BG42: -8000 | BH42: -8000 | BI42: -8000 | BJ42: -8000 | BK42: -8000 | BL42: -8000 | BM42: -8000 | BN42: -8000 | BO42: -8000 | BP42: -8000 | BQ42: -8000 | BR42: -8000 | BS42: -8000 | BT42: -8000 | BU42: -8000 | BV42: -8000 | BW42: -8000 | BX42: -8000 | BY42: -8000 | BZ42: -8000 | CA42: -8000 | CB42: -8000 | CC42: -8000 | CD42: -8000 | CE42: -8000 | CF42: -8000 | CG42: -8000 | CH42: -8000 | CI42: -8000 | CJ42: -8000 | CK42: -8000 | CL42: -8000 | CM42: -8000 | CN42: -8000 | DY42: 0 | DZ42: 0 | EA42: 0 | EB42: 0 | EC42: 0 | ED42: 0 | EE42: 0 | EF42: 0 | EG42: 0 | EH42: 0 | EI42: 0 | EJ42: 0 | EK42: 0 | EL42: 0 | EM42: 0 | EN42: 0 | EO42: 0 | EP42: 0 | EQ42: 0 | ER42: 0 | ES42: 0 | ET42: 0 | EU42: 0 | EV42: 0 | EW42: 0 | EX42: 0 | EY42: 0 | EZ42: 0 | FA42: 0 | FB42: 0 | FC42: 0 | FD42: 0 | FE42: 0 | FF42: 0 | FG42: 0 | FH42: 0 | FI42: 0 | FJ42: 0 | FK42: 0 | FL42: 0 | FM42: 0 | FN42: 0 | FO42: 0 | FP42: 0 | FQ42: 0 | FR42: 0 | FS42: 0 | FT42: 0 | FU42: 0 | FV42: 0 | FW42: 0 | FX42: 0 | FY42: 0 | FZ42: 0 | GA42: 0 | GB42: 0 | GC42: 0 | GD42: 0 | GE42: 0 | GF42: 0 | GG42: 0 | GH42: 0 | GI42: 0 | GJ42: 0 | GK42: 0 | GL42: 0 | GM42: 0 | GN42: 0 | GO42: 0 | GP42: 0 | GQ42: 0 | GR42: 0 | GS42: 0 | GT42: 0 | GU42: 0 | GV42: 0 | GW42: 0 | GX42: 0 | GY42: 0 | GZ42: 0 | HA42: 0 | HB42: 0 | HC42: 0 | HD42: 0 | HE42: 0 | HF42: 0 | HG42: 0 | HH42: 0 | HI42: 0 | HJ42: 0 | HK42: 0 | HL42: 0 | HM42: 0 | HN42: 0 | HO42: 0 | HP42: 0 | HQ42: 0 | HR42: 0 | HS42: 0 | HT42: 0 | HU42: 0
A44: DESPESAS JÚRIDICAS (-)
A45: Despesas juridicas | B45: =SUM(C45:X45) | AE45: =SUM(AG45:HU45) | AG45: 0 | AH45: 0 | AI45: 0 | AJ45: 0 | AK45: 0 | AL45: 0 | AM45: 0 | AN45: 0 | AO45: 0 | AP45: 0 | AQ45: 0 | AR45: 0 | AS45: 0 | AT45: 0 | AU45: 0 | AV45: 0 | AW45: 0 | AX45: 0 | AY45: 0 | AZ45: 0 | BA45: 0 | BB45: 0 | BC45: 0 | BD45: 0 | BE45: 0 | BF45: 0 | BG45: 0 | BH45: 0 | BI45: 0 | BJ45: 0 | BK45: 0 | BL45: 0 | BM45: 0 | BN45: 0 | BO45: 0 | BP45: 0 | BQ45: 0 | BR45: 0 | BS45: 0 | BT45: 0 | BU45: 0 | BV45: 0 | BW45: 0 | BX45: 0 | BY45: 0 | BZ45: 0 | CA45: 0 | CB45: 0 | CC45: 0 | CD45: 0 | CE45: 0 | CF45: 0 | CG45: 0 | CH45: 0 | CI45: 0 | CJ45: 0 | CK45: 0 | CL45: 0 | CM45: 0 | CN45: 0 | CO45: 0 | CP45: 0 | CQ45: 0 | CR45: 0 | CS45: 0 | CT45: 0 | CU45: 0 | CV45: 0 | CW45: 0 | CX45: 0 | CY45: 0 | CZ45: 0 | DA45: 0 | DB45: 0 | DC45: 0 | DD45: 0 | DE45: 0 | DF45: 0 | DG45: 0 | DH45: 0 | DI45: 0 | DJ45: 0 | DK45: 0 | DL45: 0 | DM45: 0 | DN45: 0 | DO45: 0 | DP45: 0 | DQ45: 0 | DR45: 0 | DS45: 0 | DT45: 0 | DU45: 0 | DV45: 0 | DW45: 0 | DX45: 0 | DY45: 0 | DZ45: 0 | EA45: 0 | EB45: 0 | EC45: 0 | ED45: 0 | EE45: 0 | EF45: 0 | EG45: 0 | EH45: 0 | EI45: 0 | EJ45: 0 | EK45: 0 | EL45: 0 | EM45: 0 | EN45: 0 | EO45: 0 | EP45: 0 | EQ45: 0 | ER45: 0 | ES45: 0 | ET45: 0 | EU45: 0 | EV45: 0 | EW45: 0 | EX45: 0 | EY45: 0 | EZ45: 0 | FA45: 0 | FB45: 0 | FC45: 0 | FD45: 0 | FE45: 0 | FF45: 0 | FG45: 0 | FH45: 0 | FI45: 0 | FJ45: 0 | FK45: 0 | FL45: 0 | FM45: 0 | FN45: 0 | FO45: 0 | FP45: 0 | FQ45: 0 | FR45: 0 | FS45: 0 | FT45: 0 | FU45: 0 | FV45: 0 | FW45: 0 | FX45: 0 | FY45: 0 | FZ45: 0 | GA45: 0 | GB45: 0 | GC45: 0 | GD45: 0 | GE45: 0 | GF45: 0 | GG45: 0 | GH45: 0 | GI45: 0 | GJ45: 0 | GK45: 0 | GL45: 0 | GM45: 0 | GN45: 0 | GO45: 0 | GP45: 0 | GQ45: 0 | GR45: 0 | GS45: 0 | GT45: 0 | GU45: 0 | GV45: 0 | GW45: 0 | GX45: 0 | GY45: 0 | GZ45: 0 | HA45: 0 | HB45: 0 | HC45: 0 | HD45: 0 | HE45: 0 | HF45: 0 | HG45: 0 | HH45: 0 | HI45: 0 | HJ45: 0 | HK45: 0 | HL45: 0 | HM45: 0 | HN45: 0 | HO45: 0 | HP45: 0 | HQ45: 0 | HR45: 0 | HS45: 0 | HT45: 0 | HU45: 0
A47: OUTRAS DESPESAS (-)
A48: Outras Despesas (adm) | B48: =SUM(C48:X48) | L48: -1243.93 | O48: -339 | V48: -389 | W48: 0 | X48: -4 | Y48: -1155.21 | Z48: -148.25 | AA48: -344.9 | AB48: -459.58 | AC48: =-26826.58-250 | AE48: =SUM(AG48:HU48) | AG48: -11000 | AH48: -11000 | AI48: -11000 | AJ48: -11000 | AK48: -11000 | AL48: -11000 | AM48: -11000 | AN48: -11000 | AO48: -11000 | AP48: -11000 | AQ48: -11000 | AR48: -11000 | AS48: -11000 | AT48: -11000 | AU48: -11000 | AV48: -11000 | AW48: -11000 | AX48: -11000 | AY48: -11000 | AZ48: -11000 | BA48: -11000 | BB48: -11000 | BC48: -11000 | BD48: -11000 | BE48: -11000 | BF48: -11000 | BG48: -11000 | BH48: -11000 | BI48: -11000 | BJ48: -11000 | BK48: -11000 | BL48: -11000 | BM48: -11000 | BN48: -11000 | BO48: -11000 | BP48: -11000
A50: TOTAL DE DESPESAS OPERACIONAIS (-) | B50: =SUM(C50:W50) | C50: =C48+C45+C41+C37+C34+C29 | D50: =D48+D45+D41+D37+D34+D29 | E50: =E48+E45+E41+E37+E34+E29 | F50: =F48+F45+F41+F37+F34+F29 | G50: =G48+G45+G41+G37+G34+G29 | H50: =H48+H45+H41+H37+H34+H29 | I50: =I48+I45+I41+I37+I34+I29 | J50: =J48+J45+J41+J37+J34+J29 | ... AB50: =AB48+AB45+AB41+AB37+AB34+AB29 | AC50: =AC48+AC45+AC41+AC37+AC34+AC29+AC42 | AE50: =SUM(AG50:DN50) | AG50: =AG48+AG45+AG41+AG37+AG34+AG29+AG42+AG38 | AH50: =AH48+AH45+AH41+AH37+AH34+AH29+AH42+AH38 | AI50: =AI48+AI45+AI41+AI37+AI34+AI29+AI42+AI38 | AJ50: =AJ48+AJ45+AJ41+AJ37+AJ34+AJ29+AJ42+AJ38 | AK50: =AK48+AK45+AK41+AK37+AK34+AK29+AK42+AK38 | AL50: =AL48+AL45+AL41+AL37+AL34+AL29+AL42+AL38 | AM50: =AM48+AM45+AM41+AM37+AM34+AM29+AM42+AM38 | AN50: =AN48+AN45+AN41+AN37+AN34+AN29+AN42+AN38 | ... HU50: =HU48+HU45+HU41+HU37+HU34+HU29+HU42+HU38
A51: TOTAL ACUMULADO DE DESPESAS OP.(-) | B51: =SUM(C51:W51) | D51: =C51+D50 | E51: =D51+E50 | F51: =D51+F50 | G51: =E51+G50 | H51: =F51+H50 | I51: =G51+I50 | J51: =I51+J50 | K51: =J51+K50 | L51: =K51+L50 | M51: =L51+M50 | N51: =M51+N50 | O51: =N51+O50 | P51: =O51+P50 | Q51: =P51+Q50 | ... AC51: =AB51+AC50 | AE51: =W51+AE50 | AG51: =AA51+AG50 | AH51: =AG51+AH50 | AI51: =AH51+AI50 | AJ51: =AI51+AJ50 | AK51: =AJ51+AK50 | AL51: =AK51+AL50 | AM51: =AL51+AM50 | AN51: =AM51+AN50 | AO51: =AN51+AO50 | ... HU51: =HT51+HU50
A53: IMPOSTOS (-)
A54: Impostos | B54: =SUM(C54:W54) | AC54: =-210474.96-5661 | AE54: =SUM(AG54:HU54) | AG54: =(AC8+AC9+AC12)*6.75%*-1 | AH54: =(AG8+AG9+AG12)*6.75%*-1 | AI54: =(AH8+AH9+AH12)*6.75%*-1 | AJ54: =(AI8+AI9+AI12)*6.75%*-1 | AK54: =(AJ8+AJ9+AJ12)*6.75%*-1 | AL54: =(AK8+AK9+AK12)*6.75%*-1 | AM54: =(AL8+AL9+AL12)*6.75%*-1 | AN54: =(AM8+AM9+AM12)*6.75%*-1 | AO54: =(AN8+AN9+AN12)*6.75%*-1 | ... DX54: =(DW8+DW9+DW12)*6.75%*-1 | DY54: =(DU8+DU9+DU12)*6.75%*-1 | DZ54: =(DY8+DY9+DY12)*6.75%*-1 | EA54: =(DZ8+DZ9+DZ12)*6.75%*-1 | EB54: =(EA8+EA9+EA12)*6.75%*-1 | EC54: =(EB8+EB9+EB12)*6.75%*-1 | ED54: =(EC8+EC9+EC12)*6.75%*-1 | EE54: =(ED8+ED9+ED12)*6.75%*-1 | EF54: =(EE8+EE9+EE12)*6.75%*-1 | EG54: =(EF8+EF9+EF12)*6.75%*-1 | ... HU54: =(HT8+HT9+HT12)*6.75%*-1
A56: DESAPROPRIAÇÃO (-)
A57: Desapropriação | B57: =SUM(C57:W57) | C57: 0 | D57: 0 | E57: 0 | F57: 0 | G57: 0 | I57: 0 | J57: 0 | K57: 0 | AE57: =SUM(AG57:HU57) | AG57: 0 | AH57: -475000 | AI57: -475000 | AJ57: -475000 | AK57: -475000 | AL57: -475000 | AM57: -475000 | AN57: 0 | AO57: 0 | AP57: 0 | AQ57: 0 | AR57: 0 | AS57: 0 | AT57: 0 | AU57: 0 | AV57: 0 | AW57: 0 | AX57: 0 | AY57: 0 | AZ57: 0 | BA57: 0 | BB57: 0 | BC57: 0 | BD57: 0 | BE57: 0 | BF57: 0 | BG57: 0 | BH57: 0 | BI57: 0 | BJ57: 0 | BK57: 0 | BL57: 0 | BM57: 0 | BN57: 0 | BO57: 0 | BP57: 0 | BQ57: 0 | BR57: 0 | BS57: 0 | BT57: 0 | BU57: 0 | BV57: 0 | BW57: 0 | BX57: 0 | BY57: 0 | BZ57: 0 | CA57: 0 | CB57: 0 | CC57: 0 | CD57: 0 | CE57: 0 | CF57: 0 | CG57: 0 | CH57: 0 | CI57: 0 | CJ57: 0 | CK57: 0 | CL57: 0 | CM57: 0 | CN57: 0 | CO57: 0 | CP57: 0 | CQ57: 0 | CR57: 0 | CS57: 0 | CT57: 0 | CU57: 0 | CV57: 0 | CW57: 0 | CX57: 0 | CY57: 0 | CZ57: 0 | DA57: 0 | DB57: 0 | DC57: 0 | DD57: 0 | DE57: 0 | DF57: 0 | DG57: 0 | DH57: 0 | DI57: 0 | DJ57: 0 | DK57: 0 | DL57: 0 | DM57: 0 | DN57: 0 | DO57: 0 | DP57: 0 | DQ57: 0 | DR57: 0 | DS57: 0 | DT57: 0 | DU57: 0 | DV57: 0 | DW57: 0 | DX57: 0 | DY57: 0 | DZ57: 0 | EA57: 0 | EB57: 0 | EC57: 0 | ED57: 0 | EE57: 0 | EF57: 0 | EG57: 0 | EH57: 0 | EI57: 0 | EJ57: 0 | EK57: 0 | EL57: 0 | EM57: 0 | EN57: 0 | EO57: 0 | EP57: 0 | EQ57: 0 | ER57: 0 | ES57: 0 | ET57: 0 | EU57: 0 | EV57: 0 | EW57: 0 | EX57: 0 | EY57: 0 | EZ57: 0 | FA57: 0 | FB57: 0 | FC57: 0 | FD57: 0 | FE57: 0 | FF57: 0 | FG57: 0 | FH57: 0 | FI57: 0 | FJ57: 0 | FK57: 0 | FL57: 0 | FM57: 0 | FN57: 0 | FO57: 1 | FP57: 2 | FQ57: 3 | FR57: 4 | FS57: 5 | FT57: 6 | FU57: 7 | FV57: 8 | FW57: 9 | FX57: 10 | FY57: 11 | FZ57: 12 | GA57: 13 | GB57: 14 | GC57: 15 | GD57: 16 | GE57: 17 | GF57: 18 | GG57: 19 | GH57: 20 | GI57: 21 | GJ57: 22 | GK57: 23 | GL57: 24 | GM57: 25 | GN57: 26 | GO57: 27 | GP57: 28 | GQ57: 29 | GR57: 30 | GS57: 31 | GT57: 32 | GU57: 33 | GV57: 34 | GW57: 35 | GX57: 36 | GY57: 37 | GZ57: 38 | HA57: 39 | HB57: 40 | HC57: 41 | HD57: 42 | HE57: 43 | HF57: 44 | HG57: 45 | HH57: 46 | HI57: 47 | HJ57: 48 | HK57: 49 | HL57: 50 | HM57: 51 | HN57: 52 | HO57: 53 | HP57: 54 | HQ57: 55 | HR57: 56 | HS57: 57 | HT57: 58 | HU57: 59
A59: DISTRATOS (-)
A60: Devoluções | B60: =SUM(C60:W60) | AE60: =SUM(AG60:HU60) | AG60: 0 | AH60: 0 | AI60: 0 | AJ60: 0 | AK60: 0 | AL60: 0 | AM60: 0 | AN60: 0 | AO60: 0 | AP60: 0 | AQ60: 0 | AR60: 0 | AS60: 0 | AT60: 0 | AU60: 0 | AV60: 0 | AW60: 0 | AX60: 0 | AY60: 0 | AZ60: 0 | BA60: 0 | BB60: 0 | BC60: 0 | BD60: 0 | BE60: 0 | BF60: 0 | BG60: 0 | BH60: 0 | BI60: 0 | BJ60: 0 | BK60: 0 | BL60: 0 | BM60: 0 | BN60: 0 | BO60: 0 | BP60: 0 | BQ60: 0 | BR60: 0 | BS60: 0 | BT60: 0 | BU60: 0 | BV60: 0 | BW60: 0 | BX60: 0 | BY60: 0 | BZ60: 0 | CA60: 0 | CB60: 0 | CC60: 0 | CD60: 0 | CE60: 0 | CF60: 0 | CG60: 0 | CH60: 0 | CI60: 0 | CJ60: 0 | CK60: 0 | CL60: 0 | CM60: 0 | CN60: 0 | CO60: 0 | CP60: 0 | CQ60: 0 | CR60: 0 | CS60: 0 | CT60: 0 | CU60: 0 | CV60: 0 | CW60: 0 | CX60: 0 | CY60: 0 | CZ60: 0 | DA60: 0 | DB60: 0 | DC60: 0 | DD60: 0 | DE60: 0 | DF60: 0 | DG60: 0 | DH60: 0 | DI60: 0 | DJ60: 0 | DL60: 0 | DN60: 0
A62: DISTRIBUIÇÕES (-)
A63: Devolução de Aporte | B63: =SUM(C63:W63) | AE63: =SUM(AG63:HU63) | AG63: 0 | AH63: 0 | AI63: 0 | AJ63: 0 | AK63: 0 | AL63: 0 | AM63: 0 | AN63: 0 | AO63: 0 | AP63: 0 | AQ63: 0 | AR63: 0 | AS63: 0 | AT63: 0 | AU63: 0 | AV63: 0 | AW63: 0 | AX63: 0 | AY63: 0 | AZ63: 0 | BA63: 0 | BB63: 0 | BC63: 0 | BD63: 0 | BE63: 0 | BF63: 0 | BG63: 0 | BT63: 0 | BU63: 0 | BV63: 0 | BW63: 0 | BX63: 0 | BY63: 0 | BZ63: 0 | CA63: 0 | CB63: 0 | CC63: 0 | CD63: 0 | CE63: 0 | CF63: 0 | CG63: 0 | CH63: 0 | CI63: 0 | CJ63: 0 | CK63: 0 | CL63: 0 | CM63: 0 | CN63: 0 | CO63: 0 | CP63: 0 | CQ63: 0 | CR63: 0 | CS63: 0 | CT63: 0 | CU63: 0 | CV63: 0 | CW63: 0 | CX63: 0 | CY63: 0 | CZ63: 0 | DA63: 0 | DB63: 0 | DC63: 0 | DD63: 0 | DE63: 0 | DF63: 0 | DG63: 0 | DH63: 0 | DI63: 0
A64: Distribuição de Resultado | B64: =SUM(C64:AA64) | AE64: =SUM(AG64:DX64)
A65: Subtotal | B65: =SUM(C65:W65) | C65: =SUM(C63:C64) | D65: =SUM(D63:D64) | E65: =SUM(E63:E64) | F65: =SUM(F63:F64) | G65: =SUM(G63:G64) | H65: =SUM(H63:H64) | I65: =SUM(I63:I64) | J65: =SUM(J63:J64) | ... AB65: =SUM(AB63:AB64) | AE65: =SUM(AG65:DX65) | AG65: =SUM(AG63:AG64) | AH65: =SUM(AH63:AH64) | AI65: =SUM(AI63:AI64) | AJ65: =SUM(AJ63:AJ64) | AK65: =SUM(AK63:AK64) | AL65: =SUM(AL63:AL64) | AM65: =SUM(AM63:AM64) | AN65: =SUM(AN63:AN64) | ... DI65: =SUM(DI63:DI64) | DJ65: =SUM(DJ64:DJ64) | DK65: =SUM(DK64:DK64) | DL65: =SUM(DL64:DL64) | DM65: =SUM(DM64:DM64) | DN65: =SUM(DN64:DN64) | DO65: =SUM(DO64:DO64) | DP65: =SUM(DP64:DP64) | DQ65: =SUM(DQ64:DQ64) | ... DX65: =SUM(DX64:DX64)
A67: DESPESAS OP+TERRENO+IMP+DISTR (-) | B67: =SUM(C67:W67) | C67: =C65+C54+C50+C57+C60 | D67: =D65+D54+D50+D57+D60 | E67: =E65+E54+E50+E57+E60 | F67: =F65+F54+F50+F57+F60 | G67: =G65+G54+G50+G57+G60 | H67: =H65+H54+H50+H57+H60 | I67: =I65+I54+I50+I57+I60 | J67: =J65+J54+J50+J57+J60 | ... AC67: =AC65+AC54+AC50+AC57+AC60 | AE67: =SUM(AG67:DX67) | AG67: =AG65+AG54+AG50+AG57+AG60 | AH67: =AH65+AH54+AH50+AH57+AH60 | AI67: =AI65+AI54+AI50+AI57+AI60 | AJ67: =AJ65+AJ54+AJ50+AJ57+AJ60 | AK67: =AK65+AK54+AK50+AK57+AK60 | AL67: =AL65+AL54+AL50+AL57+AL60 | AM67: =AM65+AM54+AM50+AM57+AM60 | AN67: =AN65+AN54+AN50+AN57+AN60 | ... HU67: =HU65+HU54+HU50+HU57+HU60
A68: TOTAL ACUMULADO | C68: 0 | D68: =C68+D67 | E68: =D68+E67 | F68: =E68+F67 | G68: =F68+G67 | H68: =G68+H67 | I68: =H68+I67 | J68: =I68+J67 | K68: =J68+K67 | ... AC68: =AB68+AC67 | AE68: 0 | AG68: =AA68+AG67 | AH68: =AG68+AH67 | AI68: =AH68+AI67 | AJ68: =AI68+AJ67 | AK68: =AJ68+AK67 | AL68: =AK68+AL67 | AM68: =AL68+AM67 | AN68: =AM68+AN67 | AO68: =AN68+AO67 | ... HU68: =HT68+HU67
A70: SALDO DE CAIXA (MENSAL) | C70: =C20+C67 | D70: =D20+D67 | E70: =E20+E67 | F70: =F20+F67 | G70: =G20+G67 | H70: =H20+H67 | I70: =I20+I67 | J70: =J20+J67 | ... AC70: =AC20+AC67 | AE70: 0 | AG70: =AG20+AG67 | AH70: =AH20+AH67 | AI70: =AI20+AI67 | AJ70: =AJ20+AJ67 | AK70: =AK20+AK67 | AL70: =AL20+AL67 | AM70: =AM20+AM67 | AN70: =AN20+AN67 | ... HU70: =HU20+HU67
A71: SALDO ACUMULADO (REAL) | C71: 0 | D71: =C71+D70 | E71: =D71+E70 | F71: =E71+F70 | G71: =F71+G70 | H71: =G71+H70 | I71: =H71+I70 | J71: =I71+J70 | K71: =J71+K70 | ... AC71: =AB71+AC70 | AG71: =AA71+AG70 | AH71: =AG71+AH70 | AI71: =AH71+AI70 | AJ71: =AI71+AJ70 | AK71: =AJ71+AK70 | AL71: =AK71+AL70 | AM71: =AL71+AM70 | AN71: =AM71+AN70 | AO71: =AN71+AO70 | ... HU71: =HT71+HU70
A73: SALDO DE CAIXA (MENSAL) C/ PROJEÇÃO | C73: =C20+C67+C12 | D73: =D20+D67+D12 | E73: =E20+E67+E12 | F73: =F20+F67+F12 | G73: =G20+G67+G12 | H73: =H20+H67+H12 | I73: =I20+I67+I12 | J73: =J20+J67+J12 | ... AC73: =AC20+AC67+AC12 | AG73: =AG20+AG67+AG12 | AH73: =AH20+AH67+AH12 | AI73: =AI20+AI67+AI12 | AJ73: =AJ20+AJ67+AJ12 | AK73: =AK20+AK67+AK12 | AL73: =AL20+AL67+AL12 | AM73: =AM20+AM67+AM12 | AN73: =AN20+AN67+AN12 | ... HU73: =HU20+HU67+HU12
A74: SALDO ACUMULADO C/ PROJEÇÕES | C74: =B74+C73 | D74: =C74+D73 | E74: =D74+E73 | F74: =E74+F73 | G74: =F74+G73 | H74: =G74+H73 | I74: =H74+I73 | J74: =I74+J73 | ... AC74: =AB74+AC73 | AG74: =AC74+AG73 | AH74: =AG74+AH73 | AI74: =AH74+AI73 | AJ74: =AI74+AJ73 | AK74: =AJ74+AK73 | AL74: =AK74+AL73 | AM74: =AL74+AM73 | AN74: =AM74+AN73 | AO74: =AN74+AO73 | ... HU74: =HT74+HU73
BP75: 24 meses pós obra | CB75: 36 meses pós obra | CN75: 48 meses pós obra | CZ75: 60 meses pós obra

Sheet FC Total (5 lotes)
AR1: Total | Previsão | BF1: PREVISÃO DE | EC1: FIM DAS VENDAS | JF1: Realizado | JM1: Previsão de Maio feita no fechamento de Abril/26 | KH1: Total | Previsão
A2: Ville de Provence | AB2: =+AB8+AB9+AC8+AC9+AD8+AD9+AE8+AE9+AF8+AF9+AD62 | BF2: ENTREGA DA OBRA | JF2: No mês | JG2: Ano 2025 | JH2: Ano 2026 | JI2: Acumulado | JS2: YTD | JT2: Prev. 2025 | JU2: 2026 | JV2: 2027 | JW2: 2028 | JX2: 2029 | JY2: 2030 | JZ2: Demais
C3: 1 | D3: 2 | E3: 3 | F3: 4 | G3: 5 | H3: 6 | I3: 7 | J3: 8 | K3: 9 | L3: 10 | M3: 11 | N3: 12 | O3: 13 | P3: 14 | Q3: 15 | R3: 16 | S3: 17 | T3: 18 | U3: 19 | V3: 20 | W3: 21 | X3: 22 | Y3: 23 | Z3: 24 | AA3: 25 | AB3: 26 | AC3: 27 | AD3: 28 | AE3: 29 | AF3: 30 | AG3: 31 | AH3: 32 | AI3: 33 | AJ3: 34 | AK3: 35 | AL3: 36 | AM3: 37 | AN3: 38 | AO3: 39 | AP3: 40 | AT3: 41 | AU3: 42 | AV3: 43 | AW3: 44 | AX3: 45 | AY3: 46 | AZ3: 47 | BA3: 48 | BB3: 49 | BC3: 50 | BD3: 51 | BE3: 52 | BF3: 53 | BG3: 54 | BH3: 55 | BI3: 56 | BJ3: 57 | BK3: 58 | BL3: 59 | BM3: 60 | BN3: 61 | BO3: 62 | BP3: 63 | BQ3: 64 | BR3: 65 | BS3: 66 | BT3: 67 | BU3: 68 | BV3: 69 | BW3: 70 | BX3: 71 | BY3: 72 | BZ3: 73 | CA3: 74 | CB3: 75 | CC3: 76 | CD3: 77 | CE3: 78 | CF3: 79 | CG3: 80 | CH3: 81 | CI3: 82 | CJ3: 83 | CK3: 84 | CL3: 85 | CM3: 86 | CN3: 87 | CO3: 88 | CP3: 89 | CQ3: 90 | CR3: 91 | CS3: 92 | CT3: 93 | CU3: 94 | CV3: 95 | CW3: 96 | CX3: 97 | CY3: 98 | CZ3: 99 | DA3: 100 | DB3: 101 | DC3: 102 | DD3: 103 | DE3: 104 | DF3: 105 | DG3: 106 | DH3: 107 | DI3: 108 | DJ3: 109 | DK3: 110 | DL3: 111 | DM3: 112 | DN3: 113 | DO3: 114 | DP3: 115 | DQ3: 116 | DR3: 117 | DS3: 118 | DT3: 119 | DU3: 120 | DV3: 121 | DW3: 122 | DX3: 123 | DY3: 124 | DZ3: 125 | EA3: 126 | EB3: 127 | EC3: 128 | ED3: 129 | EE3: 130 | EF3: 131 | EG3: 132 | EH3: 133 | EI3: 134 | EJ3: 135 | EK3: 136 | EL3: 137 | EM3: 138 | EN3: 139 | EO3: 140 | EP3: 141 | EQ3: 142 | ER3: 143 | ES3: 144 | ET3: 145 | EU3: 146 | EV3: 147 | EW3: 148 | EX3: 149 | EY3: 150 | EZ3: 151 | FA3: 152 | FB3: 153 | FC3: 154 | FD3: 155 | FE3: 156 | FF3: 157 | FG3: 158 | FH3: 159 | FI3: 160 | FJ3: 161 | FK3: 162 | FL3: 163 | FM3: 164 | FN3: 165 | FO3: 166 | FP3: 167 | FQ3: 168 | FR3: 169 | FS3: 170 | FT3: 171 | FU3: 172 | FV3: 173 | FW3: 174 | FX3: 175 | FY3: 176 | FZ3: 177 | GA3: 178 | GB3: 179 | GC3: 180 | GD3: 181 | GE3: 182 | GF3: 183 | GG3: 184 | GH3: 185 | GI3: 186 | GJ3: 187 | GK3: 188 | GL3: 189 | GM3: 190 | GN3: 191 | GO3: 192 | GP3: 193 | GQ3: 194 | GR3: 195 | GS3: 196 | GT3: 197 | GU3: 198 | GV3: 199 | GW3: 200 | GX3: 201 | GY3: 202 | GZ3: 203 | HA3: 204 | HB3: 205 | HC3: 206 | HD3: 207 | HE3: 208 | HF3: 209 | HG3: 210 | HH3: 211 | HI3: 212 | HJ3: 213 | HK3: 214 | HL3: 215 | HM3: 216 | HN3: 217 | HO3: 218 | HP3: 219 | HQ3: 220 | HR3: 221 | HS3: 222 | HT3: 223 | HU3: 224 | JM3: 40
A4: Fluxo de Caixa | B4: REALIZADO | M4: REALIZADO | KG4: REALIZADO
C5: 44958 | D5: 44986 | E5: 45017 | F5: 45047 | G5: 45078 | H5: 45108 | I5: 45139 | J5: 45170 | K5: 45200 | L5: 45231 | M5: 45261 | N5: 45292 | O5: 45323 | P5: 45352 | Q5: 45383 | R5: 45413 | S5: 45444 | T5: 45474 | U5: 45505 | V5: 45536 | W5: 45566 | X5: 45597 | Y5: 45627 | Z5: 45658 | AA5: 45689 | AB5: 45717 | AC5: 45748 | AD5: 45778 | AE5: 45809 | AF5: 45839 | AG5: 45870 | AH5: 45901 | AI5: 45931 | AJ5: 45962 | AK5: 45992 | AL5: 46023 | AM5: 46054 | AN5: 46082 | AO5: 46113 | AP5: 46143 | AR5: Total | Previsão | AT5: 46174 | AU5: 46204 | AV5: 46235 | AW5: 46266 | AX5: 46296 | AY5: 46327 | AZ5: 46357 | BA5: 46388 | BB5: 46419 | BC5: 46447 | BD5: 46478 | BE5: 46508 | BF5: 46539 | BG5: 46569 | BH5: 46600 | BI5: 46631 | BJ5: 46661 | BK5: 46692 | BL5: 46722 | BM5: 46753 | BN5: 46784 | BO5: 46813 | BP5: 46844 | BQ5: 46874 | BR5: 46905 | BS5: 46935 | BT5: 46966 | BU5: 46997 | BV5: 47027 | BW5: 47058 | BX5: 47088 | BY5: 47119 | BZ5: 47150 | CA5: 47178 | CB5: 47209 | CC5: 47239 | CD5: 47270 | CE5: 47300 | CF5: 47331 | CG5: 47362 | CH5: 47392 | CI5: 47423 | CJ5: 47453 | CK5: 47484 | CL5: 47515 | CM5: 47543 | CN5: 47574 | CO5: 47604 | CP5: 47635 | CQ5: 47665 | CR5: 47696 | CS5: 47727 | CT5: 47757 | CU5: 47788 | CV5: 47818 | CW5: 47849 | CX5: 47880 | CY5: 47908 | CZ5: 47939 | DA5: 47969 | DB5: 48000 | DC5: 48030 | DD5: 48061 | DE5: 48092 | DF5: 48122 | DG5: 48153 | DH5: 48183 | DI5: 48214 | DJ5: 48245 | DK5: 48274 | DL5: 48305 | DM5: 48335 | DN5: 48366 | DO5: 48396 | DP5: 48427 | DQ5: 48458 | DR5: 48488 | DS5: 48519 | DT5: 48549 | DU5: 48580 | DV5: 48611 | DW5: 48639 | DX5: 48670 | DY5: 48700 | DZ5: 48731 | EA5: 48761 | EB5: 48792 | EC5: 48823 | ED5: 48853 | EE5: 48884 | EF5: 48914 | EG5: 48945 | EH5: 48976 | EI5: 49004 | EJ5: 49035 | EK5: 49065 | EL5: 49096 | EM5: 49126 | EN5: 49157 | EO5: 49188 | EP5: 49218 | EQ5: 49249 | ER5: 49279 | ES5: 49310 | ET5: 49341 | EU5: 49369 | EV5: 49400 | EW5: 49430 | EX5: 49461 | EY5: 49491 | EZ5: 49522 | FA5: 49553 | FB5: 49583 | FC5: 49614 | FD5: 49644 | FE5: 49675 | FF5: 49706 | FG5: 49735 | FH5: 49766 | FI5: 49796 | FJ5: 49827 | FK5: 49857 | FL5: 49888 | FM5: 49919 | FN5: 49949 | FO5: 49980 | FP5: 50010 | FQ5: 50041 | FR5: 50072 | FS5: 50100 | FT5: 50131 | FU5: 50161 | FV5: 50192 | FW5: 50222 | FX5: 50253 | FY5: 50284 | FZ5: 50314 | GA5: 50345 | GB5: 50375 | GC5: 50406 | GD5: 50437 | GE5: 50465 | GF5: 50496 | GG5: 50526 | GH5: 50557 | GI5: 50587 | GJ5: 50618 | GK5: 50649 | GL5: 50679 | GM5: 50710 | GN5: 50740 | GO5: 50771 | GP5: 50802 | GQ5: 50830 | GR5: 50861 | GS5: 50891 | GT5: 50922 | GU5: 50952 | GV5: 50983 | GW5: 51014 | GX5: 51044 | GY5: 51075 | GZ5: 51105 | HA5: 51136 | HB5: 51167 | HC5: 51196 | HD5: 51227 | HE5: 51257 | HF5: 51288 | HG5: 51318 | HH5: 51349 | HI5: 51380 | HJ5: 51410 | HK5: 51441 | HL5: 51471 | HM5: 51502 | HN5: 51533 | HO5: 51561 | HP5: 51592 | HQ5: 51622 | HR5: 51653 | HS5: 51683 | HT5: 51714 | HU5: 51745 | JM5: 46143 | KH5: Total | Previsão
A7: RECEITAS | JR7: =A7
A8: ITBI | B8: =SUM(C8:AP8) | AB8: 338614.68 | AC8: 371549.5 | AD8: 148554.82 | AE8: 170837.48 | AF8: 191671.94 | AG8: 135342.79 | AH8: 107538.42 | AI8: 89467.66 | AJ8: 89498.31 | AK8: 150726.26 | AL8: 202733.57 | AM8: 93610.35 | AN8: 102176.17 | AO8: 121648.43 | AP8: 76491.71 | AR8: =SUM(AT8:HU8) | JF8: =AP8 | JG8: =SUM(Z8:AK8) | JH8: =SUM(AL8:AP8) | JI8: =SUM(C8:AP8) | JR8: =A8 | JS8: =SUM(C8:AP8) | JU8: =SUM(AT8:AZ8) | JV8: =SUM(BA8:BL8) | JW8: =SUM(BM8:BX8) | JX8: =SUM(BY8:CJ8) | JY8: =SUM(CK8:CV8) | JZ8: =SUM(CW8:HU8) | KG8: =B8 | KH8: =AR8
A9: Receitas Contratadas | B9: =SUM(C9:AP9) | AB9: 2857997.7 | AC9: 3156158.3 | AD9: 1788940.8 | AE9: =3240637.47-AE8+19092.42 | AF9: 1881026.6 | AG9: 2310558.1 | AH9: =2548839.41-78352.42 | AI9: 2551921.9 | AJ9: =2138552.83-41382.42 | AK9: 4079024.8 | AL9: 4698660.8 | AM9: 3087731.2 | AN9: =7279760.12-30654.55 | AO9: =3684860.85-29012.57-24791.61 | AP9: 3243847.9 | AR9: =SUM(AT9:HU9) | AT9: 3574821.4 | AU9: 2767000.7 | AV9: 2446947.7 | AW9: 3652273.5 | AX9: 2932991 | AY9: 2528178 | AZ9: 3753790.3 | BA9: 4012049.6 | BB9: 3544053.9 | BC9: 3455923.5 | BD9: 3435572.3 | BE9: 2126327.4 | BF9: 1595056.3 | BG9: 1682126.5 | BH9: 1531678.3 | BI9: 1005222.9 | BJ9: 965285.41 | BK9: 1636485.1 | BL9: 1675939 | BM9: 913661.51 | BN9: 799107.12 | BO9: 1148317.9 | BP9: 1245834.1 | BQ9: 688488.99 | BR9: 475750.07 | BS9: 483123.56 | BT9: 573091.67 | BU9: 445746.79 | BV9: 445746.73 | BW9: 467823.36 | BX9: 445746.73 | BY9: 443425.39 | BZ9: 367739.24 | CA9: 393894.68 | CB9: 628058.54 | CC9: 835888.25 | CD9: 365111.17 | CE9: 422908.01 | CF9: 492947.79 | CG9: 366947.05 | CH9: 366947.12 | CI9: 380365.1 | CJ9: 358288.47 | CK9: 407361.59 | CL9: 358288.47 | CM9: 372054.76 | CN9: 633307.27 | CO9: 760631.49 | CP9: 354866.26 | CQ9: 418462.35 | CR9: 355407.32 | CS9: 355407.27 | CT9: 355407.27 | CU9: 377483.9 | CV9: 344499.82 | CW9: 393572.94 | CX9: 344499.82 | CY9: 370765.27 | CZ9: 644037.26 | DA9: 652601.6 | DB9: 332584.38 | DC9: 421539.19 | DD9: 333179.68 | DE9: 333179.7 | DF9: 333179.7 | DG9: 355256.33 | DH9: 333179.7 | DI9: 382252.82 | DJ9: 333179.7 | DK9: 359415.99 | DL9: 655336.52 | DM9: 355909.56 | DN9: 333832.92 | DO9: 431713.34 | DP9: 334487.99 | DQ9: 334487.95 | DR9: 334487.95 | DS9: 356564.58 | DT9: 334487.95 | DU9: 383561.07 | DV9: 334487.95 | DW9: 360650.28 | DX9: 531581.81 | DY9: 289043.69 | DZ9: 249797.02 | EA9: 325590.01 | EB9: 201524.86 | EC9: 177058.53 | ED9: 165595.82 | EE9: 187672.45 | EF9: 151718.75 | EG9: 186523.84 | EH9: 114989.8 | EI9: 101752.25 | EJ9: 72859.21 | EK9: 37160.03 | EL9: 0 | EM9: 0 | EN9: 0 | EO9: 0 | EP9: 0 | EQ9: 0 | ER9: 0 | ES9: 0 | ET9: 0 | EU9: 0 | EV9: 0 | EW9: 0 | EX9: 0 | EY9: 0 | EZ9: 0 | FA9: 0 | FB9: 0 | FC9: 0 | FD9: 0 | FE9: 0 | FF9: 0 | FG9: 0 | FH9: 0 | FI9: 0 | FJ9: 0 | FK9: 0 | FL9: 0 | FM9: 0 | FN9: 0 | FO9: 0 | FP9: 0 | FQ9: 0 | FR9: 0 | FS9: 0 | FT9: 0 | FU9: 0 | FV9: 0 | FW9: 0 | FX9: 0 | FY9: 0 | FZ9: 0 | GA9: 0 | GB9: 0 | GC9: 0 | GD9: 0 | GE9: 0 | GF9: 0 | GG9: 0 | GH9: 0 | GI9: 0 | GJ9: 0 | GK9: 0 | GL9: 0 | GM9: 0 | GN9: 0 | GO9: 0 | GP9: 0 | GQ9: 0 | GR9: 0 | GS9: 0 | GT9: 0 | GU9: 0 | GV9: 0 | GW9: 0 | GX9: 0 | GY9: 0 | GZ9: 0 | HA9: 0 | HB9: 0 | HC9: 0 | HD9: 0 | HE9: 0 | HF9: 0 | HG9: 0 | HH9: 0 | HI9: 0 | HJ9: 0 | HK9: 0 | HL9: 0 | HM9: 0 | HN9: 0 | HO9: 0 | HP9: 0 | HQ9: 0 | HR9: 0 | HS9: 0 | HT9: 0 | HU9: 0 | JF9: =AP9 | JG9: =SUM(Z9:AK9) | JH9: =SUM(AL9:AP9) | JI9: =SUM(C9:AP9) | JM9: 2014799.1 | JR9: =A9 | JS9: =SUM(C9:AP9) | JU9: =SUM(AT9:AZ9) | JV9: =SUM(BA9:BL9) | JW9: =SUM(BM9:BX9) | JX9: =SUM(BY9:CJ9) | JY9: =SUM(CK9:CV9) | JZ9: =SUM(CW9:HU9) | KG9: =B9 | KH9: =AR9 | KJ9: =+KG9+KH9+KH12
JF10: =AP10 | JG10: =SUM(Z10:AK10) | JH10: =SUM(AL10:AP10) | JI10: =SUM(C10:AP10) | JR10: =A10 | JS10: =SUM(C10:AP10) | JU10: =SUM(AT10:AZ10) | JV10: =SUM(BA10:BL10) | JW10: =SUM(BM10:BX10) | JX10: =SUM(BY10:CJ10) | JY10: =SUM(CK10:CV10) | JZ10: =SUM(CW10:HU10) | KG10: =B10 | KH10: =AR10
A11: PREVISÃO DE RECEITAS(ESTOQUE) | JF11: =AP11 | JG11: =SUM(Z11:AK11) | JH11: =SUM(AL11:AP11) | JI11: =SUM(C11:AP11) | JR11: =A11 | JS11: =SUM(C11:AP11) | JU11: =SUM(AT11:AZ11) | JV11: =SUM(BA11:BL11) | JW11: =SUM(BM11:BX11) | JX11: =SUM(BY11:CJ11) | JY11: =SUM(CK11:CV11) | JZ11: =SUM(CW11:HU11) | KG11: =B11 | KH11: =AR11
A12: Vendas 05 Lotes a.m. | B12: =SUM(C12:AP12) | C12: 0 | D12: 0 | E12: 0 | F12: 0 | G12: 0 | H12: 0 | I12: 0 | J12: 0 | K12: 0 | L12: 0 | M12: 0 | N12: 0 | O12: 0 | P12: 0 | Q12: 0 | R12: 0 | S12: 0 | T12: 0 | U12: 0 | V12: 0 | AR12: =SUM(AT12:HU12) | AT12: 553013.18 | AU12: 641664.18 | AV12: 730315.18 | AW12: 818966.18 | AX12: 923740.02 | AY12: 1014975.6 | AZ12: 1106211.2 | BA12: 1197446.8 | BB12: 1288682.3 | BC12: 1379917.9 | BD12: 1471153.5 | BE12: 1562389.1 | BF12: 2292757.3 | BG12: 2354685.2 | BH12: 2432736 | BI12: 2497248.4 | BJ12: 2580394.5 | BK12: 2644052.6 | BL12: 2707710.6 | BM12: 2771368.6 | BN12: 2835026.7 | BO12: 2898684.7 | BP12: 2962342.8 | BQ12: 3026000.8 | BR12: 3105781.7 | BS12: 3125526.5 | BT12: 3163905 | BU12: 3182795.4 | BV12: 3201685.8 | BW12: 3219220.6 | BX12: 3236755.4 | BY12: 3254290.2 | BZ12: 3271825 | CA12: 3289359.8 | CB12: 3323017.5 | CC12: 3343136.9 | CD12: 3381889.8 | CE12: 3396270.2 | CF12: 3410650.5 | CG12: 3423675.2 | CH12: 3436699.9 | CI12: 3449582.1 | CJ12: 3462464.4 | CK12: 3475346.7 | CL12: 3505964.1 | CM12: 3521689.4 | CN12: 3556048.4 | CO12: 3570919.2 | CP12: 3585790.1 | CQ12: 3599305.4 | CR12: 3612820.6 | CS12: 3626193.5 | CT12: 3639566.3 | CU12: 3652939.1 | CV12: 3684047.1 | CW12: 3700263 | CX12: 3736975.8 | CY12: 3752251.8 | CZ12: 3767527.8 | DA12: 3781448.1 | DB12: 3795368.5 | DC12: 3809146.5 | DD12: 3822924.4 | DE12: 3836702.4 | DF12: 3868215.4 | DG12: 3884836.4 | DH12: 3921954.4 | DI12: 3937635.5 | DJ12: 3953316.6 | DK12: 3967506.5 | DL12: 3981696.4 | DM12: 3995743.9 | DN12: 4009791.4 | DO12: 4023838.9 | DP12: 4055621.5 | DQ12: 4072512.1 | DR12: 4109899.6 | DS12: 4125850.2 | DT12: 4141800.8 | DU12: 3880882.3 | DV12: 3438130.2 | DW12: 3342071.6 | DX12: 3246012.9 | DY12: 3149954.3 | DZ12: 3053895.6 | EA12: 2957837 | EB12: 2882275.3 | EC12: 2785276.8 | ED12: 2688278.3 | EE12: 2589788.5 | EF12: 2491298.8 | EG12: 2074390.5 | EH12: 1512945.2 | EI12: 1450783.9 | EJ12: 1388622.6 | EK12: 1326461.3 | EL12: 1264300 | EM12: 1194177.7 | EN12: 1124055.4 | EO12: 1052441.9 | EP12: 980828.44 | EQ12: 908826.22 | ER12: 836824 | ES12: 764821.79 | ET12: 715973.55 | EU12: 701856.28 | EV12: 687739.01 | EW12: 673621.74 | EX12: 659504.47 | EY12: 645387.2 | EZ12: 631269.93 | FA12: 616763.92 | FB12: 602257.9 | FC12: 587751.88 | FD12: 573245.86 | FE12: 558739.85 | FF12: 546666.17 | FG12: 538240.99 | FH12: 529815.82 | FI12: 521390.64 | FJ12: 512965.47 | FK12: 504308.19 | FL12: 495650.92 | FM12: 486993.65 | FN12: 478336.38 | FO12: 469679.1 | FP12: 461021.83 | FQ12: 452364.56 | FR12: 443707.28 | FS12: 435050.01 | FT12: 426392.74 | FU12: 417503.37 | FV12: 408614 | FW12: 399724.62 | FX12: 390835.25 | FY12: 381945.88 | FZ12: 373056.51 | GA12: 364167.14 | GB12: 355277.77 | GC12: 346388.4 | GD12: 337499.03 | GE12: 328354.35 | GF12: 319209.67 | GG12: 310064.99 | GH12: 300920.31 | GI12: 291775.63 | GJ12: 282630.95 | GK12: 273486.27 | GL12: 264341.59 | GM12: 255196.91 | GN12: 246052.23 | GO12: 236652.24 | GP12: 227252.25 | GQ12: 217852.26 | GR12: 208452.28 | GS12: 199052.29 | GT12: 189652.3 | GU12: 180252.31 | GV12: 170852.32 | GW12: 161452.34 | GX12: 152052.35 | GY12: 142397.05 | GZ12: 132741.76 | HA12: 123086.46 | HB12: 113431.16 | HC12: 103775.87 | HD12: 94120.571 | HE12: 84465.275 | HF12: 74809.978 | HG12: 65154.682 | HH12: 55499.386 | HI12: 45588.781 | HJ12: 35678.177 | HK12: 25767.572 | HL12: 15856.967 | HM12: 5946.3628 | HN12: 0 | HO12: 0 | HP12: 0 | HQ12: 0 | HR12: 0 | HS12: 0 | HT12: 0 | HU12: 0 | JF12: =AP12 | JG12: =SUM(Z12:AK12) | JH12: =SUM(AL12:AP12) | JI12: =SUM(C12:AP12) | JM12: 553013.18 | JR12: =A12 | JS12: =SUM(C12:AP12) | JU12: =SUM(AT12:AZ12) | JV12: =SUM(BA12:BL12) | JW12: =SUM(BM12:BX12) | JX12: =SUM(BY12:CJ12) | JY12: =SUM(CK12:CV12) | JZ12: =SUM(CW12:HU12) | KG12: =B12 | KH12: =AR12
JF13: =AP13 | JG13: =SUM(Z13:AK13) | JH13: =SUM(AL13:AP13) | JI13: =SUM(C13:AP13) | JR13: =A13 | JS13: =SUM(C13:AP13) | JU13: =SUM(AT13:AZ13) | JV13: =SUM(BA13:BL13) | JW13: =SUM(BM13:BX13) | JX13: =SUM(BY13:CJ13) | JY13: =SUM(CK13:CV13) | JZ13: =SUM(CW13:HU13) | KG13: =B13 | KH13: =AR13
A14: APORTE DE SÓCIOS | JF14: =AP14 | JG14: =SUM(Z14:AK14) | JH14: =SUM(AL14:AP14) | JI14: =SUM(C14:AP14) | JR14: =A14 | JS14: =SUM(C14:AP14) | JU14: =SUM(AT14:AZ14) | JV14: =SUM(BA14:BL14) | JW14: =SUM(BM14:BX14) | JX14: =SUM(BY14:CJ14) | JY14: =SUM(CK14:CV14) | JZ14: =SUM(CW14:HU14) | KG14: =B14 | KH14: =AR14
A15: Aportes | B15: =SUM(C15:AP15) | C15: 2004788.2 | Y15: 1000000 | Z15: 1000000 | AB15: 1000000 | AR15: =SUM(AT15:HU15) | AX15: 200000 | AY15: 1600000 | AZ15: 500000 | BA15: 0 | BB15: 0 | BC15: 0 | BD15: 0 | BE15: 0 | BF15: 0 | BG15: 0 | BH15: 0 | BI15: 0 | BJ15: 0 | BL15: 0 | BM15: 0 | BN15: 0 | BO15: 0 | BP15: 0 | BQ15: 0 | BR15: 0 | BS15: 0 | BT15: 0 | BU15: 0 | BV15: 0 | BW15: 0 | BX15: 0 | BY15: 0 | BZ15: 0 | CA15: 0 | CB15: 0 | CC15: 0 | CD15: 0 | CE15: 0 | CF15: 0 | CG15: 0 | CH15: 0 | CI15: 0 | CJ15: 0 | CK15: 0 | CL15: 0 | CM15: 0 | CN15: 0 | CO15: 0 | CP15: 0 | CQ15: 0 | CR15: 0 | CS15: 0 | CT15: 0 | CU15: 0 | CV15: 0 | CW15: 0 | CX15: 0 | CY15: 0 | CZ15: 0 | DA15: 0 | DB15: 0 | DC15: 0 | DD15: 0 | DE15: 0 | DF15: 0 | DG15: 0 | DH15: 0 | DI15: 0 | DJ15: 0 | DK15: 0 | DL15: 0 | DM15: 0 | DN15: 0 | DO15: 0 | DP15: 0 | DQ15: 0 | DR15: 0 | DS15: 0 | DT15: 0 | DU15: 0 | DV15: 0 | DW15: 0 | DX15: 0 | DY15: 0 | DZ15: 0 | EA15: 0 | EB15: 0 | EC15: 0 | ED15: 0 | EE15: 0 | EF15: 0 | EG15: 0 | EH15: 0 | EI15: 0 | EJ15: 0 | EK15: 0 | EL15: 0 | EM15: 0 | EN15: 0 | EO15: 0 | EP15: 0 | EQ15: 0 | ER15: 0 | ES15: 0 | ET15: 0 | EU15: 0 | EV15: 0 | EW15: 0 | EX15: 0 | EY15: 0 | EZ15: 0 | FA15: 0 | FB15: 0 | FC15: 0 | FD15: 0 | FE15: 0 | FF15: 0 | FG15: 0 | FH15: 0 | FI15: 0 | FJ15: 0 | FK15: 0 | FL15: 0 | FM15: 0 | FN15: 0 | FO15: 0 | FP15: 0 | FQ15: 0 | FR15: 0 | FS15: 0 | FT15: 0 | FU15: 0 | FV15: 0 | FW15: 0 | FX15: 0 | FY15: 0 | FZ15: 0 | GA15: 0 | GB15: 0 | GC15: 0 | GD15: 0 | GE15: 0 | GF15: 0 | GG15: 0 | GH15: 0 | GI15: 0 | GJ15: 0 | GK15: 0 | GL15: 0 | GM15: 0 | GN15: 0 | GO15: 0 | GP15: 0 | GQ15: 0 | GR15: 0 | GS15: 0 | GT15: 0 | GU15: 0 | GV15: 0 | GW15: 0 | GX15: 0 | GY15: 0 | GZ15: 0 | HA15: 0 | HB15: 0 | HC15: 0 | HD15: 0 | HE15: 0 | HF15: 0 | HG15: 0 | HH15: 0 | HI15: 0 | HJ15: 0 | HK15: 0 | HL15: 0 | HM15: 0 | HN15: 0 | HO15: 0 | HP15: 0 | HQ15: 0 | HR15: 0 | HS15: 0 | HT15: 0 | HU15: 0 | JF15: =AP15 | JG15: =SUM(Z15:AK15) | JH15: =SUM(AL15:AP15) | JI15: =SUM(C15:AP15) | JR15: =A15 | JS15: =SUM(C15:AP15) | JU15: =SUM(AT15:AZ15) | JV15: =SUM(BA15:BL15) | JW15: =SUM(BM15:BX15) | JX15: =SUM(BY15:CJ15) | JY15: =SUM(CK15:CV15) | JZ15: =SUM(CW15:HU15) | KG15: =B15 | KH15: =AR15
JF16: =AP16 | JG16: =SUM(Z16:AK16) | JH16: =SUM(AL16:AP16) | JI16: =SUM(C16:AP16) | JR16: =A16 | JS16: =SUM(C16:AP16) | JU16: =SUM(AT16:AZ16) | JV16: =SUM(BA16:BL16) | JW16: =SUM(BM16:BX16) | JX16: =SUM(BY16:CJ16) | JY16: =SUM(CK16:CV16) | JZ16: =SUM(CW16:HU16) | KG16: =B16 | KH16: =AR16
A17: RECEITA FINANCEIRA (+) | JF17: =AP17 | JG17: =SUM(Z17:AK17) | JH17: =SUM(AL17:AP17) | JI17: =SUM(C17:AP17) | JR17: =A17 | JS17: =SUM(C17:AP17) | JU17: =SUM(AT17:AZ17) | JV17: =SUM(BA17:BL17) | JW17: =SUM(BM17:BX17) | JX17: =SUM(BY17:CJ17) | JY17: =SUM(CK17:CV17) | JZ17: =SUM(CW17:HU17) | KG17: =B17 | KH17: =AR17
A18: Rendimento Financeiro | B18: =SUM(C18:AP18) | AB18: 12646.02 | AC18: 38113.26 | AD18: 57998.09 | AE18: 61248.2 | AF18: 72074.91 | AG18: =38669.97+1.14+11658.76-959.8 | AH18: 113822.32 | AI18: 94885.85 | AJ18: =78967.8800000008-41382.42 | AK18: 92147.74 | AL18: 87783.19 | AM18: 36405.54 | AN18: 123144.16 | AO18: 161967.44 | AP18: 228379.68 | AR18: =SUM(AT18:HU18) | AT18: =IF(AP76>0, AP76*1%,0) | AU18: =IF(AT76>0, AT76*1%,0) | AV18: =IF(AU76>0, AU76*1%,0) | AW18: =IF(AV76>0, AV76*1%,0) | AX18: =IF(AW76>0, AW76*1%,0) | AY18: =IF(AX76>0, AX76*0.8%,0) | AZ18: =IF(AY76>0, AY76*0.8%,0) | BA18: =IF(AZ76>0, AZ76*0.8%,0) | BB18: =IF(BA76>0, BA76*0.8%,0) | BC18: =IF(BB76>0, BB76*0.8%,0) | BD18: =IF(BC76>0, BC76*0.8%,0) | BE18: =IF(BD76>0, BD76*0.8%,0) | BF18: =IF(BE76>0, BE76*0.8%,0) | ... HU18: =IF(HT76>0, HT76*0.8%,0) | JF18: =AP18 | JG18: =SUM(Z18:AK18) | JH18: =SUM(AL18:AP18) | JI18: =SUM(C18:AP18) | JM18: 125712.49 | JR18: =A18 | JS18: =SUM(C18:AP18) | JU18: =SUM(AT18:AZ18) | JV18: =SUM(BA18:BL18) | JW18: =SUM(BM18:BX18) | JX18: =SUM(BY18:CJ18) | JY18: =SUM(CK18:CV18) | JZ18: =SUM(CW18:HU18) | KG18: =B18 | KH18: =AR18
JF19: =AP19 | JG19: =SUM(Z19:AK19) | JH19: =SUM(AL19:AP19) | JI19: =SUM(C19:AP19) | JR19: =A19 | JS19: =SUM(C19:AP19) | JU19: =SUM(AT19:AZ19) | JV19: =SUM(BA19:BL19) | JW19: =SUM(BM19:BX19) | JX19: =SUM(BY19:CJ19) | JY19: =SUM(CK19:CV19) | JZ19: =SUM(CW19:HU19) | KG19: =B19 | KH19: =AR19
A20: TOTAL RECEITAS REAL (+) | B20: =SUM(C20:AP20) | C20: =SUM(C8+C9+C15+C18) | D20: =SUM(D8+D9+D15+D18) | E20: =SUM(E8+E9+E15+E18) | F20: =SUM(F8+F9+F12+F15+F18) | G20: =SUM(G8+G9+G12+G15+G18) | H20: =SUM(H8+H9+H12+H15+H18) | I20: =SUM(I8+I9+I12+I15+I18) | J20: =SUM(J8+J9+J15+J18) | K20: =SUM(K8+K9+K15+K18) | L20: =SUM(L8+L9+L15+L18) | M20: =SUM(M8+M9+M15+M18) | N20: =SUM(N8+N9+N15+N18) | O20: =SUM(O8+O9+O15+O18) | P20: =SUM(P8+P9+P15+P18) | Q20: =SUM(Q8+Q9+Q15+Q18) | ... AP20: =SUM(AP8+AP9+AP15+AP18) | AR20: =SUM(AT20:HU20) | AT20: =SUM(AT8+AT9+AT15+AT18) | AU20: =SUM(AU8+AU9+AU15+AU18) | AV20: =SUM(AV8+AV9+AV15+AV18) | AW20: =SUM(AW8+AW9+AW15+AW18) | AX20: =SUM(AX8+AX9+AX15+AX18) | AY20: =SUM(AY8+AY9+AY15+AY18) | AZ20: =SUM(AZ8+AZ9+AZ15+AZ18) | BA20: =SUM(BA8+BA9+BA15+BA18) | ... HU20: =SUM(HU8+HU9+HU15+HU18) | JF20: =AP20 | JG20: =SUM(Z20:AK20) | JH20: =SUM(AL20:AP20) | JI20: =SUM(C20:AP20) | JM20: 2140511.6 | JR20: =A20 | JS20: =SUM(C20:AP20) | JU20: =SUM(AT20:AZ20) | JV20: =SUM(BA20:BL20) | JW20: =SUM(BM20:BX20) | JX20: =SUM(BY20:CJ20) | JY20: =SUM(CK20:CV20) | JZ20: =SUM(CW20:HU20) | KG20: =B20 | KH20: =AR20
A21: TOTAL DE RECEITAS + PREVISÃO VENDAS | B21: =SUM(C21:AP21) | C21: =C12+C20 | D21: =D12+D20 | E21: =E12+E20 | F21: =F12+F20 | G21: =G12+G20 | H21: =H12+H20 | I21: =I12+I20 | J21: =J12+J9+J18+J15+J8 | K21: =K12+K9+K18+K15+K8 | L21: =L12+L9+L18+L15+L8 | M21: =M12+M9+M18+M15+M8 | N21: =N12+N9+N18+N15+N8 | O21: =O12+O9+O18+O15+O8 | P21: =P12+P9+P18+P15+P8 | Q21: =Q12+Q9+Q18+Q15+Q8 | ... AP21: =AP12+AP9+AP18+AP15+AP8 | AR21: =SUM(AT21:HU21) | AT21: =AT12+AT9+AT18+AT15+AT8 | AU21: =AU12+AU9+AU18+AU15+AU8 | AV21: =AV12+AV9+AV18+AV15+AV8 | AW21: =AW12+AW9+AW18+AW15+AW8 | AX21: =AX12+AX9+AX18+AX15+AX8 | AY21: =AY12+AY9+AY18+AY15+AY8 | AZ21: =AZ12+AZ9+AZ18+AZ15+AZ8 | BA21: =BA12+BA9+BA18+BA15+BA8 | ... HU21: =HU12+HU9+HU18+HU15+HU8 | JF21: =AP21 | JG21: =SUM(Z21:AK21) | JH21: =SUM(AL21:AP21) | JI21: =SUM(C21:AP21) | JM21: 2693524.8 | JR21: =A21 | JS21: =SUM(C21:AP21) | JU21: =SUM(AT21:AZ21) | JV21: =SUM(BA21:BL21) | JW21: =SUM(BM21:BX21) | JX21: =SUM(BY21:CJ21) | JY21: =SUM(CK21:CV21) | JZ21: =SUM(CW21:HU21) | KG21: =B21 | KH21: =AR21
JF22: =AP22 | JG22: =SUM(Z22:AK22) | JH22: =SUM(AL22:AP22) | JI22: =SUM(C22:AP22) | KG22: =B22 | KH22: =AR22
A23: DESPESAS OPERACIONAIS | JF23: =AP23 | JG23: =SUM(Z23:AK23) | JH23: =SUM(AL23:AP23) | JI23: =SUM(C23:AP23) | KG23: =B23 | KH23: =AR23
A24: DESPESAS COMERCIAIS(-) | JF24: =AP24 | JG24: =SUM(Z24:AK24) | JH24: =SUM(AL24:AP24) | JI24: =SUM(C24:AP24) | KG24: =B24 | KH24: =AR24
A25: Comissões S/ Venda (Equipe Interna) | B25: =SUM(C25:AP25) | AC25: =-128438.23-228.84 | AD25: -86736.99 | AE25: -82255.25 | AF25: -80040.85 | AG25: =-82521.74-1070.23 | AH25: =-114789.41-1258.17+78352.42 | AI25: =-37646.35-993.8 | AJ25: =-62577.85-603.53+41382.42 | AK25: =-37057.07-2155.37 | AL25: -87950.28 | AM25: =-80793.74-4080.62 | AN25: -59242.37 | AO25: =-85591.51-2480.85 | AP25: =-40733.2-1610.72 | AR25: =SUM(AT25:HU25) | AT25: -28685.08 | AU25: -28685.08 | AV25: -28685.08 | AW25: -28685.08 | AX25: -28685.08 | AY25: -28685.08 | AZ25: -28685.08 | BA25: -28685.08 | BB25: -28685.08 | BC25: -28685.08 | BD25: -28685.08 | BE25: -28685.08 | BF25: -28685.08 | BG25: -28685.08 | BH25: -28685.08 | BI25: -28685.08 | BJ25: -28685.08 | BK25: -28685.08 | BL25: -28685.08 | BM25: -28685.08 | BN25: -28685.08 | BO25: -28685.08 | BP25: -28685.08 | BQ25: -28685.08 | BR25: -28685.08 | BS25: -28685.08 | BT25: -28685.08 | BU25: -28685.08 | BV25: -28685.08 | BW25: -28685.08 | BX25: -28685.08 | BY25: -28685.08 | BZ25: -28685.08 | CA25: -15000 | CB25: -15000 | CC25: -15000 | CD25: -15000 | CE25: -15000 | CF25: -15000 | CG25: -15000 | CH25: -15000 | CI25: -15000 | CJ25: -15000 | CK25: -15000 | CL25: -15000 | CM25: -15000 | CN25: -15000 | CO25: -15000 | CP25: -15000 | CQ25: -15000 | CR25: -15000 | CS25: -15000 | CT25: -15000 | CU25: -15000 | CV25: -15000 | CW25: -15000 | CX25: -15000 | CY25: -15000 | CZ25: -15000 | DA25: -15000 | DB25: -15000 | DC25: -15000 | DD25: -15000 | DE25: -15000 | DF25: -15000 | DG25: -15000 | DH25: -15000 | DI25: -15000 | DJ25: -15000 | DK25: -15000 | DL25: -15000 | DM25: -15000 | DN25: -15000 | DO25: -15000 | DP25: -15000 | DQ25: -15000 | DS25: 0 | DT25: 0 | DU25: 0 | DV25: 0 | DW25: 0 | DX25: 0 | DY25: 0 | DZ25: 0 | EA25: 0 | EB25: 0 | EC25: 0 | ED25: 0 | EE25: 0 | EF25: 0 | EG25: 0 | EH25: 0 | EI25: 0 | EJ25: 0 | EK25: 0 | EL25: 0 | EM25: 0 | EN25: 0 | EO25: 0 | EP25: 0 | EQ25: 0 | ER25: 0 | ES25: 0 | ET25: 0 | EU25: 0 | EV25: 0 | EW25: 0 | EX25: 0 | EY25: 0 | EZ25: 0 | FA25: 0 | FB25: 0 | FC25: 0 | FD25: 0 | FE25: 0 | FF25: 0 | FG25: 0 | FH25: 0 | FI25: 0 | FJ25: 0 | FK25: 0 | FL25: 0 | FM25: 0 | FN25: 0 | FO25: 0 | FP25: 0 | FQ25: 0 | FR25: 0 | FS25: 0 | FT25: 0 | FU25: 0 | FV25: 0 | FW25: 0 | FX25: 0 | FY25: 0 | FZ25: 0 | GA25: 0 | GB25: 0 | GC25: 0 | GD25: 0 | GE25: 0 | GF25: 0 | GG25: 0 | GH25: 0 | GI25: 0 | GJ25: 0 | GK25: 0 | GL25: 0 | GM25: 0 | GN25: 0 | GO25: 0 | GP25: 0 | GQ25: 0 | GR25: 0 | GS25: 0 | GT25: 0 | GU25: 0 | GV25: 0 | GW25: 0 | GX25: 0 | GY25: 0 | GZ25: 0 | HA25: 0 | HB25: 0 | HC25: 0 | HD25: 0 | HE25: 0 | HF25: 0 | HG25: 0 | HH25: 0 | HI25: 0 | HJ25: 0 | HK25: 0 | HL25: 0 | HM25: 0 | HN25: 0 | HO25: 0 | HP25: 0 | HQ25: 0 | HR25: 0 | HS25: 0 | HT25: 0 | HU25: 0 | JF25: =AP25 | JG25: =SUM(Z25:AK25) | JH25: =SUM(AL25:AP25) | JI25: =SUM(C25:AP25) | JM25: -28685.08 | JS25: =+JS9+JS12 | JU25: =+JU9+JU12 | JV25: =+JV9+JV12 | JW25: =+JW9+JW12 | JX25: =+JX9+JX12 | JY25: =+JY9+JY12 | JZ25: =+JZ9+JZ12 | KG25: =B25 | KH25: =AR25
A26: Stand de Venda - Manutenção | B26: =SUM(C26:AP26) | W26: -34442.6 | X26: -422668.9 | Y26: -260275.15 | Z26: -364851.06 | AA26: -241871.81 | AB26: -456303.01 | AC26: =-66426.55-83395.55-107752.3 | AD26: -81306.34 | AE26: -75796.13 | AF26: -59026.11 | AG26: -44076.02 | AH26: -65441.81 | AI26: -74949.34 | AJ26: -74150.16 | AK26: =-81019.72+17900 | AL26: -79367.71 | AM26: -76750.58 | AN26: -65331.12 | AO26: -98723.83 | AP26: -70580.67 | AR26: =SUM(AT26:HU26) | AT26: -55000 | AU26: -55000 | AV26: -55000 | AW26: -55000 | AX26: -55000 | AY26: -55000 | AZ26: -55000 | BA26: -55000 | BB26: -55000 | BC26: -55000 | BD26: -55000 | BE26: -55000 | BF26: -55000 | BG26: -55000 | BH26: -55000 | BI26: -55000 | BJ26: -55000 | BK26: -55000 | BL26: -55000 | BM26: -55000 | BN26: -55000 | BO26: -55000 | BP26: -55000 | BQ26: 0 | BR26: 0 | BS26: 0 | BT26: 0 | BU26: 0 | BV26: 0 | BW26: 0 | BX26: 0 | BY26: 0 | BZ26: 0 | CA26: 0 | CB26: 0 | CC26: 0 | CD26: 0 | CE26: 0 | CF26: 0 | CG26: 0 | CH26: 0 | CI26: 0 | CJ26: 0 | CK26: 0 | CL26: 0 | CM26: 0 | CN26: 0 | CO26: 0 | CP26: 0 | CQ26: 0 | CR26: 0 | CS26: 0 | CT26: 0 | CU26: 0 | CV26: 0 | CW26: 0 | CX26: 0 | CY26: 0 | CZ26: 0 | DA26: 0 | DB26: 0 | DC26: 0 | DD26: 0 | DE26: 0 | DF26: 0 | DG26: 0 | DH26: 0 | DI26: 0 | DJ26: 0 | DK26: 0 | DL26: 0 | DM26: 0 | DN26: 0 | DO26: 0 | DP26: 0 | DQ26: 0 | DR26: 0 | DS26: 0 | DT26: 0 | DU26: 0 | DV26: 0 | DW26: 0 | DX26: 0 | DY26: 0 | DZ26: 0 | EA26: 0 | EB26: 0 | EC26: 0 | ED26: 0 | EE26: 0 | EF26: 0 | EG26: 0 | EH26: 0 | EI26: 0 | EJ26: 0 | EK26: 0 | EL26: 0 | EM26: 0 | EN26: 0 | EO26: 0 | EP26: 0 | EQ26: 0 | ER26: 0 | ES26: 0 | ET26: 0 | EU26: 0 | EV26: 0 | EW26: 0 | EX26: 0 | EY26: 0 | EZ26: 0 | FA26: 0 | FB26: 0 | FC26: 0 | FD26: 0 | FE26: 0 | FF26: 0 | FG26: 0 | FH26: 0 | FI26: 0 | FJ26: 0 | FK26: 0 | FL26: 0 | FM26: 0 | FN26: 0 | FO26: 0 | FP26: 0 | FQ26: 0 | FR26: 0 | FS26: 0 | FT26: 0 | FU26: 0 | FV26: 0 | FW26: 0 | FX26: 0 | FY26: 0 | FZ26: 0 | GA26: 0 | GB26: 0 | GC26: 0 | GD26: 0 | GE26: 0 | GF26: 0 | GG26: 0 | GH26: 0 | GI26: 0 | GJ26: 0 | GK26: 0 | GL26: 0 | GM26: 0 | GN26: 0 | GO26: 0 | GP26: 0 | GQ26: 0 | GR26: 0 | GS26: 0 | GT26: 0 | GU26: 0 | GV26: 0 | GW26: 0 | GX26: 0 | GY26: 0 | GZ26: 0 | HA26: 0 | HB26: 0 | HC26: 0 | HD26: 0 | HE26: 0 | HF26: 0 | HG26: 0 | HH26: 0 | HI26: 0 | HJ26: 0 | HK26: 0 | HL26: 0 | HM26: 0 | HN26: 0 | HO26: 0 | HP26: 0 | HQ26: 0 | HR26: 0 | HS26: 0 | HT26: 0 | HU26: 0 | JF26: =AP26 | JG26: =SUM(Z26:AK26) | JH26: =SUM(AL26:AP26) | JI26: =SUM(C26:AP26) | JM26: -55000 | KG26: =B26 | KH26: =AR26
A27: Marketing | B27: =SUM(C27:AP27) | W27: -32159.95 | X27: -30740 | Y27: -18988.62 | Z27: -196816.01 | AA27: -308461.65 | AB27: -387396.3 | AC27: -264220.34 | AD27: -187387.35 | AE27: -142662.13 | AF27: =-121163.48+959.8 | AG27: =-101944.3+959.8 | AH27: =-94040.76-9315.02 | AI27: -184088.23 | AJ27: -148907.24 | AK27: =-148676.77-17900 | AL27: -280720.57 | AM27: -80116.73 | AN27: -140928.2 | AO27: -132699.9 | AP27: -161932.68 | AR27: =SUM(AT27:HU27) | AT27: -166659.27 | AU27: -166659.27 | AV27: -166659.27 | AW27: -166659.27 | AX27: -166659.27 | AY27: -166659.27 | AZ27: -166659.27 | BA27: -83329.635 | BB27: -83329.635 | BC27: -83329.635 | BD27: -83329.635 | BE27: -83329.635 | BF27: -83329.635 | BG27: -83329.635 | BH27: -83329.635 | BI27: -83329.635 | BJ27: -83329.635 | BK27: -83329.635 | BL27: -83329.635 | BM27: -83329.635 | BN27: -83329.635 | BO27: -83329.635 | BP27: -83329.635 | BQ27: -83329.635 | BR27: -83329.635 | BS27: -83329.635 | BT27: -83329.635 | BU27: -83329.635 | BV27: -83329.635 | BW27: -83329.635 | BX27: -83329.635 | BY27: -83329.635 | BZ27: -83329.635 | CA27: -83329.635 | CB27: -83329.635 | CC27: -83329.635 | CD27: -83329.635 | CE27: -83329.635 | CF27: -83329.635 | CG27: -83329.635 | CH27: -83329.635 | CI27: -83329.635 | CJ27: -83329.635 | CK27: -83329.635 | CL27: -83329.635 | CM27: -83329.635 | CN27: -83329.635 | CO27: -83329.635 | CP27: -83329.635 | CQ27: -83329.635 | CR27: -83329.635 | CS27: -83329.635 | CT27: -83329.635 | CU27: -83329.635 | CV27: -83329.635 | CW27: -83329.635 | CX27: -83329.635 | CY27: -83329.635 | CZ27: -83329.635 | DA27: -83329.635 | DB27: -83329.635 | DC27: -83329.635 | DD27: -83329.635 | DE27: -83329.635 | DF27: -83329.635 | DG27: -83329.635 | DH27: -83329.635 | DI27: -83329.635 | DS27: 0 | DT27: 0 | DU27: 0 | DV27: 0 | DW27: 0 | DX27: 0 | DY27: 0 | DZ27: 0 | EA27: 0 | EC27: 0 | ED27: 0 | EE27: 0 | EF27: 0 | EG27: 0 | EH27: 0 | EI27: 0 | EJ27: 0 | EK27: 0 | EL27: 0 | EM27: 0 | EN27: 0 | EO27: 0 | EP27: 0 | EQ27: 0 | ER27: 0 | ES27: 0 | ET27: 0 | EU27: 0 | EV27: 0 | EW27: 0 | EX27: 0 | EY27: 0 | EZ27: 0 | FA27: 0 | FB27: 0 | FC27: 0 | FD27: 0 | FE27: 0 | FF27: 0 | FG27: 0 | FH27: 0 | FI27: 0 | FJ27: 0 | FK27: 0 | FL27: 0 | FM27: 0 | FN27: 0 | FO27: 0 | FP27: 0 | FQ27: 0 | FR27: 0 | FS27: 0 | FT27: 0 | FU27: 0 | FV27: 0 | FW27: 0 | FX27: 0 | FY27: 0 | FZ27: 0 | GA27: 0 | GB27: 0 | GC27: 0 | GD27: 0 | GE27: 0 | GF27: 0 | GG27: 0 | GH27: 0 | GI27: 0 | GJ27: 0 | GK27: 0 | GL27: 0 | GM27: 0 | GN27: 0 | GO27: 0 | GP27: 0 | GQ27: 0 | GR27: 0 | GS27: 0 | GT27: 0 | GU27: 0 | GV27: 0 | GW27: 0 | GX27: 0 | GY27: 0 | GZ27: 0 | HA27: 0 | HB27: 0 | HC27: 0 | HD27: 0 | HE27: 0 | HF27: 0 | HG27: 0 | HH27: 0 | HI27: 0 | HJ27: 0 | HK27: 0 | HL27: 0 | HM27: 0 | HN27: 0 | HO27: 0 | HP27: 0 | HQ27: 0 | HR27: 0 | HS27: 0 | HT27: 0 | HU27: 0 | JF27: =AP27 | JG27: =SUM(Z27:AK27) | JH27: =SUM(AL27:AP27) | JI27: =SUM(C27:AP27) | JM27: -166659.27 | KG27: =B27 | KH27: =AR27
B28: =SUM(C28:AP28) | AR28: =SUM(AT28:HU28) | DL28: 0 | DM28: 0 | DN28: 0 | DO28: 0 | DP28: 0 | DQ28: 0 | DR28: 0 | DS28: 0 | DT28: 0 | DU28: 0 | DV28: 0 | DW28: 0 | DX28: 0 | DY28: 0 | DZ28: 0 | EA28: 0 | EB28: 0 | EC28: 0 | ED28: 0 | EE28: 0 | EF28: 0 | EG28: 0 | EH28: 0 | EI28: 0 | EJ28: 0 | EK28: 0 | EL28: 0 | EM28: 0 | EN28: 0 | EO28: 0 | EP28: 0 | EQ28: 0 | ER28: 0 | ES28: 0 | ET28: 0 | EU28: 0 | EV28: 0 | EW28: 0 | EX28: 0 | EY28: 0 | EZ28: 0 | FA28: 0 | FB28: 0 | FC28: 0 | FD28: 0 | FE28: 0 | FF28: 0 | FG28: 0 | FH28: 0 | FI28: 0 | FJ28: 0 | FK28: 0 | FL28: 0 | FM28: 0 | FN28: 0 | FO28: 0 | FP28: 0 | FQ28: 0 | FR28: 0 | FS28: 0 | FT28: 0 | FU28: 0 | FV28: 0 | FW28: 0 | FX28: 0 | FY28: 0 | FZ28: 0 | GA28: 0 | GB28: 0 | GC28: 0 | GD28: 0 | GE28: 0 | GF28: 0 | GG28: 0 | GH28: 0 | GI28: 0 | GJ28: 0 | GK28: 0 | GL28: 0 | GM28: 0 | GN28: 0 | GO28: 0 | GP28: 0 | GQ28: 0 | GR28: 0 | GS28: 0 | GT28: 0 | GU28: 0 | GV28: 0 | GW28: 0 | GX28: 0 | GY28: 0 | GZ28: 0 | HA28: 0 | HB28: 0 | HC28: 0 | HD28: 0 | HE28: 0 | HF28: 0 | HG28: 0 | HH28: 0 | HI28: 0 | HJ28: 0 | HK28: 0 | HL28: 0 | HM28: 0 | HN28: 0 | HO28: 0 | HP28: 0 | HQ28: 0 | HR28: 0 | HS28: 0 | HT28: 0 | HU28: 0 | JF28: =AP28 | JG28: =SUM(Z28:AK28) | JH28: =SUM(AL28:AP28) | JI28: =SUM(C28:AP28) | KG28: =B28 | KH28: =AR28
A29: Subtotal | B29: =SUM(C29:AP29) | C29: =SUM(C25:C28) | D29: =SUM(D25:D28) | E29: =SUM(E25:E28) | F29: =SUM(F25:F28) | G29: =SUM(G25:G28) | H29: =SUM(H25:H28) | I29: =SUM(I25:I28) | J29: =SUM(J25:J28) | ... AP29: =SUM(AP25:AP28) | AR29: =SUM(AT29:HU29) | AT29: =SUM(AT25:AT28) | AU29: =SUM(AU25:AU28) | AV29: =SUM(AV25:AV28) | AW29: =SUM(AW25:AW28) | AX29: =SUM(AX25:AX28) | AY29: =SUM(AY25:AY28) | AZ29: =SUM(AZ25:AZ28) | BA29: =SUM(BA25:BA28) | ... HU29: =SUM(HU25:HU28) | JF29: =AP29 | JG29: =SUM(Z29:AK29) | JH29: =SUM(AL29:AP29) | JI29: =SUM(C29:AP29) | JM29: -250344.35 | KG29: =B29 | KH29: =AR29
JF30: =AP30 | JG30: =SUM(Z30:AK30) | JH30: =SUM(AL30:AP30) | JI30: =SUM(C30:AP30) | KG30: =B30 | KH30: =AR30
A31: ITBI + IPTU ESTOQUE(-) | JF31: =AP31 | JG31: =SUM(Z31:AK31) | JH31: =SUM(AL31:AP31) | JI31: =SUM(C31:AP31) | KG31: =B31 | KH31: =AR31
A32: ITBI | B32: =SUM(C32:AP32) | AD32: =-425723.20325 | AE32: -169878.95 | AF32: -233674.3 | AG32: -164053.77 | AH32: -88145.01 | AI32: -72316.23 | AJ32: -116408.21 | AK32: -93487.63 | AL32: -225000.78 | AM32: -144626.49 | AN32: -113015.4 | AO32: -73115.61 | AP32: -100151.9 | AR32: =SUM(AT32:HU32) | AT32: =-(B8+B32)/3 | AU32: =AT32 | AV32: =AU32 | AW32: 0 | AX32: 0 | AY32: 0 | AZ32: 0 | BA32: 0 | BB32: 0 | BC32: 0 | BD32: 0 | BE32: 0 | BF32: 0 | BG32: 0 | BH32: 0 | BI32: 0 | BJ32: 0 | BK32: 0 | BL32: 0 | BM32: 0 | BN32: 0 | BO32: 0 | BP32: 0 | BQ32: 0 | BR32: 0 | BS32: 0 | BT32: 0 | BU32: 0 | BV32: 0 | BW32: 0 | BX32: 0 | BY32: 0 | BZ32: 0 | CA32: 0 | CB32: 0 | CC32: 0 | CD32: 0 | CE32: 0 | CF32: 0 | CG32: 0 | CH32: 0 | CI32: 0 | CJ32: 0 | CK32: 0 | CL32: 0 | CM32: 0 | CN32: 0 | CO32: 0 | CP32: 0 | CQ32: 0 | CR32: 0 | CS32: 0 | CT32: 0 | CU32: 0 | CV32: 0 | CW32: 0 | CX32: 0 | CY32: 0 | CZ32: 0 | DA32: 0 | DB32: 0 | DC32: 0 | DD32: 0 | DE32: 0 | DF32: 0 | DG32: 0 | DH32: 0 | DI32: 0 | DJ32: 0 | DK32: 0 | DL32: 0 | DM32: 0 | DN32: 0 | DO32: 0 | DP32: 0 | DQ32: 0 | DR32: 0 | DS32: 0 | DT32: 0 | DU32: 0 | DV32: 0 | DW32: 0 | DX32: 0 | DY32: 0 | DZ32: 0 | EA32: 0 | EB32: 0 | EC32: 0 | ED32: 0 | EE32: 0 | EF32: 0 | EG32: 0 | EH32: 0 | EI32: 0 | EJ32: 0 | EK32: 0 | EL32: 0 | EM32: 0 | EN32: 0 | EO32: 0 | EP32: 0 | EQ32: 0 | ER32: 0 | ES32: 0 | ET32: 0 | EU32: 0 | EV32: 0 | EW32: 0 | EX32: 0 | EY32: 0 | EZ32: 0 | FA32: 0 | FB32: 0 | FC32: 0 | FD32: 0 | FE32: 0 | FF32: 0 | FG32: 0 | FH32: 0 | FI32: 0 | FJ32: 0 | FK32: 0 | FL32: 0 | FM32: 0 | FN32: 0 | FO32: 0 | FP32: 0 | FQ32: 0 | FR32: 0 | FS32: 0 | FT32: 0 | FU32: 0 | FV32: 0 | FW32: 0 | FX32: 0 | FY32: 0 | FZ32: 0 | GA32: 0 | GB32: 0 | GC32: 0 | GD32: 0 | GE32: 0 | GF32: 0 | GG32: 0 | GH32: 0 | GI32: 0 | GJ32: 0 | GK32: 0 | GL32: 0 | GM32: 0 | GN32: 0 | GO32: 0 | GP32: 0 | GQ32: 0 | GR32: 0 | GS32: 0 | GT32: 0 | GU32: 0 | GV32: 0 | GW32: 0 | GX32: 0 | GY32: 0 | GZ32: 0 | HA32: 0 | HB32: 0 | HC32: 0 | HD32: 0 | HE32: 0 | HF32: 0 | HG32: 0 | HH32: 0 | HI32: 0 | HJ32: 0 | HK32: 0 | HL32: 0 | HM32: 0 | HN32: 0 | HO32: 0 | HP32: 0 | HQ32: 0 | HR32: 0 | HS32: 0 | HT32: 0 | HU32: 0 | JF32: =AP32 | JG32: =SUM(Z32:AK32) | JH32: =SUM(AL32:AP32) | JI32: =SUM(C32:AP32) | JM32: -131508.27 | KG32: =B32 | KH32: =AR32
A33: IPTU Estoque | B33: =SUM(C33:AP33) | AE33: -63859.04 | AF33: -62215.4 | AG33: -62215.4 | AH33: -60545.9 | AI33: -61966.65 | AJ33: -58978.75 | AK33: -56594.14 | AN33: -38399.02 | AO33: -38162.09 | AP33: -37873.25 | AR33: =SUM(AT33:HU33) | AT33: -29841 | AU33: -29473.5 | AV33: -29106 | AW33: -28738.5 | AX33: -28371 | AY33: -28003.5 | AZ33: -27636 | BA33: -27268.5 | BB33: -26901 | BC33: -26533.5 | BD33: -26166 | BE33: -25798.5 | BF33: -25431 | BG33: -25063.5 | BH33: -98784 | BI33: -97314 | BJ33: -95844 | BK33: -94374 | BL33: -92904 | BM33: -91434 | BN33: -89964 | BO33: -88494 | BP33: -87024 | BQ33: -85554 | BR33: -84084 | BS33: -82614 | BT33: -81144 | BU33: -79674 | BV33: -78204 | BW33: -76734 | BX33: -75264 | BY33: -73794 | BZ33: -72324 | CA33: -70854 | CB33: -69384 | CC33: -67914 | CD33: -66444 | CE33: -64974 | CF33: -63504 | CG33: -62034 | CH33: -60564 | CI33: -59094 | CJ33: -57624 | CK33: -56154 | CL33: -54684 | CM33: -53214 | CN33: -51744 | CO33: -50274 | CP33: -48804 | CQ33: -47334 | CR33: -45864 | CS33: -44394 | CT33: -42924 | CU33: -41454 | CV33: -39984 | CW33: -38514 | CX33: -37044 | CY33: -35574 | CZ33: -34104 | DA33: -32634 | DB33: -31164 | DC33: -29694 | DD33: -28224 | DE33: -26754 | DF33: -25284 | DG33: -23814 | DH33: -22344 | DI33: -20874 | DJ33: -19404 | DK33: -17934 | DL33: -16464 | DM33: -14994 | DN33: -13524 | DO33: -12054 | DP33: -10584 | DQ33: -9114 | DR33: -7644 | DS33: -6174 | DT33: -4704 | DU33: -3234 | DV33: -1764 | DW33: -294 | DX33: 0 | DY33: 0 | DZ33: 0 | EA33: 0 | EB33: 0 | EC33: 0 | ED33: 0 | EE33: 0 | EF33: 0 | EG33: 0 | EH33: 0 | EI33: 0 | GU33: 0 | GV33: 0 | GW33: 0 | GX33: 0 | GY33: 0 | GZ33: 0 | HA33: 0 | HB33: 0 | HC33: 0 | HD33: 0 | HE33: 0 | HF33: 0 | HG33: 0 | HH33: 0 | HI33: 0 | HJ33: 0 | HK33: 0 | HL33: 0 | HM33: 0 | HN33: 0 | HO33: 0 | HP33: 0 | HQ33: 0 | HR33: 0 | HS33: 0 | HT33: 0 | HU33: 0 | JF33: =AP33 | JG33: =SUM(Z33:AK33) | JH33: =SUM(AL33:AP33) | JI33: =SUM(C33:AP33) | JM33: -30502.5 | KG33: =B33 | KH33: =AR33
A34: Condominio Estoque | B34: =SUM(C34:AP34) | AR34: =SUM(AT34:HU34) | AT34: 0 | AU34: 0 | AV34: 0 | AW34: 0 | AX34: 0 | AY34: 0 | AZ34: 0 | BA34: 0 | BB34: 0 | BC34: 0 | BD34: 0 | BE34: 0 | BF34: 0 | BG34: 0 | BH34: -336000 | BI34: -331000 | BJ34: -326000 | BK34: -321000 | BL34: -316000 | BM34: -311000 | BN34: -306000 | BO34: -301000 | BP34: -296000 | BQ34: -291000 | BR34: -286000 | BS34: -281000 | BT34: -276000 | BU34: -271000 | BV34: -266000 | BW34: -261000 | BX34: -256000 | BY34: -251000 | BZ34: -246000 | CA34: -241000 | CB34: -236000 | CC34: -231000 | CD34: -226000 | CE34: -221000 | CF34: -216000 | CG34: -211000 | CH34: -206000 | CI34: -201000 | CJ34: -196000 | CK34: -191000 | CL34: -186000 | CM34: -181000 | CN34: -176000 | CO34: -171000 | CP34: -166000 | CQ34: -161000 | CR34: -109200 | CS34: -105700 | CT34: -102200 | CU34: -98700 | CV34: -95200 | CW34: -91700 | CX34: -88200 | CY34: -84700 | CZ34: -81200 | DA34: -77700 | DB34: -74200 | DC34: -70700 | DD34: -67200 | DE34: -63700 | DF34: -60200 | DG34: -56700 | DH34: -53200 | DI34: -49700 | DJ34: -46200 | DK34: -42700 | DL34: -39200 | DM34: -35700 | DN34: -32200 | DO34: -28700 | DP34: -25200 | DQ34: -21700 | DR34: -18200 | DS34: -14700 | DT34: -11200 | DU34: -7700 | DV34: -4200 | DW34: -700 | DX34: 0 | DY34: 0 | DZ34: 0 | EA34: 0 | EB34: 0 | EC34: 0 | ED34: 0 | EE34: 0 | EF34: 0 | EG34: 0 | EH34: 0 | EI34: 0 | GU34: 0 | GV34: 0 | GW34: 0 | GX34: 0 | GY34: 0 | GZ34: 0 | HA34: 0 | HB34: 0 | HC34: 0 | HD34: 0 | HE34: 0 | HF34: 0 | HG34: 0 | HH34: 0 | HI34: 0 | HJ34: 0 | HK34: 0 | HL34: 0 | HM34: 0 | HN34: 0 | HO34: 0 | HP34: 0 | HQ34: 0 | HR34: 0 | HS34: 0 | HT34: 0 | HU34: 0 | JF34: =AP34 | JG34: =SUM(Z34:AK34) | JH34: =SUM(AL34:AP34) | JI34: =SUM(C34:AP34) | JM34: 0 | KG34: =B34 | KH34: =AR34
A35: Subtotal | B35: =SUM(C35:AP35) | C35: =SUM(C32:C33) | D35: =SUM(D32:D33) | E35: =SUM(E32:E33) | F35: =SUM(F32:F33) | G35: =SUM(G32:G33) | H35: =SUM(H32:H33) | I35: =SUM(I32:I33) | J35: =SUM(J32:J33) | ... R35: =SUM(R32:R33) | T35: =SUM(T32:T33) | U35: =SUM(U32:U33) | V35: =SUM(V32:V33) | W35: =SUM(W32:W33) | X35: =SUM(X32:X33) | Y35: =SUM(Y32:Y33) | Z35: =SUM(Z32:Z33) | AA35: =SUM(AA32:AA33) | ... AP35: =SUM(AP32:AP33) | AR35: =SUM(AT35:HU35) | AT35: =SUM(AT32:AT34) | AU35: =SUM(AU32:AU34) | AV35: =SUM(AV32:AV34) | AW35: =SUM(AW32:AW34) | AX35: =SUM(AX32:AX34) | AY35: =SUM(AY32:AY34) | AZ35: =SUM(AZ32:AZ34) | BA35: =SUM(BA32:BA34) | ... HU35: =SUM(HU32:HU34) | JF35: =AP35 | JG35: =SUM(Z35:AK35) | JH35: =SUM(AL35:AP35) | JI35: =SUM(C35:AP35) | JM35: -162010.77 | KG35: =B35 | KH35: =AR35
JF36: =AP36 | JG36: =SUM(Z36:AK36) | JH36: =SUM(AL36:AP36) | JI36: =SUM(C36:AP36) | KG36: =B36 | KH36: =AR36
A37: DESPESAS DE OBRA (-) | Projeto (-) | JF37: =AP37 | JG37: =SUM(Z37:AK37) | JH37: =SUM(AL37:AP37) | JI37: =SUM(C37:AP37) | KG37: =B37 | KH37: =AR37
A38: OBRA - (revisão ABRIL/26) | B38: =SUM(C38:AP38) | AC38: =-124003.31+107752.3 | AD38: -15360 | AE38: -494572.5 | AF38: -570102.18 | AG38: -1543804.4 | AH38: -1436152.9 | AI38: -1462529.7 | AJ38: =-2392797.39-19000 | AK38: =-3640788.84+55000 | AL38: =-2865171.27+29261.06 | AM38: -798176.19 | AN38: -1093169.7 | AO38: -1975027.4 | AP38: -3609373.3 | AR38: =SUM(AT38:HU38) | AT38: -6186623.5 | AU38: -6156623.5 | AV38: =-4814839.46-224972.62-137837.64 | AW38: -5312619.5 | AX38: -5169839.5 | AY38: -4677099.7 | AZ38: -4782099.7 | BA38: -2312321.5 | BB38: -2710771.5 | BC38: -2241943 | BD38: -2091426.8 | BE38: -1213525 | BF38: -2251060.7 | BG38: -743916.67 | BH38: -918916.67 | BI38: -918916.67 | BJ38: -918916.67 | BK38: -918916.67 | BL38: -1001416.7 | BM38: -1216416.7 | BN38: -1216416.7 | BO38: -2983083.3 | BP38: -2983083.3 | BQ38: -2768083.3 | JF38: =AP38 | JG38: =SUM(Z38:AK38) | JH38: =SUM(AL38:AP38) | JI38: =SUM(C38:AP38) | JM38: -3747210.9 | KG38: =B38 | KH38: =AR38
A39: Verba de pós obra | B39: =SUM(C39:AP39) | AR39: =SUM(AT39:HU39) | AT39: 0 | AU39: 0 | AV39: 0 | AW39: 0 | AX39: 0 | AY39: 0 | AZ39: 0 | BA39: 0 | BB39: 0 | BC39: 0 | BD39: 0 | BE39: 0 | BF39: 0 | BG39: 0 | BH39: 0 | BI39: 0 | BJ39: 0 | BK39: 0 | BL39: 0 | BM39: 0 | BN39: 0 | BO39: 0 | BP39: -74113.021 | BQ39: -74113.021 | BR39: -74113.021 | BS39: -74113.021 | BT39: -74113.021 | BU39: -74113.021 | BV39: -74113.021 | BW39: -74113.021 | BX39: -74113.021 | BY39: -74113.021 | BZ39: -74113.021 | CA39: -74113.021 | CB39: -74113.021 | CC39: -74113.021 | CD39: -74113.021 | CE39: -74113.021 | CF39: -74113.021 | CG39: -74113.021 | CH39: -74113.021 | CI39: -74113.021 | CJ39: -74113.021 | CK39: -74113.021 | CL39: -74113.021 | CM39: -74113.021 | JH39: =SUM(AL39:AP39) | JM39: 0 | KG39: =B39 | KH39: =AR39
A40: CONTRAPARTIDA SAAE | B40: =SUM(C40:AP40) | AR40: =SUM(AT40:HU40) | AT40: 0 | AU40: 0 | AV40: 0 | AW40: 0 | AX40: 0 | AY40: 0 | AZ40: 0 | BA40: 0 | BB40: 0 | BC40: 0 | BD40: 0 | BE40: =-1279528.22*1.05 | BF40: 0 | BG40: 0 | BH40: 0 | BI40: 0 | BJ40: 0 | BK40: 0 | BL40: 0 | BM40: 0 | BN40: 0 | BO40: 0 | BP40: 0 | BQ40: 0 | BR40: 0 | BS40: 0 | BT40: 0 | BU40: 0 | BV40: 0 | BW40: 0 | BX40: 0 | BY40: 0 | BZ40: 0 | CA40: 0 | CB40: 0 | CC40: 0 | CD40: 0 | CE40: 0 | CF40: 0 | CG40: 0 | CH40: 0 | CI40: 0 | CJ40: 0 | CK40: 0 | CL40: 0 | CM40: 0 | CN40: 0 | CO40: 0 | CP40: 0 | CQ40: 0 | CR40: 0 | CS40: 0 | CT40: 0 | CU40: 0 | CV40: 0 | CW40: 0 | CX40: 0 | CY40: 0 | CZ40: 0 | DA40: 0 | DB40: 0 | DC40: 0 | DD40: 0 | DE40: 0 | DF40: 0 | DG40: 0 | DH40: 0 | DI40: 0 | DJ40: 0 | DK40: 0 | DL40: 0 | DM40: 0 | DN40: 0 | DO40: 0 | DP40: 0 | DQ40: 0 | DR40: 0 | DS40: 0 | DT40: 0 | DU40: 0 | DV40: 0 | DW40: 0 | DX40: 0 | DY40: 0 | DZ40: 0 | EA40: 0 | EB40: 0 | EC40: 0 | ED40: 0 | EE40: 0 | EF40: 0 | EG40: 0 | EH40: 0 | EI40: 0 | EJ40: 0 | EK40: 0 | EL40: 0 | EM40: 0 | EN40: 0 | EO40: 0 | EP40: 0 | EQ40: 0 | ER40: 0 | ES40: 0 | ET40: 0 | EU40: 0 | EV40: 0 | EW40: 0 | EX40: 0 | EY40: 0 | EZ40: 0 | FA40: 0 | FB40: 0 | FC40: 0 | FD40: 0 | FE40: 0 | FF40: 0 | FG40: 0 | FH40: 0 | FI40: 0 | FJ40: 0 | FK40: 0 | FL40: 0 | FM40: 0 | FN40: 0 | FO40: 0 | FP40: 0 | FQ40: 0 | FR40: 0 | FS40: 0 | FT40: 0 | FU40: 0 | FV40: 0 | FW40: 0 | FX40: 0 | FY40: 0 | FZ40: 0 | GA40: 0 | GB40: 0 | GC40: 0 | GD40: 0 | GE40: 0 | GF40: 0 | GG40: 0 | GH40: 0 | GI40: 0 | GJ40: 0 | GK40: 0 | GL40: 0 | GM40: 0 | GN40: 0 | GO40: 0 | GP40: 0 | GQ40: 0 | GR40: 0 | GS40: 0 | GT40: 0 | GU40: 0 | GV40: 0 | GW40: 0 | GX40: 0 | GY40: 0 | GZ40: 0 | HA40: 0 | HB40: 0 | HC40: 0 | HD40: 0 | HE40: 0 | HF40: 0 | HG40: 0 | HH40: 0 | HI40: 0 | HJ40: 0 | HK40: 0 | HL40: 0 | HM40: 0 | HN40: 0 | HO40: 0 | HP40: 0 | HQ40: 0 | HR40: 0 | HS40: 0 | HT40: 0 | HU40: 0 | JF40: =AP40 | JG40: =SUM(Z40:AK40) | JH40: =SUM(AL40:AP40) | JI40: =SUM(C40:AP40) | JM40: 0 | KG40: =B40 | KH40: =AR40
JF41: =AP41 | JG41: =SUM(Z41:AK41) | JH41: =SUM(AL41:AP41) | JI41: =SUM(C41:AP41) | KG41: =B41 | KH41: =AR41
A42: INCORPORAÇÃO (-) | JF42: =AP42 | JG42: =SUM(Z42:AK42) | JH42: =SUM(AL42:AP42) | JI42: =SUM(C42:AP42) | KG42: =B42 | KH42: =AR42
A43: Incorporação | B43: =SUM(C43:AP43) | C43: -22569.84 | D43: -66761.36 | E43: -22685 | F43: -22753.06 | G43: -22784.91 | H43: -25995.64 | I43: -23082.07 | J43: -23105.15 | K43: -28144.43 | L43: -28223.13 | M43: -28269.57 | N43: -28285.85 | O43: -30358.04 | P43: -28421.11 | Q43: -51733.24 | R43: -57539.95 | S43: -30362.5 | T43: -56077.16 | U43: -30362.5 | V43: -98850 | W43: -36362.5 | X43: -645250.94 | Y43: -280557.39 | Z43: -29760.76 | AA43: =(-184611.43)+-24760.76 | AB43: -90439.16 | AC43: =-49101.24-49521.52 | AD43: -49311.19 | AE43: -34527.34 | AF43: -72132.68 | AG43: -18449.64 | AH43: =-19109.04+9315.02 | AI43: -16205.14 | AJ43: =-54116.08+19000 | AK43: -8356.98 | AL43: -7658.2 | AM43: -10641.73 | AN43: =-40182.18+30654.55 | AO43: =-63943+29012.57+24791.61 | AP43: -11728.44 | AR43: =SUM(AT43:HU43) | AT43: -8000 | AU43: -8000 | AV43: -8000 | AW43: -8000 | AX43: -8000 | AY43: -8000 | AZ43: -8000 | BA43: -8000 | BB43: -8000 | BC43: -8000 | BD43: -8000 | BE43: -8000 | BF43: -8000 | BG43: -8000 | BH43: -8000 | BI43: -8000 | BJ43: -8000 | BK43: -8000 | BL43: -8000 | BM43: -8000 | BN43: -8000 | BO43: -8000 | BP43: -8000 | BQ43: -8000 | BR43: -8000 | DY43: 0 | DZ43: 0 | EA43: 0 | EB43: 0 | EC43: 0 | ED43: 0 | EE43: 0 | EF43: 0 | EG43: 0 | EH43: 0 | EI43: 0 | EJ43: 0 | EK43: 0 | EL43: 0 | EM43: 0 | EN43: 0 | EO43: 0 | EP43: 0 | EQ43: 0 | ER43: 0 | ES43: 0 | ET43: 0 | EU43: 0 | EV43: 0 | EW43: 0 | EX43: 0 | EY43: 0 | EZ43: 0 | FA43: 0 | FB43: 0 | FC43: 0 | FD43: 0 | FE43: 0 | FF43: 0 | FG43: 0 | FH43: 0 | FI43: 0 | FJ43: 0 | FK43: 0 | FL43: 0 | FM43: 0 | FN43: 0 | FO43: 0 | FP43: 0 | FQ43: 0 | FR43: 0 | FS43: 0 | FT43: 0 | FU43: 0 | FV43: 0 | FW43: 0 | FX43: 0 | FY43: 0 | FZ43: 0 | GA43: 0 | GB43: 0 | GC43: 0 | GD43: 0 | GE43: 0 | GF43: 0 | GG43: 0 | GH43: 0 | GI43: 0 | GJ43: 0 | GK43: 0 | GL43: 0 | GM43: 0 | GN43: 0 | GO43: 0 | GP43: 0 | GQ43: 0 | GR43: 0 | GS43: 0 | GT43: 0 | GU43: 0 | GV43: 0 | GW43: 0 | GX43: 0 | GY43: 0 | GZ43: 0 | HA43: 0 | HB43: 0 | HC43: 0 | HD43: 0 | HE43: 0 | HF43: 0 | HG43: 0 | HH43: 0 | HI43: 0 | HJ43: 0 | HK43: 0 | HL43: 0 | HM43: 0 | HN43: 0 | HO43: 0 | HP43: 0 | HQ43: 0 | HR43: 0 | HS43: 0 | HT43: 0 | HU43: 0 | JF43: =AP43 | JG43: =SUM(Z43:AK43) | JH43: =SUM(AL43:AP43) | JI43: =SUM(C43:AP43) | JM43: -8000 | KG43: =B43 | KH43: =AR43
A44: Gerenciamento | B44: =SUM(C44:AP44) | AD44: -8000 | AE44: -8000 | AF44: -8000 | AG44: -8000 | AH44: -8000 | AI44: -8840.61 | AJ44: -8840.61 | AK44: -8840.61 | AL44: -8840.61 | AM44: -8840.61 | AN44: -8840.61 | AO44: -8840.61 | AP44: -8840.61 | AR44: =SUM(AT44:HU44) | AT44: -8840.61 | AU44: -8840.61 | AV44: -8840.61 | AW44: -8840.61 | AX44: -8840.61 | AY44: -8840.61 | AZ44: -8840.61 | BA44: -8840.61 | BB44: -8840.61 | BC44: -8840.61 | BD44: -8840.61 | BE44: -8840.61 | BF44: -8840.61 | BG44: -8840.61 | BH44: -8840.61 | BI44: -8840.61 | BJ44: -8840.61 | BK44: -8840.61 | BL44: -8840.61 | BM44: -8840.61 | BN44: -8840.61 | BO44: -8840.61 | BP44: -8840.61 | BQ44: -8840.61 | BR44: -8840.61 | BS44: -8840.61 | BT44: -8840.61 | BU44: -8840.61 | BV44: -8840.61 | BW44: -8840.61 | BX44: -8840.61 | BY44: -8840.61 | BZ44: -8840.61 | CA44: -8840.61 | CB44: -8840.61 | CC44: -8840.61 | CD44: -8840.61 | CE44: -8840.61 | CF44: -8840.61 | CG44: -8840.61 | CH44: -8840.61 | CI44: -8840.61 | CJ44: -8840.61 | CK44: -8840.61 | CL44: -8840.61 | CM44: -8840.61 | CN44: -8840.61 | DY44: 0 | DZ44: 0 | EA44: 0 | EB44: 0 | EC44: 0 | ED44: 0 | EE44: 0 | EF44: 0 | EG44: 0 | EH44: 0 | EI44: 0 | EJ44: 0 | EK44: 0 | EL44: 0 | EM44: 0 | EN44: 0 | EO44: 0 | EP44: 0 | EQ44: 0 | ER44: 0 | ES44: 0 | ET44: 0 | EU44: 0 | EV44: 0 | EW44: 0 | EX44: 0 | EY44: 0 | EZ44: 0 | FA44: 0 | FB44: 0 | FC44: 0 | FD44: 0 | FE44: 0 | FF44: 0 | FG44: 0 | FH44: 0 | FI44: 0 | FJ44: 0 | FK44: 0 | FL44: 0 | FM44: 0 | FN44: 0 | FO44: 0 | FP44: 0 | FQ44: 0 | FR44: 0 | FS44: 0 | FT44: 0 | FU44: 0 | FV44: 0 | FW44: 0 | FX44: 0 | FY44: 0 | FZ44: 0 | GA44: 0 | GB44: 0 | GC44: 0 | GD44: 0 | GE44: 0 | GF44: 0 | GG44: 0 | GH44: 0 | GI44: 0 | GJ44: 0 | GK44: 0 | GL44: 0 | GM44: 0 | GN44: 0 | GO44: 0 | GP44: 0 | GQ44: 0 | GR44: 0 | GS44: 0 | GT44: 0 | GU44: 0 | GV44: 0 | GW44: 0 | GX44: 0 | GY44: 0 | GZ44: 0 | HA44: 0 | HB44: 0 | HC44: 0 | HD44: 0 | HE44: 0 | HF44: 0 | HG44: 0 | HH44: 0 | HI44: 0 | HJ44: 0 | HK44: 0 | HL44: 0 | HM44: 0 | HN44: 0 | HO44: 0 | HP44: 0 | HQ44: 0 | HR44: 0 | HS44: 0 | HT44: 0 | HU44: 0 | JF44: =AP44 | JG44: =SUM(Z44:AK44) | JH44: =SUM(AL44:AP44) | JI44: =SUM(C44:AP44) | JM44: -8840.61 | KG44: =B44 | KH44: =AR44
JF45: =AP45 | JG45: =SUM(Z45:AK45) | JH45: =SUM(AL45:AP45) | JI45: =SUM(C45:AP45) | KG45: =B45 | KH45: =AR45
A46: DESPESAS JÚRIDICAS (-) | JF46: =AP46 | JG46: =SUM(Z46:AK46) | JH46: =SUM(AL46:AP46) | JI46: =SUM(C46:AP46) | KG46: =B46 | KH46: =AR46
A47: Despesas juridicas | B47: =SUM(C47:AP47) | AF47: =50092.5732500069-959.8 | AR47: =SUM(AT47:HU47) | AT47: 0 | AU47: 0 | AV47: 0 | AW47: 0 | AX47: 0 | AY47: 0 | AZ47: 0 | BA47: 0 | BB47: 0 | BC47: 0 | BD47: 0 | BE47: 0 | BF47: 0 | BG47: 0 | BH47: 0 | BI47: 0 | BJ47: 0 | BK47: 0 | BL47: 0 | BM47: 0 | BN47: 0 | BO47: 0 | BP47: 0 | BQ47: 0 | BR47: 0 | BS47: 0 | BT47: 0 | BU47: 0 | BV47: 0 | BW47: 0 | BX47: 0 | BY47: 0 | BZ47: 0 | CA47: 0 | CB47: 0 | CC47: 0 | CD47: 0 | CE47: 0 | CF47: 0 | CG47: 0 | CH47: 0 | CI47: 0 | CJ47: 0 | CK47: 0 | CL47: 0 | CM47: 0 | CN47: 0 | CO47: 0 | CP47: 0 | CQ47: 0 | CR47: 0 | CS47: 0 | CT47: 0 | CU47: 0 | CV47: 0 | CW47: 0 | CX47: 0 | CY47: 0 | CZ47: 0 | DA47: 0 | DB47: 0 | DC47: 0 | DD47: 0 | DE47: 0 | DF47: 0 | DG47: 0 | DH47: 0 | DI47: 0 | DJ47: 0 | DK47: 0 | DL47: 0 | DM47: 0 | DN47: 0 | DO47: 0 | DP47: 0 | DQ47: 0 | DR47: 0 | DS47: 0 | DT47: 0 | DU47: 0 | DV47: 0 | DW47: 0 | DX47: 0 | DY47: 0 | DZ47: 0 | EA47: 0 | EB47: 0 | EC47: 0 | ED47: 0 | EE47: 0 | EF47: 0 | EG47: 0 | EH47: 0 | EI47: 0 | EJ47: 0 | EK47: 0 | EL47: 0 | EM47: 0 | EN47: 0 | EO47: 0 | EP47: 0 | EQ47: 0 | ER47: 0 | ES47: 0 | ET47: 0 | EU47: 0 | EV47: 0 | EW47: 0 | EX47: 0 | EY47: 0 | EZ47: 0 | FA47: 0 | FB47: 0 | FC47: 0 | FD47: 0 | FE47: 0 | FF47: 0 | FG47: 0 | FH47: 0 | FI47: 0 | FJ47: 0 | FK47: 0 | FL47: 0 | FM47: 0 | FN47: 0 | FO47: 0 | FP47: 0 | FQ47: 0 | FR47: 0 | FS47: 0 | FT47: 0 | FU47: 0 | FV47: 0 | FW47: 0 | FX47: 0 | FY47: 0 | FZ47: 0 | GA47: 0 | GB47: 0 | GC47: 0 | GD47: 0 | GE47: 0 | GF47: 0 | GG47: 0 | GH47: 0 | GI47: 0 | GJ47: 0 | GK47: 0 | GL47: 0 | GM47: 0 | GN47: 0 | GO47: 0 | GP47: 0 | GQ47: 0 | GR47: 0 | GS47: 0 | GT47: 0 | GU47: 0 | GV47: 0 | GW47: 0 | GX47: 0 | GY47: 0 | GZ47: 0 | HA47: 0 | HB47: 0 | HC47: 0 | HD47: 0 | HE47: 0 | HF47: 0 | HG47: 0 | HH47: 0 | HI47: 0 | HJ47: 0 | HK47: 0 | HL47: 0 | HM47: 0 | HN47: 0 | HO47: 0 | HP47: 0 | HQ47: 0 | HR47: 0 | HS47: 0 | HT47: 0 | HU47: 0 | JF47: =AP47 | JG47: =SUM(Z47:AK47) | JH47: =SUM(AL47:AP47) | JI47: =SUM(C47:AP47) | JM47: 0 | KG47: =B47 | KH47: =AR47
JF48: =AP48 | JG48: =SUM(Z48:AK48) | JH48: =SUM(AL48:AP48) | JI48: =SUM(C48:AP48) | KG48: =B48 | KH48: =AR48
A49: OUTRAS DESPESAS (-) | JF49: =AP49 | JG49: =SUM(Z49:AK49) | JH49: =SUM(AL49:AP49) | JI49: =SUM(C49:AP49) | KG49: =B49 | KH49: =AR49
A50: Outras Despesas (adm) | B50: =SUM(C50:AP50) | L50: -1243.93 | O50: -339 | V50: -389 | W50: 0 | X50: -4 | Y50: -1155.21 | Z50: -148.25 | AA50: -344.9 | AB50: -459.58 | AC50: =-26826.58-250 | AD50: -6297.44 | AE50: -4312.64 | AF50: -4226.87 | AG50: -4662.58 | AH50: -4676.65 | AI50: -5244.59 | AJ50: -5086.32 | AK50: -4749.4 | AL50: -4366.28 | AM50: -4868.24 | AN50: -4811.9 | AO50: -4832.51 | AP50: -4927.16 | AR50: =SUM(AT50:HU50) | AT50: -8000 | AU50: -8000 | AV50: -8000 | AW50: -8000 | AX50: -8000 | AY50: -8000 | AZ50: -8000 | BA50: -8000 | BB50: -8000 | BC50: -8000 | BD50: -8000 | BE50: -8000 | BF50: -8000 | BG50: -8000 | BH50: -8000 | BI50: -8000 | BJ50: -8000 | BK50: -8000 | BL50: -8000 | BM50: -8000 | BN50: -8000 | BO50: -8000 | BP50: -8000 | BQ50: -8000 | BR50: -8000 | BS50: -8000 | BT50: -8000 | BU50: -8000 | BV50: -8000 | BW50: -8000 | BX50: -8000 | BY50: -8000 | BZ50: -8000 | CA50: -8000 | CB50: -8000 | CC50: -8000 | CD50: -8000 | CE50: -8000 | CF50: -8000 | CG50: -8000 | CH50: -8000 | CI50: -8000 | CJ50: -8000 | CK50: -8000 | CL50: -8000 | CM50: -8000 | CN50: -8000 | CO50: -8000 | CP50: -8000 | CQ50: -8000 | CR50: -8000 | CS50: -8000 | CT50: -8000 | CU50: -8000 | CV50: -8000 | CW50: -8000 | CX50: -8000 | CY50: -8000 | CZ50: -8000 | DA50: -8000 | DB50: -8000 | DC50: -8000 | DD50: -8000 | DE50: -8000 | DF50: -8000 | DG50: -8000 | DH50: -8000 | DI50: -8000 | DJ50: -8000 | DK50: -8000 | DL50: -8000 | DM50: -8000 | DN50: -8000 | DO50: -8000 | DP50: -8000 | DQ50: -8000 | JF50: =AP50 | JG50: =SUM(Z50:AK50) | JH50: =SUM(AL50:AP50) | JI50: =SUM(C50:AP50) | JM50: -8000 | KG50: =B50 | KH50: =AR50
JF51: =AP51 | JG51: =SUM(Z51:AK51) | JH51: =SUM(AL51:AP51) | JI51: =SUM(C51:AP51) | KG51: =B51 | KH51: =AR51
A52: TOTAL DE DESPESAS OPERACIONAIS (-) | B52: =SUM(C52:AP52) | C52: =C50+C47+C43+C38+C35+C29 | D52: =D50+D47+D43+D38+D35+D29 | E52: =E50+E47+E43+E38+E35+E29 | F52: =F50+F47+F43+F38+F35+F29 | G52: =G50+G47+G43+G38+G35+G29 | H52: =H50+H47+H43+H38+H35+H29 | I52: =I50+I47+I43+I38+I35+I29 | J52: =J50+J47+J43+J38+J35+J29 | ... AB52: =AB50+AB47+AB43+AB38+AB35+AB29 | AC52: =AC50+AC47+AC43+AC38+AC35+AC29+AC44 | AD52: =AD50+AD47+AD43+AD38+AD35+AD29+AD44 | AE52: =AE50+AE47+AE43+AE38+AE35+AE29+AE44 | AF52: =AF50+AF47+AF43+AF38+AF35+AF29+AF44 | AG52: =AG50+AG47+AG43+AG38+AG35+AG29+AG44 | AH52: =AH50+AH47+AH43+AH38+AH35+AH29+AH44 | AI52: =AI50+AI47+AI43+AI38+AI35+AI29+AI44 | AJ52: =AJ50+AJ47+AJ43+AJ38+AJ35+AJ29+AJ44 | ... AP52: =AP50+AP47+AP43+AP38+AP35+AP29+AP44 | AR52: =SUM(AT52:HU52) | AT52: =AT50+AT47+AT43+AT38+AT35+AT29+AT44+AT40+AT39 | AU52: =AU50+AU47+AU43+AU38+AU35+AU29+AU44+AU40+AU39 | AV52: =AV50+AV47+AV43+AV38+AV35+AV29+AV44+AV40+AV39 | AW52: =AW50+AW47+AW43+AW38+AW35+AW29+AW44+AW40+AW39 | AX52: =AX50+AX47+AX43+AX38+AX35+AX29+AX44+AX40+AX39 | AY52: =AY50+AY47+AY43+AY38+AY35+AY29+AY44+AY40+AY39 | AZ52: =AZ50+AZ47+AZ43+AZ38+AZ35+AZ29+AZ44+AZ40+AZ39 | BA52: =BA50+BA47+BA43+BA38+BA35+BA29+BA44+BA40+BA39 | ... HU52: =HU50+HU47+HU43+HU38+HU35+HU29+HU44+HU40+HU39 | JF52: =AP52 | JG52: =SUM(Z52:AK52) | JH52: =SUM(AL52:AP52) | JI52: =SUM(C52:AP52) | JM52: -4184406.7 | KG52: =B52 | KH52: =AR52
A53: TOTAL ACUMULADO DE DESPESAS OP.(-) | B53: =SUM(C53:AP53) | D53: =C53+D52 | E53: =D53+E52 | F53: =D53+F52 | G53: =E53+G52 | H53: =F53+H52 | I53: =G53+I52 | J53: =I53+J52 | K53: =J53+K52 | L53: =K53+L52 | M53: =L53+M52 | N53: =M53+N52 | O53: =N53+O52 | P53: =O53+P52 | Q53: =P53+Q52 | ... AP53: =AO53+AP52 | AR53: =W53+AR52 | AT53: =AP53+AT52 | AU53: =AT53+AU52 | AV53: =AU53+AV52 | AW53: =AV53+AW52 | AX53: =AW53+AX52 | AY53: =AX53+AY52 | AZ53: =AY53+AZ52 | BA53: =AZ53+BA52 | BB53: =BA53+BB52 | ... HU53: =HT53+HU52 | JF53: =AP53 | JG53: =SUM(Z53:AK53) | JH53: =SUM(AL53:AP53) | JI53: =SUM(C53:AP53) | JM53: -34156967 | KG53: =B53 | KH53: =AR53
JF54: =AP54 | JG54: =SUM(Z54:AK54) | JH54: =SUM(AL54:AP54) | JI54: =SUM(C54:AP54) | KG54: =B54 | KH54: =AR54
A55: IMPOSTOS (-) | JF55: =AP55 | JG55: =SUM(Z55:AK55) | JH55: =SUM(AL55:AP55) | JI55: =SUM(C55:AP55) | KG55: =B55 | KH55: =AR55
A56: Impostos | B56: =SUM(C56:AP56) | AC56: =-210474.96-5661 | AD56: =-120603.87-111025.76 | AE56: -112006.6 | AF56: -432705.99 | AG56: -118838.98 | AH56: -116123.91 | AI56: -354372.51 | AJ56: -173967.62 | AK56: -179418.92 | AL56: -488063.29 | AM56: -163274.46 | AN56: -135237.18 | AO56: -875555.19 | AP56: -284941.98 | AR56: =SUM(AT56:HU56) | AT56: =(AP8+AP9+AP12)*6.75%*-1 | AU56: =(AT8+AT9+AT12)*6.75%*-1 | AV56: =(AU8+AU9+AU12)*6.75%*-1 | AW56: =(AV8+AV9+AV12)*6.75%*-1 | AX56: =(AW8+AW9+AW12)*6.75%*-1 | AY56: =(AX8+AX9+AX12)*6.75%*-1 | AZ56: =(AY8+AY9+AY12)*6.75%*-1 | BA56: =(AZ8+AZ9+AZ12)*6.75%*-1 | BB56: =(BA8+BA9+BA12)*6.75%*-1 | ... DX56: =(DW8+DW9+DW12)*6.75%*-1 | DY56: =(DU8+DU9+DU12)*6.75%*-1 | DZ56: =(DY8+DY9+DY12)*6.75%*-1 | EA56: =(DZ8+DZ9+DZ12)*6.75%*-1 | EB56: =(EA8+EA9+EA12)*6.75%*-1 | EC56: =(EB8+EB9+EB12)*6.75%*-1 | ED56: =(EC8+EC9+EC12)*6.75%*-1 | EE56: =(ED8+ED9+ED12)*6.75%*-1 | EF56: =(EE8+EE9+EE12)*6.75%*-1 | EG56: =(EF8+EF9+EF12)*6.75%*-1 | ... HU56: =(HT8+HT9+HT12)*6.75%*-1 | JF56: =AP56 | JG56: =SUM(Z56:AK56) | JH56: =SUM(AL56:AP56) | JI56: =SUM(C56:AP56) | JM56: -253307.59 | KG56: =B56 | KH56: =AR56
JF57: =AP57 | JG57: =SUM(Z57:AK57) | JH57: =SUM(AL57:AP57) | JI57: =SUM(C57:AP57) | KG57: =B57 | KH57: =AR57
A58: DESAPROPRIAÇÃO (-) | JF58: =AP58 | JG58: =SUM(Z58:AK58) | JH58: =SUM(AL58:AP58) | JI58: =SUM(C58:AP58) | KG58: =B58 | KH58: =AR58
A59: Desapropriação | B59: =SUM(C59:AP59) | C59: 0 | D59: 0 | E59: 0 | F59: 0 | G59: 0 | I59: 0 | J59: 0 | K59: 0 | AG59: -2778000 | AH59: 0 | AI59: 0 | AJ59: 0 | AK59: 0 | AL59: 0 | AM59: 0 | AN59: 0 | AO59: 0 | AP59: 0 | AR59: =SUM(AT59:HU59) | AT59: 0 | AU59: 0 | AV59: 0 | AW59: 0 | AX59: 0 | AY59: 0 | AZ59: 0 | BA59: 0 | BB59: 0 | BC59: 0 | BD59: 0 | BE59: 0 | BF59: 0 | BG59: 0 | BH59: 0 | BI59: 0 | BJ59: 0 | BK59: 0 | BL59: 0 | BM59: 0 | BN59: 0 | BO59: 0 | BP59: 0 | BQ59: 0 | BR59: 0 | BS59: 0 | BT59: 0 | BU59: 0 | BV59: 0 | BW59: 0 | BX59: 0 | BY59: 0 | BZ59: 0 | CA59: 0 | CB59: 0 | CC59: 0 | CD59: 0 | CE59: 0 | CF59: 0 | CG59: 0 | CH59: 0 | CI59: 0 | CJ59: 0 | CK59: 0 | CL59: 0 | CM59: 0 | CN59: 0 | CO59: 0 | CP59: 0 | CQ59: 0 | CR59: 0 | CS59: 0 | CT59: 0 | CU59: 0 | CV59: 0 | CW59: 0 | CX59: 0 | CY59: 0 | CZ59: 0 | DA59: 0 | DB59: 0 | DC59: 0 | DD59: 0 | DE59: 0 | DF59: 0 | DG59: 0 | DH59: 0 | DI59: 0 | DJ59: 0 | DK59: 0 | DL59: 0 | DM59: 0 | DN59: 0 | DO59: 0 | DP59: 0 | DQ59: 0 | DR59: 0 | DS59: 0 | DT59: 0 | DU59: 0 | DV59: 0 | DW59: 0 | DX59: 0 | DY59: 0 | DZ59: 0 | EA59: 0 | EB59: 0 | EC59: 0 | ED59: 0 | EE59: 0 | EF59: 0 | EG59: 0 | EH59: 0 | EI59: 0 | EJ59: 0 | EK59: 0 | EL59: 0 | EM59: 0 | EN59: 0 | EO59: 0 | EP59: 0 | EQ59: 0 | ER59: 0 | ES59: 0 | ET59: 0 | EU59: 0 | EV59: 0 | EW59: 0 | EX59: 0 | EY59: 0 | EZ59: 0 | FA59: 0 | FB59: 0 | FC59: 0 | FD59: 0 | FE59: 0 | FF59: 0 | FG59: 0 | FH59: 0 | FI59: 0 | FJ59: 0 | FK59: 0 | FL59: 0 | FM59: 0 | FN59: 0 | FO59: 0 | FP59: 0 | FQ59: 0 | FR59: 0 | FS59: 0 | FT59: 0 | FU59: 0 | FV59: 0 | FW59: 0 | FX59: 0 | FY59: 0 | FZ59: 0 | GA59: 0 | GB59: 0 | GC59: 0 | GD59: 0 | GE59: 0 | GF59: 0 | GG59: 0 | GH59: 0 | GI59: 0 | GJ59: 0 | GK59: 0 | GL59: 0 | GM59: 0 | GN59: 0 | GO59: 0 | GP59: 0 | GQ59: 0 | GR59: 0 | GS59: 0 | GT59: 0 | GU59: 0 | GV59: 0 | GW59: 0 | GX59: 0 | GY59: 0 | GZ59: 0 | HA59: 0 | HB59: 0 | HC59: 0 | HD59: 0 | HE59: 0 | HF59: 0 | HG59: 0 | HH59: 0 | HI59: 0 | HJ59: 0 | HK59: 0 | HL59: 0 | HM59: 0 | HN59: 0 | HO59: 0 | HP59: 0 | HQ59: 0 | HR59: 0 | HS59: 0 | HT59: 0 | HU59: 0 | JF59: =AP59 | JG59: =SUM(Z59:AK59) | JH59: =SUM(AL59:AP59) | JI59: =SUM(C59:AP59) | JM59: 0 | KG59: =B59 | KH59: =AR59
JF60: =AP60 | JG60: =SUM(Z60:AK60) | JH60: =SUM(AL60:AP60) | JI60: =SUM(C60:AP60) | KG60: =B60 | KH60: =AR60
A61: DISTRATOS (-) | JF61: =AP61 | JG61: =SUM(Z61:AK61) | JH61: =SUM(AL61:AP61) | JI61: =SUM(C61:AP61) | KG61: =B61 | KH61: =AR61
A62: Devoluções | B62: =SUM(C62:AP62) | AD62: -138044.5 | AE62: 0 | AF62: 0 | AG62: 0 | AH62: 0 | AI62: 0 | AJ62: =-59410.58-59410.58-59359.09 | AR62: =SUM(AT62:HU62) | AT62: -91053.071 | AU62: 0 | AV62: 0 | AW62: 0 | AX62: 0 | AY62: 0 | AZ62: 0 | BA62: 0 | BB62: 0 | BC62: 0 | BD62: 0 | BE62: 0 | BF62: 0 | BG62: 0 | BH62: 0 | BI62: 0 | BJ62: 0 | BK62: 0 | BL62: 0 | BM62: 0 | BN62: 0 | BO62: 0 | BP62: 0 | BQ62: 0 | BR62: 0 | BS62: 0 | BT62: 0 | BU62: 0 | BV62: 0 | BW62: 0 | BX62: 0 | BY62: 0 | BZ62: 0 | CA62: 0 | CB62: 0 | CC62: 0 | CD62: 0 | CE62: 0 | CF62: 0 | CG62: 0 | CH62: 0 | CI62: 0 | CJ62: 0 | CK62: 0 | CL62: 0 | CM62: 0 | CN62: 0 | CO62: 0 | CP62: 0 | CQ62: 0 | CR62: 0 | CS62: 0 | CT62: 0 | CU62: 0 | CV62: 0 | CW62: 0 | CX62: 0 | CY62: 0 | CZ62: 0 | DA62: 0 | DB62: 0 | DC62: 0 | DD62: 0 | DE62: 0 | DF62: 0 | DG62: 0 | DH62: 0 | DI62: 0 | DJ62: 0 | DL62: 0 | DN62: 0 | JF62: =AP62 | JG62: =SUM(Z62:AK62) | JH62: =SUM(AL62:AP62) | JI62: =SUM(C62:AP62) | JM62: 0 | KG62: =B62 | KH62: =AR62
JF63: =AP63 | JG63: =SUM(Z63:AK63) | JH63: =SUM(AL63:AP63) | JI63: =SUM(C63:AP63) | KG63: =B63 | KH63: =AR63
A64: DISTRIBUIÇÕES (-) | JF64: =AP64 | JG64: =SUM(Z64:AK64) | JH64: =SUM(AL64:AP64) | JI64: =SUM(C64:AP64) | KG64: =B64 | KH64: =AR64
A65: Devolução de Aporte | B65: =SUM(C65:AP65) | AG65: -4000000 | AH65: 0 | AI65: 0 | AJ65: 0 | AK65: 0 | AL65: 0 | AM65: 0 | AN65: 0 | AO65: 0 | AP65: 0 | AR65: =SUM(AT65:HU65) | AT65: 0 | AU65: 0 | AV65: 0 | AW65: 0 | AX65: 0 | AY65: 0 | AZ65: 0 | BA65: -1754788.2 | BB65: =-2000000+450000 | BN65: 0 | BO65: 0 | BP65: 0 | BQ65: 0 | BR65: 0 | BS65: 0 | BT65: 0 | BU65: 0 | BV65: 0 | BW65: 0 | BX65: 0 | BY65: 0 | BZ65: 0 | CA65: 0 | CB65: 0 | CC65: 0 | CD65: 0 | CE65: 0 | CF65: 0 | CG65: 0 | CH65: 0 | CI65: 0 | CJ65: 0 | CK65: 0 | CL65: 0 | CM65: 0 | CN65: 0 | CO65: 0 | CP65: 0 | CQ65: 0 | CR65: 0 | CS65: 0 | CT65: 0 | CU65: 0 | CV65: 0 | CW65: 0 | CX65: 0 | CY65: 0 | CZ65: 0 | DA65: 0 | DB65: 0 | DC65: 0 | DD65: 0 | DE65: 0 | DF65: 0 | DG65: 0 | DH65: 0 | DI65: 0 | DJ65: 0 | DK65: 0 | DL65: 0 | DM65: 0 | DN65: 0 | DO65: 0 | DP65: 0 | DQ65: 0 | DR65: 0 | DS65: 0 | DT65: 0 | DU65: 0 | DV65: 0 | DW65: 0 | DX65: 0 | DY65: 0 | DZ65: 0 | EA65: 0 | EB65: 0 | EC65: 0 | ED65: 0 | EE65: 0 | EF65: 0 | EG65: 0 | EH65: 0 | EI65: 0 | EJ65: 0 | EK65: 0 | EL65: 0 | EM65: 0 | EN65: 0 | EO65: 0 | EP65: 0 | EQ65: 0 | ER65: 0 | ES65: 0 | ET65: 0 | EU65: 0 | EV65: 0 | EW65: 0 | EX65: 0 | EY65: 0 | EZ65: 0 | FA65: 0 | FB65: 0 | FC65: 0 | FD65: 0 | FE65: 0 | FF65: 0 | FG65: 0 | FH65: 0 | FI65: 0 | FJ65: 0 | FK65: 0 | FL65: 0 | FM65: 0 | FN65: 0 | FO65: 0 | FP65: 0 | FQ65: 0 | FR65: 0 | FS65: 0 | FT65: 0 | FU65: 0 | FV65: 0 | FW65: 0 | FX65: 0 | FY65: 0 | FZ65: 0 | GA65: 0 | GB65: 0 | GC65: 0 | GD65: 0 | GE65: 0 | GF65: 0 | GG65: 0 | GH65: 0 | GI65: 0 | GJ65: 0 | GK65: 0 | GL65: 0 | GM65: 0 | GN65: 0 | GO65: 0 | GP65: 0 | GQ65: 0 | GR65: 0 | GS65: 0 | GT65: 0 | GU65: 0 | GV65: 0 | GW65: 0 | GX65: 0 | GY65: 0 | GZ65: 0 | HA65: 0 | HB65: 0 | HC65: 0 | HD65: 0 | HE65: 0 | HF65: 0 | HG65: 0 | HH65: 0 | HI65: 0 | HJ65: 0 | HK65: 0 | HL65: 0 | HM65: 0 | HN65: 0 | HO65: 0 | HP65: 0 | HQ65: 0 | HR65: 0 | HS65: 0 | HT65: 0 | HU65: 0 | JF65: =AP65 | JG65: =SUM(Z65:AK65) | JH65: =SUM(AL65:AP65) | JI65: =SUM(C65:AP65) | JM65: 0 | KG65: =B65 | KH65: =AR65
A66: Distribuição de Resultado | B66: =SUM(C66:AP66) | AF66: 0 | AG66: 0 | AH66: 0 | AI66: 0 | AJ66: 0 | AK66: 0 | AL66: 0 | AM66: 0 | AN66: 0 | AO66: 0 | AP66: 0 | AR66: =SUM(AT66:HU66) | AT66: 0 | AU66: 0 | AV66: 0 | AW66: 0 | AX66: 0 | AY66: 0 | AZ66: 0 | BB66: -450000 | BC66: -1200000 | BD66: =-1800000+800000-750000-50000 | BE66: -1800000 | BF66: =-1800000+300000+100000 | BG66: -2500000 | BH66: =-2500000+100000 | BI66: =-1800000+100000 | BJ66: =-1800000+50000 | BK66: =-1800000-200000 | BL66: =-1500000-500000-500000 | BM66: =-1500000-500000 | BN66: =-500000-300000 | BO66: -500000 | BP66: -500000 | BQ66: =-500000+150000 | BR66: =-2750000-50000+100000 | BS66: =-2750000-50000+20000 | BT66: =-2750000-50000-20000 | BU66: =-2750000-50000-50000 | BV66: =-2750000-50000-100000 | BW66: =-2750000-50000-50000-150000 | BX66: =-2750000-50000-100000 | BY66: =-2750000-50000-100000 | BZ66: =-3000000+100000 | CA66: =-3000000+100000-100000 | CB66: =-3000000-200000 | CC66: =-3000000+50000-350000 | CD66: =-3100000+150000-150000 | CE66: =-3100000+10000 | CF66: =-3100000-50000 | CG66: =-3100000+10000-10000 | CH66: =-3100000+40000-40000 | CI66: =-3000000-100000-50000 | CJ66: =-3000000-100000 | CK66: =-3200000+20000-20000 | CL66: =-3200000+70000-70000 | CM66: =-3200000+5000-45000 | CN66: =-3500000-120000 | CO66: =-3400000+70000-170000-200000 | CP66: =-3400000+70000 | CQ66: =-3400000-50000 | CR66: =-3400000-50000 | CS66: =-3400000-50000 | CT66: =-3400000-50000-10000 | CU66: =-3400000-50000-50000 | CV66: =-3400000-100000 | CW66: =-3400000-150000-50000 | CX66: =-3600000+20000 | CY66: =-3600000+5000-5000 | CZ66: =-4100000+110000+30000 | DA66: =-3700000+110000-310000 | DB66: -3600000 | DC66: =-3800000+70000 | DD66: =-3700000+50000 | DE66: =-3700000+30000-30000 | DF66: =-3700000+10000-110000 | DG66: =-3700000-20000-30000 | DH66: =-3700000-50000-50000 | DI66: =-3900000+50000 | DJ66: =-3900000+20000 | DK66: =-3900000-50000 | DL66: =-4000000-350000+50000 | DM66: =-4000000+20000+50000-20000 | DN66: =-4000000+40000-40000 | DO66: =-4100000+20000-20000 | DP66: =-4100000+110000-10000 | DQ66: =-4100000+70000-70000 | DR66: =-4100000+20000-20000 | DS66: =-4100000-20000-30000 | DT66: =-4100000-50000 | DU66: -3950000 | DV66: -3500000 | DW66: =-3600000+100000+50000 | DX66: =-4000000+300000+50000+120000 | DY66: =-3300000+60000+20000+60000 | DZ66: =-3300000+100000+60000+60000 | EA66: =-3000000+50000-150000+40000 | EB66: =-3000000+50000+10000+80000 | EC66: =-2800000+50000 | ED66: =-2800000+60000+80000 | EE66: =-2750000+50000+50000+70000 | EF66: =-2550000+20000+70000 | EG66: =-2600000+100000+40000+400000 | EH66: =-2000000+15000+500000 | EI66: =-1350000-50000-100000+50000 | EJ66: =-1350000-50000+50000 | EK66: =-1350000+15000+60000 | EL66: =-1280000+30000+80000 | EM66: =-1200000+15000+70000 | EN66: =-1100000+60000 | EO66: =-1050000+70000 | EP66: =-1040000+30000+100000 | EQ66: =-900000+60000 | ER66: =-880000+10000+10000+90000 | ES66: =-700000-70000+60000 | ET66: =-700000+30000 | EU66: =-800000+100000+5000+20000+20000 | EV66: =-650000+10000 | EW66: =-650000+30000 | EX66: =-650000+10000+20000 | EY66: =-650000+30000+20000 | EZ66: =-600000+10000 | FA66: =-600000+50000 | FB66: =-600000+20000 | FC66: =-570000+5000+15000 | FD66: =-550000+10000+5000 | FE66: =-540000+20000-5000+5000 | FF66: =-540000+20000-5000+20000 | FG66: =-540000+20000-5000+20000 | FH66: =-500000-5000+15000 | FI66: =-500000-5000+20000 | FJ66: =-500000+10000+10000 | FK66: =-500000+10000+10000+10000 | FL66: =-500000+30000+5000 | FM66: =-450000-20000+20000 | FN66: =-450000-10000+10000+5000 | FO66: =-490000+20000+15000+10000+5000 | FP66: =-450000+10000+10000 | FQ66: =-450000+20000+10000 | FR66: =-440000+5000+5000+10000+10000 | FS66: =-400000-5000 | FT66: =-400000-15000+20000 | FU66: =-400000+5000 | FV66: =-400000+10000+10000 | FW66: =-400000+10000+10000+10000 | FX66: =-370000+5000 | FY66: =-370000+5000+10000 | FZ66: =-370000+5000+20000 | GA66: =-350000+5000 | GB66: =-350000+10000+10000 | GC66: =-360000+20000+5000+5000+10000 | GD66: =-330000+5000+10000 | GE66: =-300000-5000 | GF66: =-300000-10000+15000 | GG66: =-300000-5000+5000+10000 | GH66: =-300000+5000+5000+10000 | GI66: =-270000+10000-10000-5000 | GJ66: =-270000+10000-10000-5000+15000 | GK66: =-270000+10000-10000+5000+10000 | GL66: =-270000+10000+10000+5000 | GM66: =-260000+5000+5000+10000 | GN66: =-250000+5000+10000+10000 | GO66: =-250000+10000+10000+10000 | GP66: =-230000+1000+10000+5000 | GQ66: =-230000+10000+10000+10000 | GR66: =-220000+10000+10000+10000 | GS66: =-210000+10000+10000 | GT66: =-180000+5000-5000+5000 | GU66: =-180000+5000-5000+10000 | GV66: =-180000+5000+10000+10000 | GW66: =-180000+5000+20000 | GX66: =-135000-15000+10000 | GY66: =-135000+10000 | GZ66: =-135000+5000 | HA66: =-135000+5000+20000 | HB66: =-135000+20000+10000 | HC66: =-135000+30000+10000-5000 | HD66: =-135000+40000+5000 | HE66: =-111000+20000+15000 | HF66: =-80000+5000+5000 | HG66: =-70000+10000 | HH66: =-50000-5000+5000 | HI66: =-50000-5000+15000 | HJ66: =-50000+5000+10000 | HK66: =-49000+15000+10000-1000 | HL66: =-22000+8000 | HM66: =-14000+9000 | JF66: =AP66 | JG66: =SUM(Z66:AK66) | JH66: =SUM(AL66:AP66) | JI66: =SUM(C66:AP66) | JM66: 0 | KG66: =B66 | KH66: =AR66
A67: Subtotal | B67: =SUM(C67:AP67) | C67: =SUM(C65:C66) | D67: =SUM(D65:D66) | E67: =SUM(E65:E66) | F67: =SUM(F65:F66) | G67: =SUM(G65:G66) | H67: =SUM(H65:H66) | I67: =SUM(I65:I66) | J67: =SUM(J65:J66) | ... AB67: =SUM(AB65:AB66) | AG67: =+AG65+AG66 | AH67: =+AH65+AH66 | AI67: =+AI65+AI66 | AJ67: =+AJ65+AJ66 | AK67: =+AK65+AK66 | AL67: =+AL65+AL66 | AM67: =+AM65+AM66 | AN67: =+AN65+AN66 | ... AP67: =+AP65+AP66 | AR67: =SUM(AT67:HU67) | AT67: =SUM(AT65:AT66) | AU67: =SUM(AU65:AU66) | AV67: =SUM(AV65:AV66) | AW67: =SUM(AW65:AW66) | AX67: =SUM(AX65:AX66) | AY67: =SUM(AY65:AY66) | AZ67: =SUM(AZ65:AZ66) | BA67: =SUM(BA65:BA66) | ... HU67: =SUM(HU65:HU66) | JF67: =AP67 | JG67: =SUM(Z67:AK67) | JH67: =SUM(AL67:AP67) | JI67: =SUM(C67:AP67) | JM67: 0 | KG67: =B67 | KH67: =AR67
JF68: =AP68 | JG68: =SUM(Z68:AK68) | JH68: =SUM(AL68:AP68) | JI68: =SUM(C68:AP68) | KG68: =B68 | KH68: =AR68
A69: DESPESAS OP+TERRENO+IMP+DISTR (-) | B69: =SUM(C69:AP69) | C69: =C67+C56+C52+C59+C62 | D69: =D67+D56+D52+D59+D62 | E69: =E67+E56+E52+E59+E62 | F69: =F67+F56+F52+F59+F62 | G69: =G67+G56+G52+G59+G62 | H69: =H67+H56+H52+H59+H62 | I69: =I67+I56+I52+I59+I62 | J69: =J67+J56+J52+J59+J62 | ... AP69: =AP67+AP56+AP52+AP59+AP62 | AR69: =SUM(AT69:HU69) | AT69: =AT67+AT56+AT52+AT59+AT62 | AU69: =AU67+AU56+AU52+AU59+AU62 | AV69: =AV67+AV56+AV52+AV59+AV62 | AW69: =AW67+AW56+AW52+AW59+AW62 | AX69: =AX67+AX56+AX52+AX59+AX62 | AY69: =AY67+AY56+AY52+AY59+AY62 | AZ69: =AZ67+AZ56+AZ52+AZ59+AZ62 | BA69: =BA67+BA56+BA52+BA59+BA62 | ... HU69: =HU67+HU56+HU52+HU59+HU62 | JF69: =AP69 | JG69: =SUM(Z69:AK69) | JH69: =SUM(AL69:AP69) | JI69: =SUM(C69:AP69) | JM69: -4437714.3 | KG69: =B69 | KH69: =AR69
A70: TOTAL ACUMULADO | C70: 0 | D70: =C70+D69 | E70: =D70+E69 | F70: =E70+F69 | G70: =F70+G69 | H70: =G70+H69 | I70: =H70+I69 | J70: =I70+J69 | K70: =J70+K69 | ... AP70: =AO70+AP69 | AR70: 0 | AT70: =AP70+AT69 | AU70: =AT70+AU69 | AV70: =AU70+AV69 | AW70: =AV70+AW69 | AX70: =AW70+AX69 | AY70: =AX70+AY69 | AZ70: =AY70+AZ69 | BA70: =AZ70+BA69 | BB70: =BA70+BB69 | ... HU70: =HT70+HU69 | JF70: =AP70 | JG70: =SUM(Z70:AK70) | JH70: =SUM(AL70:AP70) | JI70: =SUM(C70:AP70) | JM70: -45150579 | KG70: =B70 | KH70: =AR70
JF71: =AP71 | JG71: =SUM(Z71:AK71) | JH71: =SUM(AL71:AP71) | JI71: =SUM(C71:AP71) | KG71: =B71 | KH71: =AR71
A72: SALDO DE CAIXA (MENSAL) | B72: =SUM(C72:AP72) | C72: =C20+C69 | D72: =D20+D69 | E72: =E20+E69 | F72: =F20+F69 | G72: =G20+G69 | H72: =H20+H69 | I72: =I20+I69 | J72: =J20+J69 | ... AP72: =AP20+AP69 | AR72: 0 | AT72: =AT20+AT69 | AU72: =AU20+AU69 | AV72: =AV20+AV69 | AW72: =AW20+AW69 | AX72: =AX20+AX69 | AY72: =AY20+AY69 | AZ72: =AZ20+AZ69 | BA72: =BA20+BA69 | ... HU72: =HU20+HU69 | JF72: =AP72 | JG72: =SUM(Z72:AK72) | JH72: =SUM(AL72:AP72) | JI72: =SUM(C72:AP72) | JM72: -2297202.7 | KG72: =B72 | KH72: =AR72
A73: SALDO ACUMULADO (REAL) | C73: =B73+C72 | D73: =C73+D72 | E73: =D73+E72 | F73: =E73+F72 | G73: =F73+G72 | H73: =G73+H72 | I73: =H73+I72 | J73: =I73+J72 | ... AP73: =AO73+AP72 | AT73: =AP73+AT72 | AU73: =AT73+AU72 | AV73: =AU73+AV72 | AW73: =AV73+AW72 | AX73: =AW73+AX72 | AY73: =AX73+AY72 | AZ73: =AY73+AZ72 | BA73: =AZ73+BA72 | BB73: =BA73+BB72 | ... HU73: =HT73+HU72 | JF73: =AP73 | JG73: =SUM(Z73:AK73) | JH73: =SUM(AL73:AP73) | JI73: =SUM(C73:AP73) | JM73: 10274046 | KG73: =B73 | KH73: =AR73
JF74: =AP74 | JG74: =SUM(Z74:AK74) | JH74: =SUM(AL74:AP74) | JI74: =SUM(C74:AP74) | KG74: =B74 | KH74: =AR74
A75: SALDO DE CAIXA (MENSAL) C/ PROJEÇÃO | B75: =SUM(C75:AP75) | C75: =C20+C69+C12 | D75: =D20+D69+D12 | E75: =E20+E69+E12 | F75: =F20+F69+F12 | G75: =G20+G69+G12 | H75: =H20+H69+H12 | I75: =I20+I69+I12 | J75: =J20+J69+J12 | ... AP75: =AP20+AP69+AP12 | AT75: =AT20+AT69+AT12 | AU75: =AU20+AU69+AU12 | AV75: =AV20+AV69+AV12 | AW75: =AW20+AW69+AW12 | AX75: =AX20+AX69+AX12 | AY75: =AY20+AY69+AY12 | AZ75: =AZ20+AZ69+AZ12 | BA75: =BA20+BA69+BA12 | ... HU75: =HU20+HU69+HU12 | JF75: =AP75 | JG75: =SUM(Z75:AK75) | JH75: =SUM(AL75:AP75) | JI75: =SUM(C75:AP75) | JM75: -1744189.5 | KG75: =B75 | KH75: =AR75
A76: SALDO ACUMULADO C/ PROJEÇÕES | C76: =B76+C75 | D76: =C76+D75 | E76: =D76+E75 | F76: =E76+F75 | G76: =F76+G75 | H76: =G76+H75 | I76: =H76+I75 | J76: =I76+J75 | ... AP76: =AO76+AP75 | AT76: =AP76+AT75 | AU76: =AT76+AU75 | AV76: =AU76+AV75 | AW76: =AV76+AW75 | AX76: =AW76+AX75 | AY76: =AX76+AY75 | AZ76: =AY76+AZ75 | BA76: =AZ76+BA75 | BB76: =BA76+BB75 | ... HU76: =HT76+HU75 | JF76: =AP76 | JG76: =SUM(Z76:AK76) | JH76: =SUM(AL76:AP76) | JI76: =SUM(C76:AP76) | JM76: 10827059 | KG76: =B76 | KH76: =AR76
AT78: =AT5 | AU78: =AU5 | AV78: =AV5 | AW78: =AW5 | AX78: =AX5 | AY78: =AY5 | AZ78: =AZ5 | BA78: =BA5 | ... HU78: =HU5
AE79: 8913488.7 | AF79: 9444535.9 | BF79: PREVISÃO DE | BR79: 1º ano pós obra | CD79: 2º ano pós obra | CP79: 3º ano pós obra | DB79: 4º ano pós obra | DN79: 5º ano pós obra | DZ79: 6º ano pós obra | EL79: 7º ano pós obra | EX79: 8º ano pós obra | FJ79: 9º ano pós obra | FV79: 10º ano pós obra | GH79: 11º ano pós obra | GT79: 12º ano pós obra | HF79: 13º ano pós obra | HR79: 14º ano pós obra
BF80: ENTREGA DA OBRA | BR80: Fundo R$ 1 MM | CD80: Fundo R$ 500k | CP80: Fundo R$ 250k | DB80: Fundo R$ 250k | DN80: Fundo R$ 250k | DZ80: Fundo R$ 250k | EL80: Fundo R$ 250k | EX80: Fundo R$ 250k | FJ80: Fundo R$ 250k | FV80: Fundo R$ 250k | GH80: Fundo R$ 250k | GT80: Fundo R$ 250k | HF80: Fundo R$ 250k | HR80: Fundo R$ 250k
AE81: =+AE79-AE76 | AF81: =+AF79-AF76 | AG81: =3013129.63-AG76 | AH81: =3775046.22-AH76 | AI81: =4232168.49-AI76 | AJ81: =3223191.08-AJ76 | AK81: =3338944.48-AK76 | AL81: =4310244.13-AL76 | AM81: =6156434.67-AM76-612.82 | AN81: =11961744.61-AN76 | AO81: =12571248.85-AO76 | AP81: =11787274.2-AP76 | BR81: =+BR76-1000000 | CD81: =+CD76-500000 | CP81: =+CP76-250000 | DB81: =+DB76-250000 | DN81: =+DN76-250000 | DZ81: =+DZ76-250000 | EL81: =+EL76-250000 | EX81: =+EX76-250000 | FJ81: =+FJ76-250000 | FV81: =+FV76-250000 | GH81: =+GH76-250000 | GT81: =+GT76-250000 | HF81: =+HF76-250000 | HR81: =+HR76-250000
AM82: =6156434.67-6155821.85
BJ84: =BJ66/$AR$66 | BK84: =BK66/$AR$66 | BL84: =BL66/$AR$66 | BM84: =BM66/$AR$66 | BN84: =BN66/$AR$66 | BO84: =BO66/$AR$66 | BP84: =BP66/$AR$66 | BQ84: =BQ66/$AR$66 | ... HT84: =HT66/$AR$66
BA85: 2250
BA86: 1500
BA87: 900
HU88: Saldo médio final pós obra
HU89: =AVERAGE(BI76:HU76)

Sheet FC Total (7 lotes)
AR1: Total | Previsão | BF1: PREVISÃO DE | EC1: FIM DAS VENDAS | JF1: Realizado | JM1: Previsão de Maio feita no fechamento de Abril/26 | KH1: Total | Previsão
A2: Ville de Provence | AB2: =+AB8+AB9+AC8+AC9+AD8+AD9+AE8+AE9+AF8+AF9+AD62 | BF2: ENTREGA DA OBRA | JF2: No mês | JG2: Ano 2025 | JH2: Ano 2026 | JI2: Acumulado | JS2: YTD | JT2: Prev. 2025 | JU2: 2026 | JV2: 2027 | JW2: 2028 | JX2: 2029 | JY2: 2030 | JZ2: Demais
C3: 1 | D3: 2 | E3: 3 | F3: 4 | G3: 5 | H3: 6 | I3: 7 | J3: 8 | K3: 9 | L3: 10 | M3: 11 | N3: 12 | O3: 13 | P3: 14 | Q3: 15 | R3: 16 | S3: 17 | T3: 18 | U3: 19 | V3: 20 | W3: 21 | X3: 22 | Y3: 23 | Z3: 24 | AA3: 25 | AB3: 26 | AC3: 27 | AD3: 28 | AE3: 29 | AF3: 30 | AG3: 31 | AH3: 32 | AI3: 33 | AJ3: 34 | AK3: 35 | AL3: 36 | AM3: 37 | AN3: 38 | AO3: 39 | AP3: 40 | AT3: 41 | AU3: 42 | AV3: 43 | AW3: 44 | AX3: 45 | AY3: 46 | AZ3: 47 | BA3: 48 | BB3: 49 | BC3: 50 | BD3: 51 | BE3: 52 | BF3: 53 | BG3: 54 | BH3: 55 | BI3: 56 | BJ3: 57 | BK3: 58 | BL3: 59 | BM3: 60 | BN3: 61 | BO3: 62 | BP3: 63 | BQ3: 64 | BR3: 65 | BS3: 66 | BT3: 67 | BU3: 68 | BV3: 69 | BW3: 70 | BX3: 71 | BY3: 72 | BZ3: 73 | CA3: 74 | CB3: 75 | CC3: 76 | CD3: 77 | CE3: 78 | CF3: 79 | CG3: 80 | CH3: 81 | CI3: 82 | CJ3: 83 | CK3: 84 | CL3: 85 | CM3: 86 | CN3: 87 | CO3: 88 | CP3: 89 | CQ3: 90 | CR3: 91 | CS3: 92 | CT3: 93 | CU3: 94 | CV3: 95 | CW3: 96 | CX3: 97 | CY3: 98 | CZ3: 99 | DA3: 100 | DB3: 101 | DC3: 102 | DD3: 103 | DE3: 104 | DF3: 105 | DG3: 106 | DH3: 107 | DI3: 108 | DJ3: 109 | DK3: 110 | DL3: 111 | DM3: 112 | DN3: 113 | DO3: 114 | DP3: 115 | DQ3: 116 | DR3: 117 | DS3: 118 | DT3: 119 | DU3: 120 | DV3: 121 | DW3: 122 | DX3: 123 | DY3: 124 | DZ3: 125 | EA3: 126 | EB3: 127 | EC3: 128 | ED3: 129 | EE3: 130 | EF3: 131 | EG3: 132 | EH3: 133 | EI3: 134 | EJ3: 135 | EK3: 136 | EL3: 137 | EM3: 138 | EN3: 139 | EO3: 140 | EP3: 141 | EQ3: 142 | ER3: 143 | ES3: 144 | ET3: 145 | EU3: 146 | EV3: 147 | EW3: 148 | EX3: 149 | EY3: 150 | EZ3: 151 | FA3: 152 | FB3: 153 | FC3: 154 | FD3: 155 | FE3: 156 | FF3: 157 | FG3: 158 | FH3: 159 | FI3: 160 | FJ3: 161 | FK3: 162 | FL3: 163 | FM3: 164 | FN3: 165 | FO3: 166 | FP3: 167 | FQ3: 168 | FR3: 169 | FS3: 170 | FT3: 171 | FU3: 172 | FV3: 173 | FW3: 174 | FX3: 175 | FY3: 176 | FZ3: 177 | GA3: 178 | GB3: 179 | GC3: 180 | GD3: 181 | GE3: 182 | GF3: 183 | GG3: 184 | GH3: 185 | GI3: 186 | GJ3: 187 | GK3: 188 | GL3: 189 | GM3: 190 | GN3: 191 | GO3: 192 | GP3: 193 | GQ3: 194 | GR3: 195 | GS3: 196 | GT3: 197 | GU3: 198 | GV3: 199 | GW3: 200 | GX3: 201 | GY3: 202 | GZ3: 203 | HA3: 204 | HB3: 205 | HC3: 206 | HD3: 207 | HE3: 208 | HF3: 209 | HG3: 210 | HH3: 211 | HI3: 212 | HJ3: 213 | HK3: 214 | HL3: 215 | HM3: 216 | HN3: 217 | HO3: 218 | HP3: 219 | HQ3: 220 | HR3: 221 | HS3: 222 | HT3: 223 | HU3: 224 | JM3: 40
A4: Fluxo de Caixa | B4: REALIZADO | M4: REALIZADO | KG4: REALIZADO
C5: 44958 | D5: 44986 | E5: 45017 | F5: 45047 | G5: 45078 | H5: 45108 | I5: 45139 | J5: 45170 | K5: 45200 | L5: 45231 | M5: 45261 | N5: 45292 | O5: 45323 | P5: 45352 | Q5: 45383 | R5: 45413 | S5: 45444 | T5: 45474 | U5: 45505 | V5: 45536 | W5: 45566 | X5: 45597 | Y5: 45627 | Z5: 45658 | AA5: 45689 | AB5: 45717 | AC5: 45748 | AD5: 45778 | AE5: 45809 | AF5: 45839 | AG5: 45870 | AH5: 45901 | AI5: 45931 | AJ5: 45962 | AK5: 45992 | AL5: 46023 | AM5: 46054 | AN5: 46082 | AO5: 46113 | AP5: 46143 | AR5: Total | Previsão | AT5: 46174 | AU5: 46204 | AV5: 46235 | AW5: 46266 | AX5: 46296 | AY5: 46327 | AZ5: 46357 | BA5: 46388 | BB5: 46419 | BC5: 46447 | BD5: 46478 | BE5: 46508 | BF5: 46539 | BG5: 46569 | BH5: 46600 | BI5: 46631 | BJ5: 46661 | BK5: 46692 | BL5: 46722 | BM5: 46753 | BN5: 46784 | BO5: 46813 | BP5: 46844 | BQ5: 46874 | BR5: 46905 | BS5: 46935 | BT5: 46966 | BU5: 46997 | BV5: 47027 | BW5: 47058 | BX5: 47088 | BY5: 47119 | BZ5: 47150 | CA5: 47178 | CB5: 47209 | CC5: 47239 | CD5: 47270 | CE5: 47300 | CF5: 47331 | CG5: 47362 | CH5: 47392 | CI5: 47423 | CJ5: 47453 | CK5: 47484 | CL5: 47515 | CM5: 47543 | CN5: 47574 | CO5: 47604 | CP5: 47635 | CQ5: 47665 | CR5: 47696 | CS5: 47727 | CT5: 47757 | CU5: 47788 | CV5: 47818 | CW5: 47849 | CX5: 47880 | CY5: 47908 | CZ5: 47939 | DA5: 47969 | DB5: 48000 | DC5: 48030 | DD5: 48061 | DE5: 48092 | DF5: 48122 | DG5: 48153 | DH5: 48183 | DI5: 48214 | DJ5: 48245 | DK5: 48274 | DL5: 48305 | DM5: 48335 | DN5: 48366 | DO5: 48396 | DP5: 48427 | DQ5: 48458 | DR5: 48488 | DS5: 48519 | DT5: 48549 | DU5: 48580 | DV5: 48611 | DW5: 48639 | DX5: 48670 | DY5: 48700 | DZ5: 48731 | EA5: 48761 | EB5: 48792 | EC5: 48823 | ED5: 48853 | EE5: 48884 | EF5: 48914 | EG5: 48945 | EH5: 48976 | EI5: 49004 | EJ5: 49035 | EK5: 49065 | EL5: 49096 | EM5: 49126 | EN5: 49157 | EO5: 49188 | EP5: 49218 | EQ5: 49249 | ER5: 49279 | ES5: 49310 | ET5: 49341 | EU5: 49369 | EV5: 49400 | EW5: 49430 | EX5: 49461 | EY5: 49491 | EZ5: 49522 | FA5: 49553 | FB5: 49583 | FC5: 49614 | FD5: 49644 | FE5: 49675 | FF5: 49706 | FG5: 49735 | FH5: 49766 | FI5: 49796 | FJ5: 49827 | FK5: 49857 | FL5: 49888 | FM5: 49919 | FN5: 49949 | FO5: 49980 | FP5: 50010 | FQ5: 50041 | FR5: 50072 | FS5: 50100 | FT5: 50131 | FU5: 50161 | FV5: 50192 | FW5: 50222 | FX5: 50253 | FY5: 50284 | FZ5: 50314 | GA5: 50345 | GB5: 50375 | GC5: 50406 | GD5: 50437 | GE5: 50465 | GF5: 50496 | GG5: 50526 | GH5: 50557 | GI5: 50587 | GJ5: 50618 | GK5: 50649 | GL5: 50679 | GM5: 50710 | GN5: 50740 | GO5: 50771 | GP5: 50802 | GQ5: 50830 | GR5: 50861 | GS5: 50891 | GT5: 50922 | GU5: 50952 | GV5: 50983 | GW5: 51014 | GX5: 51044 | GY5: 51075 | GZ5: 51105 | HA5: 51136 | HB5: 51167 | HC5: 51196 | HD5: 51227 | HE5: 51257 | HF5: 51288 | HG5: 51318 | HH5: 51349 | HI5: 51380 | HJ5: 51410 | HK5: 51441 | HL5: 51471 | HM5: 51502 | HN5: 51533 | HO5: 51561 | HP5: 51592 | HQ5: 51622 | HR5: 51653 | HS5: 51683 | HT5: 51714 | HU5: 51745 | JM5: 46143 | KH5: Total | Previsão
A7: RECEITAS | JR7: =A7
A8: ITBI | B8: =SUM(C8:AP8) | AB8: 338614.68 | AC8: 371549.5 | AD8: 148554.82 | AE8: 170837.48 | AF8: 191671.94 | AG8: 135342.79 | AH8: 107538.42 | AI8: 89467.66 | AJ8: 89498.31 | AK8: 150726.26 | AL8: 202733.57 | AM8: 93610.35 | AN8: 102176.17 | AO8: 121648.43 | AP8: 76491.71 | AR8: =SUM(AT8:HU8) | JF8: =AP8 | JG8: =SUM(Z8:AK8) | JH8: =SUM(AL8:AP8) | JI8: =SUM(C8:AP8) | JR8: =A8 | JS8: =SUM(C8:AP8) | JU8: =SUM(AT8:AZ8) | JV8: =SUM(BA8:BL8) | JW8: =SUM(BM8:BX8) | JX8: =SUM(BY8:CJ8) | JY8: =SUM(CK8:CV8) | JZ8: =SUM(CW8:HU8) | KG8: =B8 | KH8: =AR8
A9: Receitas Contratadas | B9: =SUM(C9:AP9) | AB9: 2857997.7 | AC9: 3156158.3 | AD9: 1788940.8 | AE9: =3240637.47-AE8+19092.42 | AF9: 1881026.6 | AG9: 2310558.1 | AH9: =2548839.41-78352.42 | AI9: 2551921.9 | AJ9: =2138552.83-41382.42 | AK9: 4079024.8 | AL9: 4698660.8 | AM9: 3087731.2 | AN9: =7279760.12-30654.55 | AO9: =3684860.85-29012.57-24791.61 | AP9: 3243847.9 | AR9: =SUM(AT9:HU9) | AT9: 3574821.4 | AU9: 2767000.7 | AV9: 2446947.7 | AW9: 3652273.5 | AX9: 2932991 | AY9: 2528178 | AZ9: 3753790.3 | BA9: 4012049.6 | BB9: 3544053.9 | BC9: 3455923.5 | BD9: 3435572.3 | BE9: 2126327.4 | BF9: 1595056.3 | BG9: 1682126.5 | BH9: 1531678.3 | BI9: 1005222.9 | BJ9: 965285.41 | BK9: 1636485.1 | BL9: 1675939 | BM9: 913661.51 | BN9: 799107.12 | BO9: 1148317.9 | BP9: 1245834.1 | BQ9: 688488.99 | BR9: 475750.07 | BS9: 483123.56 | BT9: 573091.67 | BU9: 445746.79 | BV9: 445746.73 | BW9: 467823.36 | BX9: 445746.73 | BY9: 443425.39 | BZ9: 367739.24 | CA9: 393894.68 | CB9: 628058.54 | CC9: 835888.25 | CD9: 365111.17 | CE9: 422908.01 | CF9: 492947.79 | CG9: 366947.05 | CH9: 366947.12 | CI9: 380365.1 | CJ9: 358288.47 | CK9: 407361.59 | CL9: 358288.47 | CM9: 372054.76 | CN9: 633307.27 | CO9: 760631.49 | CP9: 354866.26 | CQ9: 418462.35 | CR9: 355407.32 | CS9: 355407.27 | CT9: 355407.27 | CU9: 377483.9 | CV9: 344499.82 | CW9: 393572.94 | CX9: 344499.82 | CY9: 370765.27 | CZ9: 644037.26 | DA9: 652601.6 | DB9: 332584.38 | DC9: 421539.19 | DD9: 333179.68 | DE9: 333179.7 | DF9: 333179.7 | DG9: 355256.33 | DH9: 333179.7 | DI9: 382252.82 | DJ9: 333179.7 | DK9: 359415.99 | DL9: 655336.52 | DM9: 355909.56 | DN9: 333832.92 | DO9: 431713.34 | DP9: 334487.99 | DQ9: 334487.95 | DR9: 334487.95 | DS9: 356564.58 | DT9: 334487.95 | DU9: 383561.07 | DV9: 334487.95 | DW9: 360650.28 | DX9: 531581.81 | DY9: 289043.69 | DZ9: 249797.02 | EA9: 325590.01 | EB9: 201524.86 | EC9: 177058.53 | ED9: 165595.82 | EE9: 187672.45 | EF9: 151718.75 | EG9: 186523.84 | EH9: 114989.8 | EI9: 101752.25 | EJ9: 72859.21 | EK9: 37160.03 | EL9: 0 | EM9: 0 | EN9: 0 | EO9: 0 | EP9: 0 | EQ9: 0 | ER9: 0 | ES9: 0 | ET9: 0 | EU9: 0 | EV9: 0 | EW9: 0 | EX9: 0 | EY9: 0 | EZ9: 0 | FA9: 0 | FB9: 0 | FC9: 0 | FD9: 0 | FE9: 0 | FF9: 0 | FG9: 0 | FH9: 0 | FI9: 0 | FJ9: 0 | FK9: 0 | FL9: 0 | FM9: 0 | FN9: 0 | FO9: 0 | FP9: 0 | FQ9: 0 | FR9: 0 | FS9: 0 | FT9: 0 | FU9: 0 | FV9: 0 | FW9: 0 | FX9: 0 | FY9: 0 | FZ9: 0 | GA9: 0 | GB9: 0 | GC9: 0 | GD9: 0 | GE9: 0 | GF9: 0 | GG9: 0 | GH9: 0 | GI9: 0 | GJ9: 0 | GK9: 0 | GL9: 0 | GM9: 0 | GN9: 0 | GO9: 0 | GP9: 0 | GQ9: 0 | GR9: 0 | GS9: 0 | GT9: 0 | GU9: 0 | GV9: 0 | GW9: 0 | GX9: 0 | GY9: 0 | GZ9: 0 | HA9: 0 | HB9: 0 | HC9: 0 | HD9: 0 | HE9: 0 | HF9: 0 | HG9: 0 | HH9: 0 | HI9: 0 | HJ9: 0 | HK9: 0 | HL9: 0 | HM9: 0 | HN9: 0 | HO9: 0 | HP9: 0 | HQ9: 0 | HR9: 0 | HS9: 0 | HT9: 0 | HU9: 0 | JF9: =AP9 | JG9: =SUM(Z9:AK9) | JH9: =SUM(AL9:AP9) | JI9: =SUM(C9:AP9) | JM9: 2014799.1 | JR9: =A9 | JS9: =SUM(C9:AP9) | JU9: =SUM(AT9:AZ9) | JV9: =SUM(BA9:BL9) | JW9: =SUM(BM9:BX9) | JX9: =SUM(BY9:CJ9) | JY9: =SUM(CK9:CV9) | JZ9: =SUM(CW9:HU9) | KG9: =B9 | KH9: =AR9 | KJ9: =+KG9+KH9+KH12
JF10: =AP10 | JG10: =SUM(Z10:AK10) | JH10: =SUM(AL10:AP10) | JI10: =SUM(C10:AP10) | JR10: =A10 | JS10: =SUM(C10:AP10) | JU10: =SUM(AT10:AZ10) | JV10: =SUM(BA10:BL10) | JW10: =SUM(BM10:BX10) | JX10: =SUM(BY10:CJ10) | JY10: =SUM(CK10:CV10) | JZ10: =SUM(CW10:HU10) | KG10: =B10 | KH10: =AR10
A11: PREVISÃO DE RECEITAS(ESTOQUE) | JF11: =AP11 | JG11: =SUM(Z11:AK11) | JH11: =SUM(AL11:AP11) | JI11: =SUM(C11:AP11) | JR11: =A11 | JS11: =SUM(C11:AP11) | JU11: =SUM(AT11:AZ11) | JV11: =SUM(BA11:BL11) | JW11: =SUM(BM11:BX11) | JX11: =SUM(BY11:CJ11) | JY11: =SUM(CK11:CV11) | JZ11: =SUM(CW11:HU11) | KG11: =B11 | KH11: =AR11
A12: Vendas 05 Lotes a.m. | B12: =SUM(C12:AP12) | C12: 0 | D12: 0 | E12: 0 | F12: 0 | G12: 0 | H12: 0 | I12: 0 | J12: 0 | K12: 0 | L12: 0 | M12: 0 | N12: 0 | O12: 0 | P12: 0 | Q12: 0 | R12: 0 | S12: 0 | T12: 0 | U12: 0 | V12: 0 | AR12: =SUM(AT12:HU12) | AT12: 741900.15 | AU12: 860830.76 | AV12: 979761.37 | AW12: 1120321.7 | AX12: 1242719.7 | AY12: 1365117.7 | AZ12: 1487515.6 | BA12: 1609913.6 | BB12: 1732311.6 | BC12: 1854709.5 | BD12: 1998737.3 | BE12: 2124602.6 | BF12: 3107902.5 | BG12: 3194449.8 | BH12: 3280997.2 | BI12: 3392542.6 | BJ12: 3477943.7 | BK12: 3584974.5 | BL12: 3673842.9 | BM12: 3762711.3 | BN12: 3851579.7 | BO12: 3940448.1 | BP12: 4054314.6 | BQ12: 4142036.8 | BR12: 4251388.6 | BS12: 4280198.6 | BT12: 4309008.6 | BU12: 4337818.6 | BV12: 4364809.9 | BW12: 4416799.4 | BX12: 4442644.4 | BY12: 4492282.2 | BZ12: 4521941.3 | CA12: 4551600.5 | CB12: 4581259.6 | CC12: 4609100.1 | CD12: 4661938.7 | CE12: 4682079.9 | CF12: 4702221.1 | CG12: 4746155.1 | CH12: 4769919.3 | CI12: 4793683.6 | CJ12: 4815629.2 | CK12: 4865072.7 | CL12: 4885757.4 | CM12: 4906442.1 | CN12: 4950919.5 | CO12: 4975227.3 | CP12: 4999535 | CQ12: 5022024.1 | CR12: 5044513.2 | CS12: 5094500.2 | CT12: 5115728.4 | CU12: 5160749.2 | CV12: 5185600.5 | CW12: 5210451.7 | CX12: 5101361 | CY12: 4311412.2 | CZ12: 4213704.4 | DA12: 4087237.7 | DB12: 3960771 | DC12: 3834113.3 | DD12: 3707455.5 | DE12: 3580797.8 | DF12: 3452139.5 | DG12: 3350979.2 | DH12: 3221060 | DI12: 3091140.9 | DJ12: 2808523.2 | DK12: 1770456.1 | DL12: 1689273.7 | DM12: 1606090.7 | DN12: 1522907.8 | DO12: 1439724.8 | DP12: 1356541.9 | DQ12: 1273358.9 | DR12: 1189965.8 | DS12: 1106572.7 | DT12: 1021179.1 | DU12: 935785.5 | DV12: 850391.89 | DW12: 776092.01 | DX12: 768354.5 | DY12: 760406.84 | DZ12: 752459.18 | EA12: 744511.52 | EB12: 736563.86 | EC12: 728616.21 | ED12: 720668.55 | EE12: 712720.89 | EF12: 704563.07 | EG12: 696405.26 | EH12: 688247.45 | EI12: 681255.04 | EJ12: 681255.04 | EK12: 681255.04 | EL12: 681255.04 | EM12: 670574.91 | EN12: 659894.78 | EO12: 649214.66 | EP12: 638223.16 | EQ12: 627231.66 | ER12: 616240.16 | ES12: 605248.66 | ET12: 594257.16 | EU12: 583265.66 | EV12: 572274.16 | EW12: 560971.28 | EX12: 549668.41 | EY12: 538365.54 | EZ12: 527062.66 | FA12: 515759.79 | FB12: 504456.91 | FC12: 493154.04 | FD12: 481539.79 | FE12: 469925.55 | FF12: 458311.3 | FG12: 446697.05 | FH12: 435082.8 | FI12: 423468.55 | FJ12: 411854.31 | FK12: 399928.68 | FL12: 388003.06 | FM12: 376077.44 | FN12: 364151.82 | FO12: 352226.2 | FP12: 340300.58 | FQ12: 328374.95 | FR12: 316106.82 | FS12: 303838.69 | FT12: 291570.55 | FU12: 279302.42 | FV12: 267034.29 | FW12: 254766.15 | FX12: 242498.02 | FY12: 230229.89 | FZ12: 217619.24 | GA12: 205008.6 | GB12: 192397.96 | GC12: 179787.31 | GD12: 167176.67 | GE12: 154566.02 | GF12: 141955.38 | GG12: 129002.22 | GH12: 116049.07 | GI12: 103095.91 | GJ12: 90142.755 | GK12: 77189.599 | GL12: 64236.443 | GM12: 51283.287 | GN12: 37987.62 | GO12: 24691.953 | GP12: 11396.286 | JF12: =AP12 | JG12: =SUM(Z12:AK12) | JH12: =SUM(AL12:AP12) | JI12: =SUM(C12:AP12) | JM12: 553013.18 | JR12: =A12 | JS12: =SUM(C12:AP12) | JU12: =SUM(AT12:AZ12) | JV12: =SUM(BA12:BL12) | JW12: =SUM(BM12:BX12) | JX12: =SUM(BY12:CJ12) | JY12: =SUM(CK12:CV12) | JZ12: =SUM(CW12:HU12) | KG12: =B12 | KH12: =AR12
JF13: =AP13 | JG13: =SUM(Z13:AK13) | JH13: =SUM(AL13:AP13) | JI13: =SUM(C13:AP13) | JR13: =A13 | JS13: =SUM(C13:AP13) | JU13: =SUM(AT13:AZ13) | JV13: =SUM(BA13:BL13) | JW13: =SUM(BM13:BX13) | JX13: =SUM(BY13:CJ13) | JY13: =SUM(CK13:CV13) | JZ13: =SUM(CW13:HU13) | KG13: =B13 | KH13: =AR13
A14: APORTE DE SÓCIOS | JF14: =AP14 | JG14: =SUM(Z14:AK14) | JH14: =SUM(AL14:AP14) | JI14: =SUM(C14:AP14) | JR14: =A14 | JS14: =SUM(C14:AP14) | JU14: =SUM(AT14:AZ14) | JV14: =SUM(BA14:BL14) | JW14: =SUM(BM14:BX14) | JX14: =SUM(BY14:CJ14) | JY14: =SUM(CK14:CV14) | JZ14: =SUM(CW14:HU14) | KG14: =B14 | KH14: =AR14
A15: Aportes | B15: =SUM(C15:AP15) | C15: 2004788.2 | Y15: 1000000 | Z15: 1000000 | AB15: 1000000 | AR15: =SUM(AT15:HU15) | AY15: 320000 | BA15: 0 | BB15: 0 | BC15: 0 | BD15: 0 | BE15: 0 | BF15: 0 | BG15: 0 | BH15: 0 | BI15: 0 | BJ15: 0 | BL15: 0 | BM15: 0 | BN15: 0 | BO15: 0 | BP15: 0 | BQ15: 0 | BR15: 0 | BS15: 0 | BT15: 0 | BU15: 0 | BV15: 0 | BW15: 0 | BX15: 0 | BY15: 0 | BZ15: 0 | CA15: 0 | CB15: 0 | CC15: 0 | CD15: 0 | CE15: 0 | CF15: 0 | CG15: 0 | CH15: 0 | CI15: 0 | CJ15: 0 | CK15: 0 | CL15: 0 | CM15: 0 | CN15: 0 | CO15: 0 | CP15: 0 | CQ15: 0 | CR15: 0 | CS15: 0 | CT15: 0 | CU15: 0 | CV15: 0 | CW15: 0 | CX15: 0 | CY15: 0 | CZ15: 0 | DA15: 0 | DB15: 0 | DC15: 0 | DD15: 0 | DE15: 0 | DF15: 0 | DG15: 0 | DH15: 0 | DI15: 0 | DJ15: 0 | DK15: 0 | DL15: 0 | DM15: 0 | DN15: 0 | DO15: 0 | DP15: 0 | DQ15: 0 | DR15: 0 | DS15: 0 | DT15: 0 | DU15: 0 | DV15: 0 | DW15: 0 | DX15: 0 | DY15: 0 | DZ15: 0 | EA15: 0 | EB15: 0 | EC15: 0 | ED15: 0 | EE15: 0 | EF15: 0 | EG15: 0 | EH15: 0 | EI15: 0 | EJ15: 0 | EK15: 0 | EL15: 0 | EM15: 0 | EN15: 0 | EO15: 0 | EP15: 0 | EQ15: 0 | ER15: 0 | ES15: 0 | ET15: 0 | EU15: 0 | EV15: 0 | EW15: 0 | EX15: 0 | EY15: 0 | EZ15: 0 | FA15: 0 | FB15: 0 | FC15: 0 | FD15: 0 | FE15: 0 | FF15: 0 | FG15: 0 | FH15: 0 | FI15: 0 | FJ15: 0 | FK15: 0 | FL15: 0 | FM15: 0 | FN15: 0 | FO15: 0 | FP15: 0 | FQ15: 0 | FR15: 0 | FS15: 0 | FT15: 0 | FU15: 0 | FV15: 0 | FW15: 0 | FX15: 0 | FY15: 0 | FZ15: 0 | GA15: 0 | GB15: 0 | GC15: 0 | GD15: 0 | GE15: 0 | GF15: 0 | GG15: 0 | GH15: 0 | GI15: 0 | GJ15: 0 | GK15: 0 | GL15: 0 | GM15: 0 | GN15: 0 | GO15: 0 | GP15: 0 | GQ15: 0 | GR15: 0 | GS15: 0 | GT15: 0 | GU15: 0 | GV15: 0 | GW15: 0 | GX15: 0 | GY15: 0 | GZ15: 0 | HA15: 0 | HB15: 0 | HC15: 0 | HD15: 0 | HE15: 0 | HF15: 0 | HG15: 0 | HH15: 0 | HI15: 0 | HJ15: 0 | HK15: 0 | HL15: 0 | HM15: 0 | HN15: 0 | HO15: 0 | HP15: 0 | HQ15: 0 | HR15: 0 | HS15: 0 | HT15: 0 | HU15: 0 | JF15: =AP15 | JG15: =SUM(Z15:AK15) | JH15: =SUM(AL15:AP15) | JI15: =SUM(C15:AP15) | JR15: =A15 | JS15: =SUM(C15:AP15) | JU15: =SUM(AT15:AZ15) | JV15: =SUM(BA15:BL15) | JW15: =SUM(BM15:BX15) | JX15: =SUM(BY15:CJ15) | JY15: =SUM(CK15:CV15) | JZ15: =SUM(CW15:HU15) | KG15: =B15 | KH15: =AR15
JF16: =AP16 | JG16: =SUM(Z16:AK16) | JH16: =SUM(AL16:AP16) | JI16: =SUM(C16:AP16) | JR16: =A16 | JS16: =SUM(C16:AP16) | JU16: =SUM(AT16:AZ16) | JV16: =SUM(BA16:BL16) | JW16: =SUM(BM16:BX16) | JX16: =SUM(BY16:CJ16) | JY16: =SUM(CK16:CV16) | JZ16: =SUM(CW16:HU16) | KG16: =B16 | KH16: =AR16
A17: RECEITA FINANCEIRA (+) | JF17: =AP17 | JG17: =SUM(Z17:AK17) | JH17: =SUM(AL17:AP17) | JI17: =SUM(C17:AP17) | JR17: =A17 | JS17: =SUM(C17:AP17) | JU17: =SUM(AT17:AZ17) | JV17: =SUM(BA17:BL17) | JW17: =SUM(BM17:BX17) | JX17: =SUM(BY17:CJ17) | JY17: =SUM(CK17:CV17) | JZ17: =SUM(CW17:HU17) | KG17: =B17 | KH17: =AR17
A18: Rendimento Financeiro | B18: =SUM(C18:AP18) | AB18: 12646.02 | AC18: 38113.26 | AD18: 57998.09 | AE18: 61248.2 | AF18: 72074.91 | AG18: =38669.97+1.14+11658.76-959.8 | AH18: 113822.32 | AI18: 94885.85 | AJ18: =78967.8800000008-41382.42 | AK18: 92147.74 | AL18: 87783.19 | AM18: 36405.54 | AN18: 123144.16 | AO18: 161967.44 | AP18: 228379.68 | AR18: =SUM(AT18:HU18) | AT18: =IF(AP76>0, AP76*1%,0) | AU18: =IF(AT76>0, AT76*1%,0) | AV18: =IF(AU76>0, AU76*1%,0) | AW18: =IF(AV76>0, AV76*1%,0) | AX18: =IF(AW76>0, AW76*1%,0) | AY18: =IF(AX76>0, AX76*0.8%,0) | AZ18: =IF(AY76>0, AY76*0.8%,0) | BA18: =IF(AZ76>0, AZ76*0.8%,0) | BB18: =IF(BA76>0, BA76*0.8%,0) | BC18: =IF(BB76>0, BB76*0.8%,0) | BD18: =IF(BC76>0, BC76*0.8%,0) | BE18: =IF(BD76>0, BD76*0.8%,0) | BF18: =IF(BE76>0, BE76*0.8%,0) | ... HU18: =IF(HT76>0, HT76*0.8%,0) | JF18: =AP18 | JG18: =SUM(Z18:AK18) | JH18: =SUM(AL18:AP18) | JI18: =SUM(C18:AP18) | JM18: 125712.49 | JR18: =A18 | JS18: =SUM(C18:AP18) | JU18: =SUM(AT18:AZ18) | JV18: =SUM(BA18:BL18) | JW18: =SUM(BM18:BX18) | JX18: =SUM(BY18:CJ18) | JY18: =SUM(CK18:CV18) | JZ18: =SUM(CW18:HU18) | KG18: =B18 | KH18: =AR18
JF19: =AP19 | JG19: =SUM(Z19:AK19) | JH19: =SUM(AL19:AP19) | JI19: =SUM(C19:AP19) | JR19: =A19 | JS19: =SUM(C19:AP19) | JU19: =SUM(AT19:AZ19) | JV19: =SUM(BA19:BL19) | JW19: =SUM(BM19:BX19) | JX19: =SUM(BY19:CJ19) | JY19: =SUM(CK19:CV19) | JZ19: =SUM(CW19:HU19) | KG19: =B19 | KH19: =AR19
A20: TOTAL RECEITAS REAL (+) | B20: =SUM(C20:AP20) | C20: =SUM(C8+C9+C15+C18) | D20: =SUM(D8+D9+D15+D18) | E20: =SUM(E8+E9+E15+E18) | F20: =SUM(F8+F9+F12+F15+F18) | G20: =SUM(G8+G9+G12+G15+G18) | H20: =SUM(H8+H9+H12+H15+H18) | I20: =SUM(I8+I9+I12+I15+I18) | J20: =SUM(J8+J9+J15+J18) | K20: =SUM(K8+K9+K15+K18) | L20: =SUM(L8+L9+L15+L18) | M20: =SUM(M8+M9+M15+M18) | N20: =SUM(N8+N9+N15+N18) | O20: =SUM(O8+O9+O15+O18) | P20: =SUM(P8+P9+P15+P18) | Q20: =SUM(Q8+Q9+Q15+Q18) | ... AP20: =SUM(AP8+AP9+AP15+AP18) | AR20: =SUM(AT20:HU20) | AT20: =SUM(AT8+AT9+AT15+AT18) | AU20: =SUM(AU8+AU9+AU15+AU18) | AV20: =SUM(AV8+AV9+AV15+AV18) | AW20: =SUM(AW8+AW9+AW15+AW18) | AX20: =SUM(AX8+AX9+AX15+AX18) | AY20: =SUM(AY8+AY9+AY15+AY18) | AZ20: =SUM(AZ8+AZ9+AZ15+AZ18) | BA20: =SUM(BA8+BA9+BA15+BA18) | ... HU20: =SUM(HU8+HU9+HU15+HU18) | JF20: =AP20 | JG20: =SUM(Z20:AK20) | JH20: =SUM(AL20:AP20) | JI20: =SUM(C20:AP20) | JM20: 2140511.6 | JR20: =A20 | JS20: =SUM(C20:AP20) | JU20: =SUM(AT20:AZ20) | JV20: =SUM(BA20:BL20) | JW20: =SUM(BM20:BX20) | JX20: =SUM(BY20:CJ20) | JY20: =SUM(CK20:CV20) | JZ20: =SUM(CW20:HU20) | KG20: =B20 | KH20: =AR20
A21: TOTAL DE RECEITAS + PREVISÃO VENDAS | B21: =SUM(C21:AP21) | C21: =C12+C20 | D21: =D12+D20 | E21: =E12+E20 | F21: =F12+F20 | G21: =G12+G20 | H21: =H12+H20 | I21: =I12+I20 | J21: =J12+J9+J18+J15+J8 | K21: =K12+K9+K18+K15+K8 | L21: =L12+L9+L18+L15+L8 | M21: =M12+M9+M18+M15+M8 | N21: =N12+N9+N18+N15+N8 | O21: =O12+O9+O18+O15+O8 | P21: =P12+P9+P18+P15+P8 | Q21: =Q12+Q9+Q18+Q15+Q8 | ... AP21: =AP12+AP9+AP18+AP15+AP8 | AR21: =SUM(AT21:HU21) | AT21: =AT12+AT9+AT18+AT15+AT8 | AU21: =AU12+AU9+AU18+AU15+AU8 | AV21: =AV12+AV9+AV18+AV15+AV8 | AW21: =AW12+AW9+AW18+AW15+AW8 | AX21: =AX12+AX9+AX18+AX15+AX8 | AY21: =AY12+AY9+AY18+AY15+AY8 | AZ21: =AZ12+AZ9+AZ18+AZ15+AZ8 | BA21: =BA12+BA9+BA18+BA15+BA8 | ... HU21: =HU12+HU9+HU18+HU15+HU8 | JF21: =AP21 | JG21: =SUM(Z21:AK21) | JH21: =SUM(AL21:AP21) | JI21: =SUM(C21:AP21) | JM21: 2693524.8 | JR21: =A21 | JS21: =SUM(C21:AP21) | JU21: =SUM(AT21:AZ21) | JV21: =SUM(BA21:BL21) | JW21: =SUM(BM21:BX21) | JX21: =SUM(BY21:CJ21) | JY21: =SUM(CK21:CV21) | JZ21: =SUM(CW21:HU21) | KG21: =B21 | KH21: =AR21
JF22: =AP22 | JG22: =SUM(Z22:AK22) | JH22: =SUM(AL22:AP22) | JI22: =SUM(C22:AP22) | KG22: =B22 | KH22: =AR22
A23: DESPESAS OPERACIONAIS | JF23: =AP23 | JG23: =SUM(Z23:AK23) | JH23: =SUM(AL23:AP23) | JI23: =SUM(C23:AP23) | KG23: =B23 | KH23: =AR23
A24: DESPESAS COMERCIAIS(-) | JF24: =AP24 | JG24: =SUM(Z24:AK24) | JH24: =SUM(AL24:AP24) | JI24: =SUM(C24:AP24) | KG24: =B24 | KH24: =AR24
A25: Comissões S/ Venda (Equipe Interna) | B25: =SUM(C25:AP25) | AC25: =-128438.23-228.84 | AD25: -86736.99 | AE25: -82255.25 | AF25: -80040.85 | AG25: =-82521.74-1070.23 | AH25: =-114789.41-1258.17+78352.42 | AI25: =-37646.35-993.8 | AJ25: =-62577.85-603.53+41382.42 | AK25: =-37057.07-2155.37 | AL25: -87950.28 | AM25: =-80793.74-4080.62 | AN25: -59242.37 | AO25: =-85591.51-2480.85 | AP25: =-40733.2-1610.72 | AR25: =SUM(AT25:HU25) | AT25: -28685.08 | AU25: -28685.08 | AV25: -28685.08 | AW25: -28685.08 | AX25: -28685.08 | AY25: -28685.08 | AZ25: -28685.08 | BA25: -28685.08 | BB25: -28685.08 | BC25: -28685.08 | BD25: -28685.08 | BE25: -28685.08 | BF25: -28685.08 | BG25: -28685.08 | BH25: -28685.08 | BI25: -28685.08 | BJ25: -28685.08 | BK25: -28685.08 | BL25: -28685.08 | BM25: -28685.08 | BN25: -28685.08 | BO25: -28685.08 | BP25: -28685.08 | BQ25: -28685.08 | BR25: -28685.08 | BS25: -28685.08 | BT25: -28685.08 | BU25: -28685.08 | BV25: -28685.08 | BW25: -28685.08 | BX25: -28685.08 | BY25: -28685.08 | BZ25: -28685.08 | CA25: -15000 | CB25: -15000 | CC25: -15000 | CD25: -15000 | CE25: -15000 | CF25: -15000 | CG25: -15000 | CH25: -15000 | CI25: -15000 | CJ25: -15000 | CK25: -15000 | CL25: -15000 | CM25: -15000 | CN25: -15000 | CO25: -15000 | CP25: -15000 | CQ25: -15000 | CR25: -15000 | CS25: -15000 | CT25: -15000 | CU25: -15000 | CV25: -15000 | CW25: -15000 | CX25: -15000 | CY25: -15000 | CZ25: -15000 | DA25: -15000 | DB25: -15000 | DC25: -15000 | DD25: -15000 | DE25: -15000 | DF25: -15000 | DG25: -15000 | DH25: -15000 | DI25: -15000 | DJ25: -15000 | DK25: -15000 | DL25: -15000 | DM25: -15000 | DN25: -15000 | DO25: -15000 | DP25: -15000 | DQ25: -15000 | DS25: 0 | DT25: 0 | DU25: 0 | DV25: 0 | DW25: 0 | DX25: 0 | DY25: 0 | DZ25: 0 | EA25: 0 | EB25: 0 | EC25: 0 | ED25: 0 | EE25: 0 | EF25: 0 | EG25: 0 | EH25: 0 | EI25: 0 | EJ25: 0 | EK25: 0 | EL25: 0 | EM25: 0 | EN25: 0 | EO25: 0 | EP25: 0 | EQ25: 0 | ER25: 0 | ES25: 0 | ET25: 0 | EU25: 0 | EV25: 0 | EW25: 0 | EX25: 0 | EY25: 0 | EZ25: 0 | FA25: 0 | FB25: 0 | FC25: 0 | FD25: 0 | FE25: 0 | FF25: 0 | FG25: 0 | FH25: 0 | FI25: 0 | FJ25: 0 | FK25: 0 | FL25: 0 | FM25: 0 | FN25: 0 | FO25: 0 | FP25: 0 | FQ25: 0 | FR25: 0 | FS25: 0 | FT25: 0 | FU25: 0 | FV25: 0 | FW25: 0 | FX25: 0 | FY25: 0 | FZ25: 0 | GA25: 0 | GB25: 0 | GC25: 0 | GD25: 0 | GE25: 0 | GF25: 0 | GG25: 0 | GH25: 0 | GI25: 0 | GJ25: 0 | GK25: 0 | GL25: 0 | GM25: 0 | GN25: 0 | GO25: 0 | GP25: 0 | GQ25: 0 | GR25: 0 | GS25: 0 | GT25: 0 | GU25: 0 | GV25: 0 | GW25: 0 | GX25: 0 | GY25: 0 | GZ25: 0 | HA25: 0 | HB25: 0 | HC25: 0 | HD25: 0 | HE25: 0 | HF25: 0 | HG25: 0 | HH25: 0 | HI25: 0 | HJ25: 0 | HK25: 0 | HL25: 0 | HM25: 0 | HN25: 0 | HO25: 0 | HP25: 0 | HQ25: 0 | HR25: 0 | HS25: 0 | HT25: 0 | HU25: 0 | JF25: =AP25 | JG25: =SUM(Z25:AK25) | JH25: =SUM(AL25:AP25) | JI25: =SUM(C25:AP25) | JM25: -28685.08 | JS25: =+JS9+JS12 | JU25: =+JU9+JU12 | JV25: =+JV9+JV12 | JW25: =+JW9+JW12 | JX25: =+JX9+JX12 | JY25: =+JY9+JY12 | JZ25: =+JZ9+JZ12 | KG25: =B25 | KH25: =AR25
A26: Stand de Venda - Manutenção | B26: =SUM(C26:AP26) | W26: -34442.6 | X26: -422668.9 | Y26: -260275.15 | Z26: -364851.06 | AA26: -241871.81 | AB26: -456303.01 | AC26: =-66426.55-83395.55-107752.3 | AD26: -81306.34 | AE26: -75796.13 | AF26: -59026.11 | AG26: -44076.02 | AH26: -65441.81 | AI26: -74949.34 | AJ26: -74150.16 | AK26: =-81019.72+17900 | AL26: -79367.71 | AM26: -76750.58 | AN26: -65331.12 | AO26: -98723.83 | AP26: -70580.67 | AR26: =SUM(AT26:HU26) | AT26: -55000 | AU26: -55000 | AV26: -55000 | AW26: -55000 | AX26: -55000 | AY26: -55000 | AZ26: -55000 | BA26: -55000 | BB26: -55000 | BC26: -55000 | BD26: -55000 | BE26: -55000 | BF26: -55000 | BG26: -55000 | BH26: -55000 | BI26: -55000 | BJ26: -55000 | BK26: -55000 | BL26: -55000 | BM26: -55000 | BN26: -55000 | BO26: -55000 | BP26: -55000 | BQ26: 0 | BR26: 0 | BS26: 0 | BT26: 0 | BU26: 0 | BV26: 0 | BW26: 0 | BX26: 0 | BY26: 0 | BZ26: 0 | CA26: 0 | CB26: 0 | CC26: 0 | CD26: 0 | CE26: 0 | CF26: 0 | CG26: 0 | CH26: 0 | CI26: 0 | CJ26: 0 | CK26: 0 | CL26: 0 | CM26: 0 | CN26: 0 | CO26: 0 | CP26: 0 | CQ26: 0 | CR26: 0 | CS26: 0 | CT26: 0 | CU26: 0 | CV26: 0 | CW26: 0 | CX26: 0 | CY26: 0 | CZ26: 0 | DA26: 0 | DB26: 0 | DC26: 0 | DD26: 0 | DE26: 0 | DF26: 0 | DG26: 0 | DH26: 0 | DI26: 0 | DJ26: 0 | DK26: 0 | DL26: 0 | DM26: 0 | DN26: 0 | DO26: 0 | DP26: 0 | DQ26: 0 | DR26: 0 | DS26: 0 | DT26: 0 | DU26: 0 | DV26: 0 | DW26: 0 | DX26: 0 | DY26: 0 | DZ26: 0 | EA26: 0 | EB26: 0 | EC26: 0 | ED26: 0 | EE26: 0 | EF26: 0 | EG26: 0 | EH26: 0 | EI26: 0 | EJ26: 0 | EK26: 0 | EL26: 0 | EM26: 0 | EN26: 0 | EO26: 0 | EP26: 0 | EQ26: 0 | ER26: 0 | ES26: 0 | ET26: 0 | EU26: 0 | EV26: 0 | EW26: 0 | EX26: 0 | EY26: 0 | EZ26: 0 | FA26: 0 | FB26: 0 | FC26: 0 | FD26: 0 | FE26: 0 | FF26: 0 | FG26: 0 | FH26: 0 | FI26: 0 | FJ26: 0 | FK26: 0 | FL26: 0 | FM26: 0 | FN26: 0 | FO26: 0 | FP26: 0 | FQ26: 0 | FR26: 0 | FS26: 0 | FT26: 0 | FU26: 0 | FV26: 0 | FW26: 0 | FX26: 0 | FY26: 0 | FZ26: 0 | GA26: 0 | GB26: 0 | GC26: 0 | GD26: 0 | GE26: 0 | GF26: 0 | GG26: 0 | GH26: 0 | GI26: 0 | GJ26: 0 | GK26: 0 | GL26: 0 | GM26: 0 | GN26: 0 | GO26: 0 | GP26: 0 | GQ26: 0 | GR26: 0 | GS26: 0 | GT26: 0 | GU26: 0 | GV26: 0 | GW26: 0 | GX26: 0 | GY26: 0 | GZ26: 0 | HA26: 0 | HB26: 0 | HC26: 0 | HD26: 0 | HE26: 0 | HF26: 0 | HG26: 0 | HH26: 0 | HI26: 0 | HJ26: 0 | HK26: 0 | HL26: 0 | HM26: 0 | HN26: 0 | HO26: 0 | HP26: 0 | HQ26: 0 | HR26: 0 | HS26: 0 | HT26: 0 | HU26: 0 | JF26: =AP26 | JG26: =SUM(Z26:AK26) | JH26: =SUM(AL26:AP26) | JI26: =SUM(C26:AP26) | JM26: -55000 | KG26: =B26 | KH26: =AR26
A27: Marketing | B27: =SUM(C27:AP27) | W27: -32159.95 | X27: -30740 | Y27: -18988.62 | Z27: -196816.01 | AA27: -308461.65 | AB27: -387396.3 | AC27: -264220.34 | AD27: -187387.35 | AE27: -142662.13 | AF27: =-121163.48+959.8 | AG27: =-101944.3+959.8 | AH27: =-94040.76-9315.02 | AI27: -184088.23 | AJ27: -148907.24 | AK27: =-148676.77-17900 | AL27: -280720.57 | AM27: -80116.73 | AN27: -140928.2 | AO27: -132699.9 | AP27: -161932.68 | AR27: =SUM(AT27:HU27) | AT27: -166659.27 | AU27: -166659.27 | AV27: -166659.27 | AW27: -166659.27 | AX27: -166659.27 | AY27: -166659.27 | AZ27: -166659.27 | BA27: -83329.635 | BB27: -83329.635 | BC27: -83329.635 | BD27: -83329.635 | BE27: -83329.635 | BF27: -83329.635 | BG27: -83329.635 | BH27: -83329.635 | BI27: -83329.635 | BJ27: -83329.635 | BK27: -83329.635 | BL27: -83329.635 | BM27: -83329.635 | BN27: -83329.635 | BO27: -83329.635 | BP27: -83329.635 | BQ27: -83329.635 | BR27: -83329.635 | BS27: -83329.635 | BT27: -83329.635 | BU27: -83329.635 | BV27: -83329.635 | BW27: -83329.635 | BX27: -83329.635 | BY27: -83329.635 | BZ27: -83329.635 | CA27: -83329.635 | CB27: -83329.635 | CC27: -83329.635 | CD27: -83329.635 | CE27: -83329.635 | CF27: -83329.635 | CG27: -83329.635 | CH27: -83329.635 | CI27: -83329.635 | CJ27: -83329.635 | CK27: -83329.635 | CL27: -83329.635 | CM27: -83329.635 | CN27: -83329.635 | CO27: -83329.635 | CP27: -83329.635 | CQ27: -83329.635 | CR27: -83329.635 | CS27: -83329.635 | CT27: -83329.635 | CU27: -83329.635 | CV27: -83329.635 | CW27: -83329.635 | CX27: -83329.635 | CY27: -83329.635 | CZ27: -83329.635 | DA27: -83329.635 | DB27: -83329.635 | DC27: -83329.635 | DD27: -83329.635 | DE27: -83329.635 | DF27: -83329.635 | DG27: -83329.635 | DH27: -83329.635 | DI27: -83329.635 | DS27: 0 | DT27: 0 | DU27: 0 | DV27: 0 | DW27: 0 | DX27: 0 | DY27: 0 | DZ27: 0 | EA27: 0 | EC27: 0 | ED27: 0 | EE27: 0 | EF27: 0 | EG27: 0 | EH27: 0 | EI27: 0 | EJ27: 0 | EK27: 0 | EL27: 0 | EM27: 0 | EN27: 0 | EO27: 0 | EP27: 0 | EQ27: 0 | ER27: 0 | ES27: 0 | ET27: 0 | EU27: 0 | EV27: 0 | EW27: 0 | EX27: 0 | EY27: 0 | EZ27: 0 | FA27: 0 | FB27: 0 | FC27: 0 | FD27: 0 | FE27: 0 | FF27: 0 | FG27: 0 | FH27: 0 | FI27: 0 | FJ27: 0 | FK27: 0 | FL27: 0 | FM27: 0 | FN27: 0 | FO27: 0 | FP27: 0 | FQ27: 0 | FR27: 0 | FS27: 0 | FT27: 0 | FU27: 0 | FV27: 0 | FW27: 0 | FX27: 0 | FY27: 0 | FZ27: 0 | GA27: 0 | GB27: 0 | GC27: 0 | GD27: 0 | GE27: 0 | GF27: 0 | GG27: 0 | GH27: 0 | GI27: 0 | GJ27: 0 | GK27: 0 | GL27: 0 | GM27: 0 | GN27: 0 | GO27: 0 | GP27: 0 | GQ27: 0 | GR27: 0 | GS27: 0 | GT27: 0 | GU27: 0 | GV27: 0 | GW27: 0 | GX27: 0 | GY27: 0 | GZ27: 0 | HA27: 0 | HB27: 0 | HC27: 0 | HD27: 0 | HE27: 0 | HF27: 0 | HG27: 0 | HH27: 0 | HI27: 0 | HJ27: 0 | HK27: 0 | HL27: 0 | HM27: 0 | HN27: 0 | HO27: 0 | HP27: 0 | HQ27: 0 | HR27: 0 | HS27: 0 | HT27: 0 | HU27: 0 | JF27: =AP27 | JG27: =SUM(Z27:AK27) | JH27: =SUM(AL27:AP27) | JI27: =SUM(C27:AP27) | JM27: -166659.27 | KG27: =B27 | KH27: =AR27
B28: =SUM(C28:AP28) | AR28: =SUM(AT28:HU28) | DL28: 0 | DM28: 0 | DN28: 0 | DO28: 0 | DP28: 0 | DQ28: 0 | DR28: 0 | DS28: 0 | DT28: 0 | DU28: 0 | DV28: 0 | DW28: 0 | DX28: 0 | DY28: 0 | DZ28: 0 | EA28: 0 | EB28: 0 | EC28: 0 | ED28: 0 | EE28: 0 | EF28: 0 | EG28: 0 | EH28: 0 | EI28: 0 | EJ28: 0 | EK28: 0 | EL28: 0 | EM28: 0 | EN28: 0 | EO28: 0 | EP28: 0 | EQ28: 0 | ER28: 0 | ES28: 0 | ET28: 0 | EU28: 0 | EV28: 0 | EW28: 0 | EX28: 0 | EY28: 0 | EZ28: 0 | FA28: 0 | FB28: 0 | FC28: 0 | FD28: 0 | FE28: 0 | FF28: 0 | FG28: 0 | FH28: 0 | FI28: 0 | FJ28: 0 | FK28: 0 | FL28: 0 | FM28: 0 | FN28: 0 | FO28: 0 | FP28: 0 | FQ28: 0 | FR28: 0 | FS28: 0 | FT28: 0 | FU28: 0 | FV28: 0 | FW28: 0 | FX28: 0 | FY28: 0 | FZ28: 0 | GA28: 0 | GB28: 0 | GC28: 0 | GD28: 0 | GE28: 0 | GF28: 0 | GG28: 0 | GH28: 0 | GI28: 0 | GJ28: 0 | GK28: 0 | GL28: 0 | GM28: 0 | GN28: 0 | GO28: 0 | GP28: 0 | GQ28: 0 | GR28: 0 | GS28: 0 | GT28: 0 | GU28: 0 | GV28: 0 | GW28: 0 | GX28: 0 | GY28: 0 | GZ28: 0 | HA28: 0 | HB28: 0 | HC28: 0 | HD28: 0 | HE28: 0 | HF28: 0 | HG28: 0 | HH28: 0 | HI28: 0 | HJ28: 0 | HK28: 0 | HL28: 0 | HM28: 0 | HN28: 0 | HO28: 0 | HP28: 0 | HQ28: 0 | HR28: 0 | HS28: 0 | HT28: 0 | HU28: 0 | JF28: =AP28 | JG28: =SUM(Z28:AK28) | JH28: =SUM(AL28:AP28) | JI28: =SUM(C28:AP28) | KG28: =B28 | KH28: =AR28
A29: Subtotal | B29: =SUM(C29:AP29) | C29: =SUM(C25:C28) | D29: =SUM(D25:D28) | E29: =SUM(E25:E28) | F29: =SUM(F25:F28) | G29: =SUM(G25:G28) | H29: =SUM(H25:H28) | I29: =SUM(I25:I28) | J29: =SUM(J25:J28) | ... AP29: =SUM(AP25:AP28) | AR29: =SUM(AT29:HU29) | AT29: =SUM(AT25:AT28) | AU29: =SUM(AU25:AU28) | AV29: =SUM(AV25:AV28) | AW29: =SUM(AW25:AW28) | AX29: =SUM(AX25:AX28) | AY29: =SUM(AY25:AY28) | AZ29: =SUM(AZ25:AZ28) | BA29: =SUM(BA25:BA28) | ... HU29: =SUM(HU25:HU28) | JF29: =AP29 | JG29: =SUM(Z29:AK29) | JH29: =SUM(AL29:AP29) | JI29: =SUM(C29:AP29) | JM29: -250344.35 | KG29: =B29 | KH29: =AR29
JF30: =AP30 | JG30: =SUM(Z30:AK30) | JH30: =SUM(AL30:AP30) | JI30: =SUM(C30:AP30) | KG30: =B30 | KH30: =AR30
A31: ITBI + IPTU ESTOQUE(-) | JF31: =AP31 | JG31: =SUM(Z31:AK31) | JH31: =SUM(AL31:AP31) | JI31: =SUM(C31:AP31) | KG31: =B31 | KH31: =AR31
A32: ITBI | B32: =SUM(C32:AP32) | AD32: =-425723.20325 | AE32: -169878.95 | AF32: -233674.3 | AG32: -164053.77 | AH32: -88145.01 | AI32: -72316.23 | AJ32: -116408.21 | AK32: -93487.63 | AL32: -225000.78 | AM32: -144626.49 | AN32: -113015.4 | AO32: -73115.61 | AP32: -100151.9 | AR32: =SUM(AT32:HU32) | AT32: =-(B8+B32)/3 | AU32: =AT32 | AV32: =AU32 | AW32: 0 | AX32: 0 | AY32: 0 | AZ32: 0 | BA32: 0 | BB32: 0 | BC32: 0 | BD32: 0 | BE32: 0 | BF32: 0 | BG32: 0 | BH32: 0 | BI32: 0 | BJ32: 0 | BK32: 0 | BL32: 0 | BM32: 0 | BN32: 0 | BO32: 0 | BP32: 0 | BQ32: 0 | BR32: 0 | BS32: 0 | BT32: 0 | BU32: 0 | BV32: 0 | BW32: 0 | BX32: 0 | BY32: 0 | BZ32: 0 | CA32: 0 | CB32: 0 | CC32: 0 | CD32: 0 | CE32: 0 | CF32: 0 | CG32: 0 | CH32: 0 | CI32: 0 | CJ32: 0 | CK32: 0 | CL32: 0 | CM32: 0 | CN32: 0 | CO32: 0 | CP32: 0 | CQ32: 0 | CR32: 0 | CS32: 0 | CT32: 0 | CU32: 0 | CV32: 0 | CW32: 0 | CX32: 0 | CY32: 0 | CZ32: 0 | DA32: 0 | DB32: 0 | DC32: 0 | DD32: 0 | DE32: 0 | DF32: 0 | DG32: 0 | DH32: 0 | DI32: 0 | DJ32: 0 | DK32: 0 | DL32: 0 | DM32: 0 | DN32: 0 | DO32: 0 | DP32: 0 | DQ32: 0 | DR32: 0 | DS32: 0 | DT32: 0 | DU32: 0 | DV32: 0 | DW32: 0 | DX32: 0 | DY32: 0 | DZ32: 0 | EA32: 0 | EB32: 0 | EC32: 0 | ED32: 0 | EE32: 0 | EF32: 0 | EG32: 0 | EH32: 0 | EI32: 0 | EJ32: 0 | EK32: 0 | EL32: 0 | EM32: 0 | EN32: 0 | EO32: 0 | EP32: 0 | EQ32: 0 | ER32: 0 | ES32: 0 | ET32: 0 | EU32: 0 | EV32: 0 | EW32: 0 | EX32: 0 | EY32: 0 | EZ32: 0 | FA32: 0 | FB32: 0 | FC32: 0 | FD32: 0 | FE32: 0 | FF32: 0 | FG32: 0 | FH32: 0 | FI32: 0 | FJ32: 0 | FK32: 0 | FL32: 0 | FM32: 0 | FN32: 0 | FO32: 0 | FP32: 0 | FQ32: 0 | FR32: 0 | FS32: 0 | FT32: 0 | FU32: 0 | FV32: 0 | FW32: 0 | FX32: 0 | FY32: 0 | FZ32: 0 | GA32: 0 | GB32: 0 | GC32: 0 | GD32: 0 | GE32: 0 | GF32: 0 | GG32: 0 | GH32: 0 | GI32: 0 | GJ32: 0 | GK32: 0 | GL32: 0 | GM32: 0 | GN32: 0 | GO32: 0 | GP32: 0 | GQ32: 0 | GR32: 0 | GS32: 0 | GT32: 0 | GU32: 0 | GV32: 0 | GW32: 0 | GX32: 0 | GY32: 0 | GZ32: 0 | HA32: 0 | HB32: 0 | HC32: 0 | HD32: 0 | HE32: 0 | HF32: 0 | HG32: 0 | HH32: 0 | HI32: 0 | HJ32: 0 | HK32: 0 | HL32: 0 | HM32: 0 | HN32: 0 | HO32: 0 | HP32: 0 | HQ32: 0 | HR32: 0 | HS32: 0 | HT32: 0 | HU32: 0 | JF32: =AP32 | JG32: =SUM(Z32:AK32) | JH32: =SUM(AL32:AP32) | JI32: =SUM(C32:AP32) | JM32: -131508.27 | KG32: =B32 | KH32: =AR32
A33: IPTU Estoque | B33: =SUM(C33:AP33) | AE33: -63859.04 | AF33: -62215.4 | AG33: -62215.4 | AH33: -60545.9 | AI33: -61966.65 | AJ33: -58978.75 | AK33: -56594.14 | AN33: -38399.02 | AO33: -38162.09 | AP33: -37873.25 | AR33: =SUM(AT33:HU33) | AT33: -29841 | AU33: -29326.5 | AV33: -28812 | AW33: -28297.5 | AX33: -27783 | AY33: -27268.5 | AZ33: -26754 | BA33: -26239.5 | BB33: -25725 | BC33: -25210.5 | BD33: -24696 | BE33: -24181.5 | BF33: -23667 | BG33: -23152.5 | BH33: -90552 | BI33: -88494 | BJ33: -86436 | BK33: -84378 | BL33: -82320 | BM33: -80262 | BN33: -78204 | BO33: -76146 | BP33: -74088 | BQ33: -72030 | BR33: -69972 | BS33: -67914 | BT33: -65856 | BU33: -63798 | BV33: -61740 | BW33: -59682 | BX33: -57624 | BY33: -55566 | BZ33: -53508 | CA33: -51450 | CB33: -49392 | CC33: -47334 | CD33: -45276 | CE33: -43218 | CF33: -41160 | CG33: -39102 | CH33: -37044 | CI33: -34986 | CJ33: -32928 | CK33: -30870 | CL33: -28812 | CM33: -26754 | CN33: -24696 | CO33: -22638 | CP33: -20580 | CQ33: -18522 | CR33: -16464 | CS33: -14406 | CT33: -12348 | CU33: -10290 | CV33: -8232 | CW33: -6174 | CX33: -4116 | CY33: -2058 | CZ33: 0 | DA33: 0 | DB33: 0 | DC33: 0 | DD33: 0 | DE33: 0 | DF33: 0 | DG33: 0 | DH33: 0 | DI33: 0 | DJ33: 0 | DK33: 0 | DL33: 0 | DM33: 0 | DN33: 0 | DO33: 0 | DP33: 0 | DQ33: 0 | DR33: 0 | DS33: 0 | DT33: 0 | DU33: 0 | DV33: 0 | DW33: 0 | DX33: 0 | DY33: 0 | DZ33: 0 | EA33: 0 | EB33: 0 | EC33: 0 | ED33: 0 | EE33: 0 | EF33: 0 | EG33: 0 | EH33: 0 | EI33: 0 | GU33: 0 | GV33: 0 | GW33: 0 | GX33: 0 | GY33: 0 | GZ33: 0 | HA33: 0 | HB33: 0 | HC33: 0 | HD33: 0 | HE33: 0 | HF33: 0 | HG33: 0 | HH33: 0 | HI33: 0 | HJ33: 0 | HK33: 0 | HL33: 0 | HM33: 0 | HN33: 0 | HO33: 0 | HP33: 0 | HQ33: 0 | HR33: 0 | HS33: 0 | HT33: 0 | HU33: 0 | JF33: =AP33 | JG33: =SUM(Z33:AK33) | JH33: =SUM(AL33:AP33) | JI33: =SUM(C33:AP33) | JM33: -30502.5 | KG33: =B33 | KH33: =AR33
A34: Condominio Estoque | B34: =SUM(C34:AP34) | AR34: =SUM(AT34:HU34) | AT34: 0 | AU34: 0 | AV34: 0 | AW34: 0 | AX34: 0 | AY34: 0 | AZ34: 0 | BA34: 0 | BB34: 0 | BC34: 0 | BD34: 0 | BE34: 0 | BF34: 0 | BG34: 0 | BH34: -308000 | BI34: -301000 | BJ34: -294000 | BK34: -287000 | BL34: -280000 | BM34: -273000 | BN34: -266000 | BO34: -259000 | BP34: -252000 | BQ34: -245000 | BR34: -238000 | BS34: -231000 | BT34: -224000 | BU34: -217000 | BV34: -210000 | BW34: -203000 | BX34: -196000 | BY34: -189000 | BZ34: -182000 | CA34: -175000 | CB34: -168000 | CC34: -161000 | CD34: -154000 | CE34: -147000 | CF34: -140000 | CG34: -133000 | CH34: -126000 | CI34: -119000 | CJ34: -112000 | CK34: -105000 | CL34: -98000 | CM34: -91000 | CN34: -84000 | CO34: -77000 | CP34: -70000 | CQ34: -63000 | CR34: -39200 | CS34: -34300 | CT34: -29400 | CU34: -24500 | CV34: -19600 | CW34: -14700 | CX34: -9800 | CY34: -4900 | CZ34: 0 | DA34: 0 | DB34: 0 | DC34: 0 | DD34: 0 | DE34: 0 | DF34: 0 | DG34: 0 | DH34: 0 | DI34: 0 | DJ34: 0 | DK34: 0 | DL34: 0 | DM34: 0 | DN34: 0 | DO34: 0 | DP34: 0 | DQ34: 0 | DR34: 0 | DS34: 0 | DT34: 0 | DU34: 0 | DV34: 0 | DW34: 0 | DX34: 0 | DY34: 0 | DZ34: 0 | EA34: 0 | EB34: 0 | EC34: 0 | ED34: 0 | EE34: 0 | EF34: 0 | EG34: 0 | EH34: 0 | EI34: 0 | GU34: 0 | GV34: 0 | GW34: 0 | GX34: 0 | GY34: 0 | GZ34: 0 | HA34: 0 | HB34: 0 | HC34: 0 | HD34: 0 | HE34: 0 | HF34: 0 | HG34: 0 | HH34: 0 | HI34: 0 | HJ34: 0 | HK34: 0 | HL34: 0 | HM34: 0 | HN34: 0 | HO34: 0 | HP34: 0 | HQ34: 0 | HR34: 0 | HS34: 0 | HT34: 0 | HU34: 0 | JF34: =AP34 | JG34: =SUM(Z34:AK34) | JH34: =SUM(AL34:AP34) | JI34: =SUM(C34:AP34) | JM34: 0 | KG34: =B34 | KH34: =AR34
A35: Subtotal | B35: =SUM(C35:AP35) | C35: =SUM(C32:C33) | D35: =SUM(D32:D33) | E35: =SUM(E32:E33) | F35: =SUM(F32:F33) | G35: =SUM(G32:G33) | H35: =SUM(H32:H33) | I35: =SUM(I32:I33) | J35: =SUM(J32:J33) | ... R35: =SUM(R32:R33) | T35: =SUM(T32:T33) | U35: =SUM(U32:U33) | V35: =SUM(V32:V33) | W35: =SUM(W32:W33) | X35: =SUM(X32:X33) | Y35: =SUM(Y32:Y33) | Z35: =SUM(Z32:Z33) | AA35: =SUM(AA32:AA33) | ... AP35: =SUM(AP32:AP33) | AR35: =SUM(AT35:HU35) | AT35: =SUM(AT32:AT34) | AU35: =SUM(AU32:AU34) | AV35: =SUM(AV32:AV34) | AW35: =SUM(AW32:AW34) | AX35: =SUM(AX32:AX34) | AY35: =SUM(AY32:AY34) | AZ35: =SUM(AZ32:AZ34) | BA35: =SUM(BA32:BA34) | ... HU35: =SUM(HU32:HU34) | JF35: =AP35 | JG35: =SUM(Z35:AK35) | JH35: =SUM(AL35:AP35) | JI35: =SUM(C35:AP35) | JM35: -162010.77 | KG35: =B35 | KH35: =AR35
JF36: =AP36 | JG36: =SUM(Z36:AK36) | JH36: =SUM(AL36:AP36) | JI36: =SUM(C36:AP36) | KG36: =B36 | KH36: =AR36
A37: DESPESAS DE OBRA (-) | Projeto (-) | JF37: =AP37 | JG37: =SUM(Z37:AK37) | JH37: =SUM(AL37:AP37) | JI37: =SUM(C37:AP37) | KG37: =B37 | KH37: =AR37
A38: OBRA - (revisão ABRIL/26) | B38: =SUM(C38:AP38) | AC38: =-124003.31+107752.3 | AD38: -15360 | AE38: -494572.5 | AF38: -570102.18 | AG38: -1543804.4 | AH38: -1436152.9 | AI38: -1462529.7 | AJ38: =-2392797.39-19000 | AK38: =-3640788.84+55000 | AL38: =-2865171.27+29261.06 | AM38: -798176.19 | AN38: -1093169.7 | AO38: -1975027.4 | AP38: -3609373.3 | AR38: =SUM(AT38:HU38) | AT38: -6186623.5 | AU38: -6156623.5 | AV38: =-4814839.46-224972.62-137837.64 | AW38: -5312619.5 | AX38: -5169839.5 | AY38: -4677099.7 | AZ38: -4782099.7 | BA38: -2312321.5 | BB38: -2710771.5 | BC38: -2241943 | BD38: -2091426.8 | BE38: -1213525 | BF38: -2251060.7 | BG38: -743916.67 | BH38: -918916.67 | BI38: -918916.67 | BJ38: -918916.67 | BK38: -918916.67 | BL38: -1001416.7 | BM38: -1216416.7 | BN38: -1216416.7 | BO38: -2983083.3 | BP38: -2983083.3 | BQ38: -2768083.3 | JF38: =AP38 | JG38: =SUM(Z38:AK38) | JH38: =SUM(AL38:AP38) | JI38: =SUM(C38:AP38) | JM38: -3747210.9 | KG38: =B38 | KH38: =AR38
A39: Verba de pós obra | B39: =SUM(C39:AP39) | AR39: =SUM(AT39:HU39) | AT39: 0 | AU39: 0 | AV39: 0 | AW39: 0 | AX39: 0 | AY39: 0 | AZ39: 0 | BA39: 0 | BB39: 0 | BC39: 0 | BD39: 0 | BE39: 0 | BF39: 0 | BG39: 0 | BH39: 0 | BI39: 0 | BJ39: 0 | BK39: 0 | BL39: 0 | BM39: 0 | BN39: 0 | BO39: 0 | BP39: -74113.021 | BQ39: -74113.021 | BR39: -74113.021 | BS39: -74113.021 | BT39: -74113.021 | BU39: -74113.021 | BV39: -74113.021 | BW39: -74113.021 | BX39: -74113.021 | BY39: -74113.021 | BZ39: -74113.021 | CA39: -74113.021 | CB39: -74113.021 | CC39: -74113.021 | CD39: -74113.021 | CE39: -74113.021 | CF39: -74113.021 | CG39: -74113.021 | CH39: -74113.021 | CI39: -74113.021 | CJ39: -74113.021 | CK39: -74113.021 | CL39: -74113.021 | CM39: -74113.021 | JH39: =SUM(AL39:AP39) | JM39: 0 | KG39: =B39 | KH39: =AR39
A40: CONTRAPARTIDA SAAE | B40: =SUM(C40:AP40) | AR40: =SUM(AT40:HU40) | AT40: 0 | AU40: 0 | AV40: 0 | AW40: 0 | AX40: 0 | AY40: 0 | AZ40: 0 | BA40: 0 | BB40: 0 | BC40: 0 | BD40: 0 | BE40: =-1279528.22*1.05 | BF40: 0 | BG40: 0 | BH40: 0 | BI40: 0 | BJ40: 0 | BK40: 0 | BL40: 0 | BM40: 0 | BN40: 0 | BO40: 0 | BP40: 0 | BQ40: 0 | BR40: 0 | BS40: 0 | BT40: 0 | BU40: 0 | BV40: 0 | BW40: 0 | BX40: 0 | BY40: 0 | BZ40: 0 | CA40: 0 | CB40: 0 | CC40: 0 | CD40: 0 | CE40: 0 | CF40: 0 | CG40: 0 | CH40: 0 | CI40: 0 | CJ40: 0 | CK40: 0 | CL40: 0 | CM40: 0 | CN40: 0 | CO40: 0 | CP40: 0 | CQ40: 0 | CR40: 0 | CS40: 0 | CT40: 0 | CU40: 0 | CV40: 0 | CW40: 0 | CX40: 0 | CY40: 0 | CZ40: 0 | DA40: 0 | DB40: 0 | DC40: 0 | DD40: 0 | DE40: 0 | DF40: 0 | DG40: 0 | DH40: 0 | DI40: 0 | DJ40: 0 | DK40: 0 | DL40: 0 | DM40: 0 | DN40: 0 | DO40: 0 | DP40: 0 | DQ40: 0 | DR40: 0 | DS40: 0 | DT40: 0 | DU40: 0 | DV40: 0 | DW40: 0 | DX40: 0 | DY40: 0 | DZ40: 0 | EA40: 0 | EB40: 0 | EC40: 0 | ED40: 0 | EE40: 0 | EF40: 0 | EG40: 0 | EH40: 0 | EI40: 0 | EJ40: 0 | EK40: 0 | EL40: 0 | EM40: 0 | EN40: 0 | EO40: 0 | EP40: 0 | EQ40: 0 | ER40: 0 | ES40: 0 | ET40: 0 | EU40: 0 | EV40: 0 | EW40: 0 | EX40: 0 | EY40: 0 | EZ40: 0 | FA40: 0 | FB40: 0 | FC40: 0 | FD40: 0 | FE40: 0 | FF40: 0 | FG40: 0 | FH40: 0 | FI40: 0 | FJ40: 0 | FK40: 0 | FL40: 0 | FM40: 0 | FN40: 0 | FO40: 0 | FP40: 0 | FQ40: 0 | FR40: 0 | FS40: 0 | FT40: 0 | FU40: 0 | FV40: 0 | FW40: 0 | FX40: 0 | FY40: 0 | FZ40: 0 | GA40: 0 | GB40: 0 | GC40: 0 | GD40: 0 | GE40: 0 | GF40: 0 | GG40: 0 | GH40: 0 | GI40: 0 | GJ40: 0 | GK40: 0 | GL40: 0 | GM40: 0 | GN40: 0 | GO40: 0 | GP40: 0 | GQ40: 0 | GR40: 0 | GS40: 0 | GT40: 0 | GU40: 0 | GV40: 0 | GW40: 0 | GX40: 0 | GY40: 0 | GZ40: 0 | HA40: 0 | HB40: 0 | HC40: 0 | HD40: 0 | HE40: 0 | HF40: 0 | HG40: 0 | HH40: 0 | HI40: 0 | HJ40: 0 | HK40: 0 | HL40: 0 | HM40: 0 | HN40: 0 | HO40: 0 | HP40: 0 | HQ40: 0 | HR40: 0 | HS40: 0 | HT40: 0 | HU40: 0 | JF40: =AP40 | JG40: =SUM(Z40:AK40) | JH40: =SUM(AL40:AP40) | JI40: =SUM(C40:AP40) | JM40: 0 | KG40: =B40 | KH40: =AR40
JF41: =AP41 | JG41: =SUM(Z41:AK41) | JH41: =SUM(AL41:AP41) | JI41: =SUM(C41:AP41) | KG41: =B41 | KH41: =AR41
A42: INCORPORAÇÃO (-) | JF42: =AP42 | JG42: =SUM(Z42:AK42) | JH42: =SUM(AL42:AP42) | JI42: =SUM(C42:AP42) | KG42: =B42 | KH42: =AR42
A43: Incorporação | B43: =SUM(C43:AP43) | C43: -22569.84 | D43: -66761.36 | E43: -22685 | F43: -22753.06 | G43: -22784.91 | H43: -25995.64 | I43: -23082.07 | J43: -23105.15 | K43: -28144.43 | L43: -28223.13 | M43: -28269.57 | N43: -28285.85 | O43: -30358.04 | P43: -28421.11 | Q43: -51733.24 | R43: -57539.95 | S43: -30362.5 | T43: -56077.16 | U43: -30362.5 | V43: -98850 | W43: -36362.5 | X43: -645250.94 | Y43: -280557.39 | Z43: -29760.76 | AA43: =(-184611.43)+-24760.76 | AB43: -90439.16 | AC43: =-49101.24-49521.52 | AD43: -49311.19 | AE43: -34527.34 | AF43: -72132.68 | AG43: -18449.64 | AH43: =-19109.04+9315.02 | AI43: -16205.14 | AJ43: =-54116.08+19000 | AK43: -8356.98 | AL43: -7658.2 | AM43: -10641.73 | AN43: =-40182.18+30654.55 | AO43: =-63943+29012.57+24791.61 | AP43: -11728.44 | AR43: =SUM(AT43:HU43) | AT43: -8000 | AU43: -8000 | AV43: -8000 | AW43: -8000 | AX43: -8000 | AY43: -8000 | AZ43: -8000 | BA43: -8000 | BB43: -8000 | BC43: -8000 | BD43: -8000 | BE43: -8000 | BF43: -8000 | BG43: -8000 | BH43: -8000 | BI43: -8000 | BJ43: -8000 | BK43: -8000 | BL43: -8000 | BM43: -8000 | BN43: -8000 | BO43: -8000 | BP43: -8000 | BQ43: -8000 | BR43: -8000 | DY43: 0 | DZ43: 0 | EA43: 0 | EB43: 0 | EC43: 0 | ED43: 0 | EE43: 0 | EF43: 0 | EG43: 0 | EH43: 0 | EI43: 0 | EJ43: 0 | EK43: 0 | EL43: 0 | EM43: 0 | EN43: 0 | EO43: 0 | EP43: 0 | EQ43: 0 | ER43: 0 | ES43: 0 | ET43: 0 | EU43: 0 | EV43: 0 | EW43: 0 | EX43: 0 | EY43: 0 | EZ43: 0 | FA43: 0 | FB43: 0 | FC43: 0 | FD43: 0 | FE43: 0 | FF43: 0 | FG43: 0 | FH43: 0 | FI43: 0 | FJ43: 0 | FK43: 0 | FL43: 0 | FM43: 0 | FN43: 0 | FO43: 0 | FP43: 0 | FQ43: 0 | FR43: 0 | FS43: 0 | FT43: 0 | FU43: 0 | FV43: 0 | FW43: 0 | FX43: 0 | FY43: 0 | FZ43: 0 | GA43: 0 | GB43: 0 | GC43: 0 | GD43: 0 | GE43: 0 | GF43: 0 | GG43: 0 | GH43: 0 | GI43: 0 | GJ43: 0 | GK43: 0 | GL43: 0 | GM43: 0 | GN43: 0 | GO43: 0 | GP43: 0 | GQ43: 0 | GR43: 0 | GS43: 0 | GT43: 0 | GU43: 0 | GV43: 0 | GW43: 0 | GX43: 0 | GY43: 0 | GZ43: 0 | HA43: 0 | HB43: 0 | HC43: 0 | HD43: 0 | HE43: 0 | HF43: 0 | HG43: 0 | HH43: 0 | HI43: 0 | HJ43: 0 | HK43: 0 | HL43: 0 | HM43: 0 | HN43: 0 | HO43: 0 | HP43: 0 | HQ43: 0 | HR43: 0 | HS43: 0 | HT43: 0 | HU43: 0 | JF43: =AP43 | JG43: =SUM(Z43:AK43) | JH43: =SUM(AL43:AP43) | JI43: =SUM(C43:AP43) | JM43: -8000 | KG43: =B43 | KH43: =AR43
A44: Gerenciamento | B44: =SUM(C44:AP44) | AD44: -8000 | AE44: -8000 | AF44: -8000 | AG44: -8000 | AH44: -8000 | AI44: -8840.61 | AJ44: -8840.61 | AK44: -8840.61 | AL44: -8840.61 | AM44: -8840.61 | AN44: -8840.61 | AO44: -8840.61 | AP44: -8840.61 | AR44: =SUM(AT44:HU44) | AT44: -8840.61 | AU44: -8840.61 | AV44: -8840.61 | AW44: -8840.61 | AX44: -8840.61 | AY44: -8840.61 | AZ44: -8840.61 | BA44: -8840.61 | BB44: -8840.61 | BC44: -8840.61 | BD44: -8840.61 | BE44: -8840.61 | BF44: -8840.61 | BG44: -8840.61 | BH44: -8840.61 | BI44: -8840.61 | BJ44: -8840.61 | BK44: -8840.61 | BL44: -8840.61 | BM44: -8840.61 | BN44: -8840.61 | BO44: -8840.61 | BP44: -8840.61 | BQ44: -8840.61 | BR44: -8840.61 | BS44: -8840.61 | BT44: -8840.61 | BU44: -8840.61 | BV44: -8840.61 | BW44: -8840.61 | BX44: -8840.61 | BY44: -8840.61 | BZ44: -8840.61 | CA44: -8840.61 | CB44: -8840.61 | CC44: -8840.61 | CD44: -8840.61 | CE44: -8840.61 | CF44: -8840.61 | CG44: -8840.61 | CH44: -8840.61 | CI44: -8840.61 | CJ44: -8840.61 | CK44: -8840.61 | CL44: -8840.61 | CM44: -8840.61 | CN44: -8840.61 | DY44: 0 | DZ44: 0 | EA44: 0 | EB44: 0 | EC44: 0 | ED44: 0 | EE44: 0 | EF44: 0 | EG44: 0 | EH44: 0 | EI44: 0 | EJ44: 0 | EK44: 0 | EL44: 0 | EM44: 0 | EN44: 0 | EO44: 0 | EP44: 0 | EQ44: 0 | ER44: 0 | ES44: 0 | ET44: 0 | EU44: 0 | EV44: 0 | EW44: 0 | EX44: 0 | EY44: 0 | EZ44: 0 | FA44: 0 | FB44: 0 | FC44: 0 | FD44: 0 | FE44: 0 | FF44: 0 | FG44: 0 | FH44: 0 | FI44: 0 | FJ44: 0 | FK44: 0 | FL44: 0 | FM44: 0 | FN44: 0 | FO44: 0 | FP44: 0 | FQ44: 0 | FR44: 0 | FS44: 0 | FT44: 0 | FU44: 0 | FV44: 0 | FW44: 0 | FX44: 0 | FY44: 0 | FZ44: 0 | GA44: 0 | GB44: 0 | GC44: 0 | GD44: 0 | GE44: 0 | GF44: 0 | GG44: 0 | GH44: 0 | GI44: 0 | GJ44: 0 | GK44: 0 | GL44: 0 | GM44: 0 | GN44: 0 | GO44: 0 | GP44: 0 | GQ44: 0 | GR44: 0 | GS44: 0 | GT44: 0 | GU44: 0 | GV44: 0 | GW44: 0 | GX44: 0 | GY44: 0 | GZ44: 0 | HA44: 0 | HB44: 0 | HC44: 0 | HD44: 0 | HE44: 0 | HF44: 0 | HG44: 0 | HH44: 0 | HI44: 0 | HJ44: 0 | HK44: 0 | HL44: 0 | HM44: 0 | HN44: 0 | HO44: 0 | HP44: 0 | HQ44: 0 | HR44: 0 | HS44: 0 | HT44: 0 | HU44: 0 | JF44: =AP44 | JG44: =SUM(Z44:AK44) | JH44: =SUM(AL44:AP44) | JI44: =SUM(C44:AP44) | JM44: -8840.61 | KG44: =B44 | KH44: =AR44
JF45: =AP45 | JG45: =SUM(Z45:AK45) | JH45: =SUM(AL45:AP45) | JI45: =SUM(C45:AP45) | KG45: =B45 | KH45: =AR45
A46: DESPESAS JÚRIDICAS (-) | JF46: =AP46 | JG46: =SUM(Z46:AK46) | JH46: =SUM(AL46:AP46) | JI46: =SUM(C46:AP46) | KG46: =B46 | KH46: =AR46
A47: Despesas juridicas | B47: =SUM(C47:AP47) | AF47: =50092.5732500069-959.8 | AR47: =SUM(AT47:HU47) | AT47: 0 | AU47: 0 | AV47: 0 | AW47: 0 | AX47: 0 | AY47: 0 | AZ47: 0 | BA47: 0 | BB47: 0 | BC47: 0 | BD47: 0 | BE47: 0 | BF47: 0 | BG47: 0 | BH47: 0 | BI47: 0 | BJ47: 0 | BK47: 0 | BL47: 0 | BM47: 0 | BN47: 0 | BO47: 0 | BP47: 0 | BQ47: 0 | BR47: 0 | BS47: 0 | BT47: 0 | BU47: 0 | BV47: 0 | BW47: 0 | BX47: 0 | BY47: 0 | BZ47: 0 | CA47: 0 | CB47: 0 | CC47: 0 | CD47: 0 | CE47: 0 | CF47: 0 | CG47: 0 | CH47: 0 | CI47: 0 | CJ47: 0 | CK47: 0 | CL47: 0 | CM47: 0 | CN47: 0 | CO47: 0 | CP47: 0 | CQ47: 0 | CR47: 0 | CS47: 0 | CT47: 0 | CU47: 0 | CV47: 0 | CW47: 0 | CX47: 0 | CY47: 0 | CZ47: 0 | DA47: 0 | DB47: 0 | DC47: 0 | DD47: 0 | DE47: 0 | DF47: 0 | DG47: 0 | DH47: 0 | DI47: 0 | DJ47: 0 | DK47: 0 | DL47: 0 | DM47: 0 | DN47: 0 | DO47: 0 | DP47: 0 | DQ47: 0 | DR47: 0 | DS47: 0 | DT47: 0 | DU47: 0 | DV47: 0 | DW47: 0 | DX47: 0 | DY47: 0 | DZ47: 0 | EA47: 0 | EB47: 0 | EC47: 0 | ED47: 0 | EE47: 0 | EF47: 0 | EG47: 0 | EH47: 0 | EI47: 0 | EJ47: 0 | EK47: 0 | EL47: 0 | EM47: 0 | EN47: 0 | EO47: 0 | EP47: 0 | EQ47: 0 | ER47: 0 | ES47: 0 | ET47: 0 | EU47: 0 | EV47: 0 | EW47: 0 | EX47: 0 | EY47: 0 | EZ47: 0 | FA47: 0 | FB47: 0 | FC47: 0 | FD47: 0 | FE47: 0 | FF47: 0 | FG47: 0 | FH47: 0 | FI47: 0 | FJ47: 0 | FK47: 0 | FL47: 0 | FM47: 0 | FN47: 0 | FO47: 0 | FP47: 0 | FQ47: 0 | FR47: 0 | FS47: 0 | FT47: 0 | FU47: 0 | FV47: 0 | FW47: 0 | FX47: 0 | FY47: 0 | FZ47: 0 | GA47: 0 | GB47: 0 | GC47: 0 | GD47: 0 | GE47: 0 | GF47: 0 | GG47: 0 | GH47: 0 | GI47: 0 | GJ47: 0 | GK47: 0 | GL47: 0 | GM47: 0 | GN47: 0 | GO47: 0 | GP47: 0 | GQ47: 0 | GR47: 0 | GS47: 0 | GT47: 0 | GU47: 0 | GV47: 0 | GW47: 0 | GX47: 0 | GY47: 0 | GZ47: 0 | HA47: 0 | HB47: 0 | HC47: 0 | HD47: 0 | HE47: 0 | HF47: 0 | HG47: 0 | HH47: 0 | HI47: 0 | HJ47: 0 | HK47: 0 | HL47: 0 | HM47: 0 | HN47: 0 | HO47: 0 | HP47: 0 | HQ47: 0 | HR47: 0 | HS47: 0 | HT47: 0 | HU47: 0 | JF47: =AP47 | JG47: =SUM(Z47:AK47) | JH47: =SUM(AL47:AP47) | JI47: =SUM(C47:AP47) | JM47: 0 | KG47: =B47 | KH47: =AR47
JF48: =AP48 | JG48: =SUM(Z48:AK48) | JH48: =SUM(AL48:AP48) | JI48: =SUM(C48:AP48) | KG48: =B48 | KH48: =AR48
A49: OUTRAS DESPESAS (-) | JF49: =AP49 | JG49: =SUM(Z49:AK49) | JH49: =SUM(AL49:AP49) | JI49: =SUM(C49:AP49) | KG49: =B49 | KH49: =AR49
A50: Outras Despesas (adm) | B50: =SUM(C50:AP50) | L50: -1243.93 | O50: -339 | V50: -389 | W50: 0 | X50: -4 | Y50: -1155.21 | Z50: -148.25 | AA50: -344.9 | AB50: -459.58 | AC50: =-26826.58-250 | AD50: -6297.44 | AE50: -4312.64 | AF50: -4226.87 | AG50: -4662.58 | AH50: -4676.65 | AI50: -5244.59 | AJ50: -5086.32 | AK50: -4749.4 | AL50: -4366.28 | AM50: -4868.24 | AN50: -4811.9 | AO50: -4832.51 | AP50: -4927.16 | AR50: =SUM(AT50:HU50) | AT50: -8000 | AU50: -8000 | AV50: -8000 | AW50: -8000 | AX50: -8000 | AY50: -8000 | AZ50: -8000 | BA50: -8000 | BB50: -8000 | BC50: -8000 | BD50: -8000 | BE50: -8000 | BF50: -8000 | BG50: -8000 | BH50: -8000 | BI50: -8000 | BJ50: -8000 | BK50: -8000 | BL50: -8000 | BM50: -8000 | BN50: -8000 | BO50: -8000 | BP50: -8000 | BQ50: -8000 | BR50: -8000 | BS50: -8000 | BT50: -8000 | BU50: -8000 | BV50: -8000 | BW50: -8000 | BX50: -8000 | BY50: -8000 | BZ50: -8000 | CA50: -8000 | CB50: -8000 | CC50: -8000 | CD50: -8000 | CE50: -8000 | CF50: -8000 | CG50: -8000 | CH50: -8000 | CI50: -8000 | CJ50: -8000 | CK50: -8000 | CL50: -8000 | CM50: -8000 | CN50: -8000 | CO50: -8000 | CP50: -8000 | CQ50: -8000 | CR50: -8000 | CS50: -8000 | CT50: -8000 | CU50: -8000 | CV50: -8000 | CW50: -8000 | CX50: -8000 | CY50: -8000 | CZ50: -8000 | DA50: -8000 | DB50: -8000 | DC50: -8000 | DD50: -8000 | DE50: -8000 | DF50: -8000 | DG50: -8000 | DH50: -8000 | DI50: -8000 | DJ50: -8000 | DK50: -8000 | DL50: -8000 | DM50: -8000 | DN50: -8000 | DO50: -8000 | DP50: -8000 | DQ50: -8000 | JF50: =AP50 | JG50: =SUM(Z50:AK50) | JH50: =SUM(AL50:AP50) | JI50: =SUM(C50:AP50) | JM50: -8000 | KG50: =B50 | KH50: =AR50
JF51: =AP51 | JG51: =SUM(Z51:AK51) | JH51: =SUM(AL51:AP51) | JI51: =SUM(C51:AP51) | KG51: =B51 | KH51: =AR51
A52: TOTAL DE DESPESAS OPERACIONAIS (-) | B52: =SUM(C52:AP52) | C52: =C50+C47+C43+C38+C35+C29 | D52: =D50+D47+D43+D38+D35+D29 | E52: =E50+E47+E43+E38+E35+E29 | F52: =F50+F47+F43+F38+F35+F29 | G52: =G50+G47+G43+G38+G35+G29 | H52: =H50+H47+H43+H38+H35+H29 | I52: =I50+I47+I43+I38+I35+I29 | J52: =J50+J47+J43+J38+J35+J29 | ... AB52: =AB50+AB47+AB43+AB38+AB35+AB29 | AC52: =AC50+AC47+AC43+AC38+AC35+AC29+AC44 | AD52: =AD50+AD47+AD43+AD38+AD35+AD29+AD44 | AE52: =AE50+AE47+AE43+AE38+AE35+AE29+AE44 | AF52: =AF50+AF47+AF43+AF38+AF35+AF29+AF44 | AG52: =AG50+AG47+AG43+AG38+AG35+AG29+AG44 | AH52: =AH50+AH47+AH43+AH38+AH35+AH29+AH44 | AI52: =AI50+AI47+AI43+AI38+AI35+AI29+AI44 | AJ52: =AJ50+AJ47+AJ43+AJ38+AJ35+AJ29+AJ44 | ... AP52: =AP50+AP47+AP43+AP38+AP35+AP29+AP44 | AR52: =SUM(AT52:HU52) | AT52: =AT50+AT47+AT43+AT38+AT35+AT29+AT44+AT40+AT39 | AU52: =AU50+AU47+AU43+AU38+AU35+AU29+AU44+AU40+AU39 | AV52: =AV50+AV47+AV43+AV38+AV35+AV29+AV44+AV40+AV39 | AW52: =AW50+AW47+AW43+AW38+AW35+AW29+AW44+AW40+AW39 | AX52: =AX50+AX47+AX43+AX38+AX35+AX29+AX44+AX40+AX39 | AY52: =AY50+AY47+AY43+AY38+AY35+AY29+AY44+AY40+AY39 | AZ52: =AZ50+AZ47+AZ43+AZ38+AZ35+AZ29+AZ44+AZ40+AZ39 | BA52: =BA50+BA47+BA43+BA38+BA35+BA29+BA44+BA40+BA39 | ... HU52: =HU50+HU47+HU43+HU38+HU35+HU29+HU44+HU40+HU39 | JF52: =AP52 | JG52: =SUM(Z52:AK52) | JH52: =SUM(AL52:AP52) | JI52: =SUM(C52:AP52) | JM52: -4184406.7 | KG52: =B52 | KH52: =AR52
A53: TOTAL ACUMULADO DE DESPESAS OP.(-) | B53: =SUM(C53:AP53) | D53: =C53+D52 | E53: =D53+E52 | F53: =D53+F52 | G53: =E53+G52 | H53: =F53+H52 | I53: =G53+I52 | J53: =I53+J52 | K53: =J53+K52 | L53: =K53+L52 | M53: =L53+M52 | N53: =M53+N52 | O53: =N53+O52 | P53: =O53+P52 | Q53: =P53+Q52 | ... AP53: =AO53+AP52 | AR53: =W53+AR52 | AT53: =AP53+AT52 | AU53: =AT53+AU52 | AV53: =AU53+AV52 | AW53: =AV53+AW52 | AX53: =AW53+AX52 | AY53: =AX53+AY52 | AZ53: =AY53+AZ52 | BA53: =AZ53+BA52 | BB53: =BA53+BB52 | ... HU53: =HT53+HU52 | JF53: =AP53 | JG53: =SUM(Z53:AK53) | JH53: =SUM(AL53:AP53) | JI53: =SUM(C53:AP53) | JM53: -34156967 | KG53: =B53 | KH53: =AR53
JF54: =AP54 | JG54: =SUM(Z54:AK54) | JH54: =SUM(AL54:AP54) | JI54: =SUM(C54:AP54) | KG54: =B54 | KH54: =AR54
A55: IMPOSTOS (-) | JF55: =AP55 | JG55: =SUM(Z55:AK55) | JH55: =SUM(AL55:AP55) | JI55: =SUM(C55:AP55) | KG55: =B55 | KH55: =AR55
A56: Impostos | B56: =SUM(C56:AP56) | AC56: =-210474.96-5661 | AD56: =-120603.87-111025.76 | AE56: -112006.6 | AF56: -432705.99 | AG56: -118838.98 | AH56: -116123.91 | AI56: -354372.51 | AJ56: -173967.62 | AK56: -179418.92 | AL56: -488063.29 | AM56: -163274.46 | AN56: -135237.18 | AO56: -875555.19 | AP56: -284941.98 | AR56: =SUM(AT56:HU56) | AT56: =(AP8+AP9+AP12)*6.75%*-1 | AU56: =(AT8+AT9+AT12)*6.75%*-1 | AV56: =(AU8+AU9+AU12)*6.75%*-1 | AW56: =(AV8+AV9+AV12)*6.75%*-1 | AX56: =(AW8+AW9+AW12)*6.75%*-1 | AY56: =(AX8+AX9+AX12)*6.75%*-1 | AZ56: =(AY8+AY9+AY12)*6.75%*-1 | BA56: =(AZ8+AZ9+AZ12)*6.75%*-1 | BB56: =(BA8+BA9+BA12)*6.75%*-1 | ... DX56: =(DW8+DW9+DW12)*6.75%*-1 | DY56: =(DU8+DU9+DU12)*6.75%*-1 | DZ56: =(DY8+DY9+DY12)*6.75%*-1 | EA56: =(DZ8+DZ9+DZ12)*6.75%*-1 | EB56: =(EA8+EA9+EA12)*6.75%*-1 | EC56: =(EB8+EB9+EB12)*6.75%*-1 | ED56: =(EC8+EC9+EC12)*6.75%*-1 | EE56: =(ED8+ED9+ED12)*6.75%*-1 | EF56: =(EE8+EE9+EE12)*6.75%*-1 | EG56: =(EF8+EF9+EF12)*6.75%*-1 | ... HU56: =(HT8+HT9+HT12)*6.75%*-1 | JF56: =AP56 | JG56: =SUM(Z56:AK56) | JH56: =SUM(AL56:AP56) | JI56: =SUM(C56:AP56) | JM56: -253307.59 | KG56: =B56 | KH56: =AR56
JF57: =AP57 | JG57: =SUM(Z57:AK57) | JH57: =SUM(AL57:AP57) | JI57: =SUM(C57:AP57) | KG57: =B57 | KH57: =AR57
A58: DESAPROPRIAÇÃO (-) | JF58: =AP58 | JG58: =SUM(Z58:AK58) | JH58: =SUM(AL58:AP58) | JI58: =SUM(C58:AP58) | KG58: =B58 | KH58: =AR58
A59: Desapropriação | B59: =SUM(C59:AP59) | C59: 0 | D59: 0 | E59: 0 | F59: 0 | G59: 0 | I59: 0 | J59: 0 | K59: 0 | AG59: -2778000 | AH59: 0 | AI59: 0 | AJ59: 0 | AK59: 0 | AL59: 0 | AM59: 0 | AN59: 0 | AO59: 0 | AP59: 0 | AR59: =SUM(AT59:HU59) | AT59: 0 | AU59: 0 | AV59: 0 | AW59: 0 | AX59: 0 | AY59: 0 | AZ59: 0 | BA59: 0 | BB59: 0 | BC59: 0 | BD59: 0 | BE59: 0 | BF59: 0 | BG59: 0 | BH59: 0 | BI59: 0 | BJ59: 0 | BK59: 0 | BL59: 0 | BM59: 0 | BN59: 0 | BO59: 0 | BP59: 0 | BQ59: 0 | BR59: 0 | BS59: 0 | BT59: 0 | BU59: 0 | BV59: 0 | BW59: 0 | BX59: 0 | BY59: 0 | BZ59: 0 | CA59: 0 | CB59: 0 | CC59: 0 | CD59: 0 | CE59: 0 | CF59: 0 | CG59: 0 | CH59: 0 | CI59: 0 | CJ59: 0 | CK59: 0 | CL59: 0 | CM59: 0 | CN59: 0 | CO59: 0 | CP59: 0 | CQ59: 0 | CR59: 0 | CS59: 0 | CT59: 0 | CU59: 0 | CV59: 0 | CW59: 0 | CX59: 0 | CY59: 0 | CZ59: 0 | DA59: 0 | DB59: 0 | DC59: 0 | DD59: 0 | DE59: 0 | DF59: 0 | DG59: 0 | DH59: 0 | DI59: 0 | DJ59: 0 | DK59: 0 | DL59: 0 | DM59: 0 | DN59: 0 | DO59: 0 | DP59: 0 | DQ59: 0 | DR59: 0 | DS59: 0 | DT59: 0 | DU59: 0 | DV59: 0 | DW59: 0 | DX59: 0 | DY59: 0 | DZ59: 0 | EA59: 0 | EB59: 0 | EC59: 0 | ED59: 0 | EE59: 0 | EF59: 0 | EG59: 0 | EH59: 0 | EI59: 0 | EJ59: 0 | EK59: 0 | EL59: 0 | EM59: 0 | EN59: 0 | EO59: 0 | EP59: 0 | EQ59: 0 | ER59: 0 | ES59: 0 | ET59: 0 | EU59: 0 | EV59: 0 | EW59: 0 | EX59: 0 | EY59: 0 | EZ59: 0 | FA59: 0 | FB59: 0 | FC59: 0 | FD59: 0 | FE59: 0 | FF59: 0 | FG59: 0 | FH59: 0 | FI59: 0 | FJ59: 0 | FK59: 0 | FL59: 0 | FM59: 0 | FN59: 0 | FO59: 0 | FP59: 0 | FQ59: 0 | FR59: 0 | FS59: 0 | FT59: 0 | FU59: 0 | FV59: 0 | FW59: 0 | FX59: 0 | FY59: 0 | FZ59: 0 | GA59: 0 | GB59: 0 | GC59: 0 | GD59: 0 | GE59: 0 | GF59: 0 | GG59: 0 | GH59: 0 | GI59: 0 | GJ59: 0 | GK59: 0 | GL59: 0 | GM59: 0 | GN59: 0 | GO59: 0 | GP59: 0 | GQ59: 0 | GR59: 0 | GS59: 0 | GT59: 0 | GU59: 0 | GV59: 0 | GW59: 0 | GX59: 0 | GY59: 0 | GZ59: 0 | HA59: 0 | HB59: 0 | HC59: 0 | HD59: 0 | HE59: 0 | HF59: 0 | HG59: 0 | HH59: 0 | HI59: 0 | HJ59: 0 | HK59: 0 | HL59: 0 | HM59: 0 | HN59: 0 | HO59: 0 | HP59: 0 | HQ59: 0 | HR59: 0 | HS59: 0 | HT59: 0 | HU59: 0 | JF59: =AP59 | JG59: =SUM(Z59:AK59) | JH59: =SUM(AL59:AP59) | JI59: =SUM(C59:AP59) | JM59: 0 | KG59: =B59 | KH59: =AR59
JF60: =AP60 | JG60: =SUM(Z60:AK60) | JH60: =SUM(AL60:AP60) | JI60: =SUM(C60:AP60) | KG60: =B60 | KH60: =AR60
A61: DISTRATOS (-) | JF61: =AP61 | JG61: =SUM(Z61:AK61) | JH61: =SUM(AL61:AP61) | JI61: =SUM(C61:AP61) | KG61: =B61 | KH61: =AR61
A62: Devoluções | B62: =SUM(C62:AP62) | AD62: -138044.5 | AE62: 0 | AF62: 0 | AG62: 0 | AH62: 0 | AI62: 0 | AJ62: =-59410.58-59410.58-59359.09 | AR62: =SUM(AT62:HU62) | AT62: -91053.071 | AU62: 0 | AV62: 0 | AW62: 0 | AX62: 0 | AY62: 0 | AZ62: 0 | BA62: 0 | BB62: 0 | BC62: 0 | BD62: 0 | BE62: 0 | BF62: 0 | BG62: 0 | BH62: 0 | BI62: 0 | BJ62: 0 | BK62: 0 | BL62: 0 | BM62: 0 | BN62: 0 | BO62: 0 | BP62: 0 | BQ62: 0 | BR62: 0 | BS62: 0 | BT62: 0 | BU62: 0 | BV62: 0 | BW62: 0 | BX62: 0 | BY62: 0 | BZ62: 0 | CA62: 0 | CB62: 0 | CC62: 0 | CD62: 0 | CE62: 0 | CF62: 0 | CG62: 0 | CH62: 0 | CI62: 0 | CJ62: 0 | CK62: 0 | CL62: 0 | CM62: 0 | CN62: 0 | CO62: 0 | CP62: 0 | CQ62: 0 | CR62: 0 | CS62: 0 | CT62: 0 | CU62: 0 | CV62: 0 | CW62: 0 | CX62: 0 | CY62: 0 | CZ62: 0 | DA62: 0 | DB62: 0 | DC62: 0 | DD62: 0 | DE62: 0 | DF62: 0 | DG62: 0 | DH62: 0 | DI62: 0 | DJ62: 0 | DL62: 0 | DN62: 0 | JF62: =AP62 | JG62: =SUM(Z62:AK62) | JH62: =SUM(AL62:AP62) | JI62: =SUM(C62:AP62) | JM62: 0 | KG62: =B62 | KH62: =AR62
JF63: =AP63 | JG63: =SUM(Z63:AK63) | JH63: =SUM(AL63:AP63) | JI63: =SUM(C63:AP63) | KG63: =B63 | KH63: =AR63
A64: DISTRIBUIÇÕES (-) | JF64: =AP64 | JG64: =SUM(Z64:AK64) | JH64: =SUM(AL64:AP64) | JI64: =SUM(C64:AP64) | KG64: =B64 | KH64: =AR64
A65: Devolução de Aporte | B65: =SUM(C65:AP65) | AG65: -4000000 | AH65: 0 | AI65: 0 | AJ65: 0 | AK65: 0 | AL65: 0 | AM65: 0 | AN65: 0 | AO65: 0 | AP65: 0 | AR65: =SUM(AT65:HU65) | AT65: 0 | AU65: 0 | AV65: 0 | AW65: 0 | AX65: 0 | BA65: =-1004788.24-900000+500000+80000 | BD65: 0 | BF65: 0 | BG65: 0 | BH65: 0 | BI65: 0 | BJ65: 0 | BK65: 0 | BL65: 0 | BM65: 0 | BN65: 0 | BO65: 0 | BP65: 0 | BQ65: 0 | BS65: 0 | BT65: 0 | BU65: 0 | BV65: 0 | BW65: 0 | BX65: 0 | BY65: 0 | BZ65: 0 | CA65: 0 | CB65: 0 | CC65: 0 | CD65: 0 | CE65: 0 | CF65: 0 | CG65: 0 | CH65: 0 | CI65: 0 | CJ65: 0 | CK65: 0 | CL65: 0 | CM65: 0 | CN65: 0 | CO65: 0 | CP65: 0 | CQ65: 0 | CR65: 0 | CS65: 0 | CT65: 0 | CU65: 0 | CV65: 0 | CW65: 0 | CX65: 0 | CY65: 0 | CZ65: 0 | DA65: 0 | DB65: 0 | DC65: 0 | DD65: 0 | DE65: 0 | DF65: 0 | DG65: 0 | DH65: 0 | DI65: 0 | DJ65: 0 | DK65: 0 | DL65: 0 | DM65: 0 | DN65: 0 | DO65: 0 | DP65: 0 | DQ65: 0 | DR65: 0 | DS65: 0 | DT65: 0 | DU65: 0 | DV65: 0 | DW65: 0 | DX65: 0 | DY65: 0 | DZ65: 0 | EA65: 0 | EB65: 0 | EC65: 0 | ED65: 0 | EE65: 0 | EF65: 0 | EG65: 0 | EH65: 0 | EI65: 0 | EJ65: 0 | EK65: 0 | EL65: 0 | EM65: 0 | EN65: 0 | EO65: 0 | EP65: 0 | EQ65: 0 | ER65: 0 | ES65: 0 | ET65: 0 | EU65: 0 | EV65: 0 | EW65: 0 | EX65: 0 | EY65: 0 | EZ65: 0 | FA65: 0 | FB65: 0 | FC65: 0 | FD65: 0 | FE65: 0 | FF65: 0 | FG65: 0 | FH65: 0 | FI65: 0 | FJ65: 0 | FK65: 0 | FL65: 0 | FM65: 0 | FN65: 0 | FO65: 0 | FP65: 0 | FQ65: 0 | FR65: 0 | FS65: 0 | FT65: 0 | FU65: 0 | FV65: 0 | FW65: 0 | FX65: 0 | FY65: 0 | FZ65: 0 | GA65: 0 | GB65: 0 | GC65: 0 | GD65: 0 | GE65: 0 | GF65: 0 | GG65: 0 | GH65: 0 | GI65: 0 | GJ65: 0 | GK65: 0 | GL65: 0 | GM65: 0 | GN65: 0 | GO65: 0 | GP65: 0 | GQ65: 0 | GR65: 0 | GS65: 0 | GT65: 0 | GU65: 0 | GV65: 0 | GW65: 0 | GX65: 0 | GY65: 0 | GZ65: 0 | HA65: 0 | HB65: 0 | HC65: 0 | HD65: 0 | HE65: 0 | HF65: 0 | HG65: 0 | HH65: 0 | HI65: 0 | HJ65: 0 | HK65: 0 | HL65: 0 | HM65: 0 | HN65: 0 | HO65: 0 | HP65: 0 | HQ65: 0 | HR65: 0 | HS65: 0 | HT65: 0 | HU65: 0 | JF65: =AP65 | JG65: =SUM(Z65:AK65) | JH65: =SUM(AL65:AP65) | JI65: =SUM(C65:AP65) | JM65: 0 | KG65: =B65 | KH65: =AR65
A66: Distribuição de Resultado | B66: =SUM(C66:AP66) | AF66: 0 | AG66: 0 | AH66: 0 | AI66: 0 | AJ66: 0 | AK66: 0 | AL66: 0 | AM66: 0 | AN66: 0 | AO66: 0 | AP66: 0 | AR66: =SUM(AT66:HU66) | AT66: 0 | AU66: 0 | AV66: 0 | AW66: 0 | AX66: 0 | AY66: 0 | BA66: =-800000-80000 | BB66: =-2000000+600000-600000 | BC66: -2400000 | BD66: -2800000 | BE66: =-2700000+300000+1000000 | BF66: =-2000000+400000 | BG66: =-3000000-300000 | BH66: =-3000000-400000 | BI66: -2800000 | BJ66: =-2800000+100000 | BK66: =-3000000-200000 | BL66: =-3500000+300000-100000 | BM66: =-2500000-300000 | BN66: =-1000000-1000000-500000 | BO66: =-1000000-1000000+150000+400000+50000 | BP66: =-1200000-100000 | BQ66: =-1200000+50000 | BR66: =-3500000-200000-150000 | BS66: =-3800000-200000 | BT66: =-3800000-200000-100000+50000 | BU66: =-3800000-200000-50000+50000 | BV66: =-3800000-200000 | BW66: =-3800000-200000-50000-50000 | BX66: =-3800000-200000-50000-50000 | BY66: =-3800000-200000-100000-50000 | BZ66: =-4200000+50000 | CA66: =-4300000+150000-50000 | CB66: =-4200000-250000 | CC66: =-4400000-250000 | CD66: =-4400000+20000 | CE66: =-4000000-500000+150000 | CF66: =-4200000-200000-100000 | CG66: =-4500000+50000 | CH66: -4500000 | CI66: -4500000 | CJ66: -4500000 | CK66: =-4700000+50000 | CL66: -4500000 | CM66: -4650000 | CN66: =-4200000-800000 | CO66: -5200000 | CP66: =-4900000+150000-50000 | CQ66: =-5000000+100000 | CR66: =-5000000+140000 | CS66: =-5000000+100000 | CT66: =-5000000+50000 | CU66: =-5000000-20000 | CV66: =-5100000+80000-20000 | CW66: -5100000 | CX66: =-5100000+20000+100000 | CY66: =-4500000+50000+250000 | CZ66: =-4600000+150000+10000 | DA66: =-3900000-50000-350000 | DB66: =-3900000-50000+100000 | DC66: =-3900000-50000+80000 | DD66: =-3700000+50000 | DE66: =-3450000-150000+60000 | DF66: =-3450000+30000 | DG66: =-3200000-200000+60000 | DH66: =-3200000-50000+50000 | DI66: =-3200000+80000 | DJ66: =-3000000-100000+220000 | DK66: =-1900000-200000+200000 | DL66: =-1900000-300000+15000 | DM66: =-1800000-50000+70000 | DN66: -1700000 | DO66: =-1750000+50000-50000+20000+2000 | DP66: =-1500000-150000+110000 | DQ66: =-1500000+50000-50000+30000 | DR66: =-1500000+85000 | DS66: -1350000 | DT66: =-1250000+50000-100000+30000 | DU66: =-1250000+50000-50000+25000 | DV66: -1100000 | DW66: =-1100000+50000 | DX66: =-1400000+100000+10000+60000 | DY66: =-900000-20000-30000 | DZ66: =-900000-20000 | EA66: -1000000 | EB66: =-800000-50000-20000 | EC66: =-800000-30000-10000 | ED66: -850000 | EE66: =-800000+20000-40000-10000 | EF66: =-800000+20000+10000-15000-10000 | EG66: =-770000+5000-50000-10000 | EH66: =-700000-40000-10000 | EI66: =-700000+5000-30000-5000 | EJ66: =-650000-30000-20000 | EK66: =-650000-20000 | EL66: =-600000-40000+1000+5000 | EM66: =-600000-40000+15000 | EN66: =-600000-10000 | EO66: =-600000-5000 | EP66: -600000 | EQ66: =-600000+18000 | ER66: =-600000+25000 | ES66: =-500000-50000-10000 | ET66: =-500000-50000-5000 | EU66: =-620000+70000+5000 | EV66: =-620000+70000+20000 | EW66: -520000 | EX66: -500000 | EY66: =-500000-20000 | EZ66: =-500000+10000 | FA66: =-500000+10000+10000 | FB66: =-450000-20000 | FC66: =-500000+30000+11000 | FD66: =-450000+2000 | FE66: =-420000-20000+2000 | FF66: =-420000-5000 | FG66: =-420000+3000 | FH66: =-420000+15000 | FI66: =-410000+1000+15000 | FJ66: =-390000+15000-5000 | FK66: =-390000+15000 | FL66: =-330000-30000 | FM66: =-330000-50000+30000 | FN66: =-330000-10000 | FO66: =-330000-30000+32000 | FP66: =-330000+15000 | FQ66: =-300000-10000+3000 | FR66: =-320000+5000+10000+12000 | FS66: =-290000+7000 | FT66: =-280000+2000+7000 | FU66: =-270000+5000+5000 | FV66: =-260000+5000+7000 | FW66: =-250000+5000+8000 | FX66: =-235000+2000+8000 | FY66: =-220000+6000 | FZ66: =-220000+10000+8000 | GA66: =-180000-10000 | GB66: =-180000-10000+11000 | GC66: =-180000+5000+8000 | GD66: =-120000-30000-4000 | GE66: =-120000-30000+6000 | GF66: =-120000-15000+3000 | GG66: =-120000+1000 | GH66: =-110000-10000+12000 | GI66: =-100000+5000 | GJ66: =-85000+2000 | GK66: =-85000+15000 | GL66: -60000 | GM66: =-60000+14000 | GN66: =-60000+20000+4000 | GO66: =-55000+30000+3000 | GP66: =-12000-5000+7000+1000 | GQ66: =-12000-5000+7000+1000 | GR66: -2000 | GW66: 0 | GX66: 0 | GY66: 0 | GZ66: 0 | HA66: 0 | HB66: 0 | HC66: 0 | HD66: 0 | HE66: 0 | HF66: 0 | HG66: 0 | HH66: 0 | HI66: 0 | HJ66: 0 | HK66: 0 | HL66: 0 | HM66: 0 | HO66: 0 | HP66: 0 | HQ66: 0 | HS66: 0 | HT66: 0 | JF66: =AP66 | JG66: =SUM(Z66:AK66) | JH66: =SUM(AL66:AP66) | JI66: =SUM(C66:AP66) | JM66: 0 | KG66: =B66 | KH66: =AR66
A67: Subtotal | B67: =SUM(C67:AP67) | C67: =SUM(C65:C66) | D67: =SUM(D65:D66) | E67: =SUM(E65:E66) | F67: =SUM(F65:F66) | G67: =SUM(G65:G66) | H67: =SUM(H65:H66) | I67: =SUM(I65:I66) | J67: =SUM(J65:J66) | ... AB67: =SUM(AB65:AB66) | AG67: =+AG65+AG66 | AH67: =+AH65+AH66 | AI67: =+AI65+AI66 | AJ67: =+AJ65+AJ66 | AK67: =+AK65+AK66 | AL67: =+AL65+AL66 | AM67: =+AM65+AM66 | AN67: =+AN65+AN66 | ... AP67: =+AP65+AP66 | AR67: =SUM(AT67:HU67) | AT67: =SUM(AT65:AT66) | AU67: =SUM(AU65:AU66) | AV67: =SUM(AV65:AV66) | AW67: =SUM(AW65:AW66) | AX67: =SUM(AX65:AX66) | AY67: =SUM(AY65:AY66) | AZ67: =SUM(AZ65:AZ66) | BA67: =SUM(BA65:BA66) | ... HU67: =SUM(HU65:HU66) | JF67: =AP67 | JG67: =SUM(Z67:AK67) | JH67: =SUM(AL67:AP67) | JI67: =SUM(C67:AP67) | JM67: 0 | KG67: =B67 | KH67: =AR67
JF68: =AP68 | JG68: =SUM(Z68:AK68) | JH68: =SUM(AL68:AP68) | JI68: =SUM(C68:AP68) | KG68: =B68 | KH68: =AR68
A69: DESPESAS OP+TERRENO+IMP+DISTR (-) | B69: =SUM(C69:AP69) | C69: =C67+C56+C52+C59+C62 | D69: =D67+D56+D52+D59+D62 | E69: =E67+E56+E52+E59+E62 | F69: =F67+F56+F52+F59+F62 | G69: =G67+G56+G52+G59+G62 | H69: =H67+H56+H52+H59+H62 | I69: =I67+I56+I52+I59+I62 | J69: =J67+J56+J52+J59+J62 | ... AP69: =AP67+AP56+AP52+AP59+AP62 | AR69: =SUM(AT69:HU69) | AT69: =AT67+AT56+AT52+AT59+AT62 | AU69: =AU67+AU56+AU52+AU59+AU62 | AV69: =AV67+AV56+AV52+AV59+AV62 | AW69: =AW67+AW56+AW52+AW59+AW62 | AX69: =AX67+AX56+AX52+AX59+AX62 | AY69: =AY67+AY56+AY52+AY59+AY62 | AZ69: =AZ67+AZ56+AZ52+AZ59+AZ62 | BA69: =BA67+BA56+BA52+BA59+BA62 | ... HU69: =HU67+HU56+HU52+HU59+HU62 | JF69: =AP69 | JG69: =SUM(Z69:AK69) | JH69: =SUM(AL69:AP69) | JI69: =SUM(C69:AP69) | JM69: -4437714.3 | KG69: =B69 | KH69: =AR69
A70: TOTAL ACUMULADO | C70: 0 | D70: =C70+D69 | E70: =D70+E69 | F70: =E70+F69 | G70: =F70+G69 | H70: =G70+H69 | I70: =H70+I69 | J70: =I70+J69 | K70: =J70+K69 | ... AP70: =AO70+AP69 | AR70: 0 | AT70: =AP70+AT69 | AU70: =AT70+AU69 | AV70: =AU70+AV69 | AW70: =AV70+AW69 | AX70: =AW70+AX69 | AY70: =AX70+AY69 | AZ70: =AY70+AZ69 | BA70: =AZ70+BA69 | BB70: =BA70+BB69 | ... HU70: =HT70+HU69 | JF70: =AP70 | JG70: =SUM(Z70:AK70) | JH70: =SUM(AL70:AP70) | JI70: =SUM(C70:AP70) | JM70: -45150579 | KG70: =B70 | KH70: =AR70
JF71: =AP71 | JG71: =SUM(Z71:AK71) | JH71: =SUM(AL71:AP71) | JI71: =SUM(C71:AP71) | KG71: =B71 | KH71: =AR71
A72: SALDO DE CAIXA (MENSAL) | B72: =SUM(C72:AP72) | C72: =C20+C69 | D72: =D20+D69 | E72: =E20+E69 | F72: =F20+F69 | G72: =G20+G69 | H72: =H20+H69 | I72: =I20+I69 | J72: =J20+J69 | ... AP72: =AP20+AP69 | AR72: 0 | AT72: =AT20+AT69 | AU72: =AU20+AU69 | AV72: =AV20+AV69 | AW72: =AW20+AW69 | AX72: =AX20+AX69 | AY72: =AY20+AY69 | AZ72: =AZ20+AZ69 | BA72: =BA20+BA69 | ... HU72: =HU20+HU69 | JF72: =AP72 | JG72: =SUM(Z72:AK72) | JH72: =SUM(AL72:AP72) | JI72: =SUM(C72:AP72) | JM72: -2297202.7 | KG72: =B72 | KH72: =AR72
A73: SALDO ACUMULADO (REAL) | C73: =B73+C72 | D73: =C73+D72 | E73: =D73+E72 | F73: =E73+F72 | G73: =F73+G72 | H73: =G73+H72 | I73: =H73+I72 | J73: =I73+J72 | ... AP73: =AO73+AP72 | AT73: =AP73+AT72 | AU73: =AT73+AU72 | AV73: =AU73+AV72 | AW73: =AV73+AW72 | AX73: =AW73+AX72 | AY73: =AX73+AY72 | AZ73: =AY73+AZ72 | BA73: =AZ73+BA72 | BB73: =BA73+BB72 | ... HU73: =HT73+HU72 | JF73: =AP73 | JG73: =SUM(Z73:AK73) | JH73: =SUM(AL73:AP73) | JI73: =SUM(C73:AP73) | JM73: 10274046 | KG73: =B73 | KH73: =AR73
JF74: =AP74 | JG74: =SUM(Z74:AK74) | JH74: =SUM(AL74:AP74) | JI74: =SUM(C74:AP74) | KG74: =B74 | KH74: =AR74
A75: SALDO DE CAIXA (MENSAL) C/ PROJEÇÃO | B75: =SUM(C75:AP75) | C75: =C20+C69+C12 | D75: =D20+D69+D12 | E75: =E20+E69+E12 | F75: =F20+F69+F12 | G75: =G20+G69+G12 | H75: =H20+H69+H12 | I75: =I20+I69+I12 | J75: =J20+J69+J12 | ... AP75: =AP20+AP69+AP12 | AT75: =AT20+AT69+AT12 | AU75: =AU20+AU69+AU12 | AV75: =AV20+AV69+AV12 | AW75: =AW20+AW69+AW12 | AX75: =AX20+AX69+AX12 | AY75: =AY20+AY69+AY12 | AZ75: =AZ20+AZ69+AZ12 | BA75: =BA20+BA69+BA12 | ... HU75: =HU20+HU69+HU12 | JF75: =AP75 | JG75: =SUM(Z75:AK75) | JH75: =SUM(AL75:AP75) | JI75: =SUM(C75:AP75) | JM75: -1744189.5 | KG75: =B75 | KH75: =AR75
A76: SALDO ACUMULADO C/ PROJEÇÕES | C76: =B76+C75 | D76: =C76+D75 | E76: =D76+E75 | F76: =E76+F75 | G76: =F76+G75 | H76: =G76+H75 | I76: =H76+I75 | J76: =I76+J75 | ... AP76: =AO76+AP75 | AT76: =AP76+AT75 | AU76: =AT76+AU75 | AV76: =AU76+AV75 | AW76: =AV76+AW75 | AX76: =AW76+AX75 | AY76: =AX76+AY75 | AZ76: =AY76+AZ75 | BA76: =AZ76+BA75 | BB76: =BA76+BB75 | ... HU76: =HT76+HU75 | JF76: =AP76 | JG76: =SUM(Z76:AK76) | JH76: =SUM(AL76:AP76) | JI76: =SUM(C76:AP76) | JM76: 10827059 | KG76: =B76 | KH76: =AR76
AT78: =AT5 | AU78: =AU5 | AV78: =AV5 | AW78: =AW5 | AX78: =AX5 | AY78: =AY5 | AZ78: =AZ5 | BA78: =BA5 | ... HU78: =HU5
AE79: 8913488.7 | AF79: 9444535.9 | BF79: PREVISÃO DE | BR79: 1º ano pós obra | CD79: 2º ano pós obra | CP79: 3º ano pós obra | DB79: 4º ano pós obra | DN79: 5º ano pós obra | DZ79: 6º ano pós obra | EL79: 7º ano pós obra | EX79: 8º ano pós obra | FJ79: 9º ano pós obra | FV79: 10º ano pós obra | GH79: 11º ano pós obra | GT79: 12º ano pós obra | HF79: 13º ano pós obra | HR79: 14º ano pós obra
BF80: ENTREGA DA OBRA | BR80: Fundo R$ 1 MM | CD80: Fundo R$ 500k | CP80: Fundo R$ 250k | DB80: Fundo R$ 250k | DN80: Fundo R$ 250k | DZ80: Fundo R$ 250k | EL80: Fundo R$ 250k | EX80: Fundo R$ 250k | FJ80: Fundo R$ 250k | FV80: Fundo R$ 250k | GH80: Fundo R$ 250k | GT80: Fundo R$ 250k | HF80: Fundo R$ 250k | HR80: Fundo R$ 250k
AE81: =+AE79-AE76 | AF81: =+AF79-AF76 | AG81: =3013129.63-AG76 | AH81: =3775046.22-AH76 | AI81: =4232168.49-AI76 | AJ81: =3223191.08-AJ76 | AK81: =3338944.48-AK76 | AL81: =4310244.13-AL76 | AM81: =6156434.67-AM76-612.82 | AN81: =11961744.61-AN76 | AO81: =12571248.85-AO76 | AP81: =11787274.2-AP76 | BR81: =+BR76-1000000 | CD81: =+CD76-500000 | CP81: =+CP76-250000 | DB81: =+DB76-250000 | DN81: =+DN76-250000 | DZ81: =+DZ76-250000 | EL81: =+EL76-250000 | EX81: =+EX76-250000 | FJ81: =+FJ76-250000 | FV81: =+FV76-250000 | GH81: =+GH76-250000 | GT81: =+GT76-250000 | HF81: =+HF76-250000 | HR81: =+HR76-250000
AM82: =6156434.67-6155821.85
BJ84: =BJ66/$AR$66 | BK84: =BK66/$AR$66 | BL84: =BL66/$AR$66 | BM84: =BM66/$AR$66 | BN84: =BN66/$AR$66 | BO84: =BO66/$AR$66 | BP84: =BP66/$AR$66 | BQ84: =BQ66/$AR$66 | ... HT84: =HT66/$AR$66
BA85: 2250
BA86: 1500
BA87: 900
HU88: Saldo médio final pós obra
HU89: =AVERAGE(BI76:HU76)

Sheet FC Total (10 lotes)
AR1: Total | Previsão | BF1: PREVISÃO DE | EC1: FIM DAS VENDAS | JF1: Realizado | JM1: Previsão de Maio feita no fechamento de Abril/26 | KH1: Total | Previsão
A2: Ville de Provence | AB2: =+AB8+AB9+AC8+AC9+AD8+AD9+AE8+AE9+AF8+AF9+AD62 | BF2: ENTREGA DA OBRA | JF2: No mês | JG2: Ano 2025 | JH2: Ano 2026 | JI2: Acumulado | JS2: YTD | JT2: Prev. 2025 | JU2: 2026 | JV2: 2027 | JW2: 2028 | JX2: 2029 | JY2: 2030 | JZ2: Demais
C3: 1 | D3: 2 | E3: 3 | F3: 4 | G3: 5 | H3: 6 | I3: 7 | J3: 8 | K3: 9 | L3: 10 | M3: 11 | N3: 12 | O3: 13 | P3: 14 | Q3: 15 | R3: 16 | S3: 17 | T3: 18 | U3: 19 | V3: 20 | W3: 21 | X3: 22 | Y3: 23 | Z3: 24 | AA3: 25 | AB3: 26 | AC3: 27 | AD3: 28 | AE3: 29 | AF3: 30 | AG3: 31 | AH3: 32 | AI3: 33 | AJ3: 34 | AK3: 35 | AL3: 36 | AM3: 37 | AN3: 38 | AO3: 39 | AP3: 40 | AT3: 41 | AU3: 42 | AV3: 43 | AW3: 44 | AX3: 45 | AY3: 46 | AZ3: 47 | BA3: 48 | BB3: 49 | BC3: 50 | BD3: 51 | BE3: 52 | BF3: 53 | BG3: 54 | BH3: 55 | BI3: 56 | BJ3: 57 | BK3: 58 | BL3: 59 | BM3: 60 | BN3: 61 | BO3: 62 | BP3: 63 | BQ3: 64 | BR3: 65 | BS3: 66 | BT3: 67 | BU3: 68 | BV3: 69 | BW3: 70 | BX3: 71 | BY3: 72 | BZ3: 73 | CA3: 74 | CB3: 75 | CC3: 76 | CD3: 77 | CE3: 78 | CF3: 79 | CG3: 80 | CH3: 81 | CI3: 82 | CJ3: 83 | CK3: 84 | CL3: 85 | CM3: 86 | CN3: 87 | CO3: 88 | CP3: 89 | CQ3: 90 | CR3: 91 | CS3: 92 | CT3: 93 | CU3: 94 | CV3: 95 | CW3: 96 | CX3: 97 | CY3: 98 | CZ3: 99 | DA3: 100 | DB3: 101 | DC3: 102 | DD3: 103 | DE3: 104 | DF3: 105 | DG3: 106 | DH3: 107 | DI3: 108 | DJ3: 109 | DK3: 110 | DL3: 111 | DM3: 112 | DN3: 113 | DO3: 114 | DP3: 115 | DQ3: 116 | DR3: 117 | DS3: 118 | DT3: 119 | DU3: 120 | DV3: 121 | DW3: 122 | DX3: 123 | DY3: 124 | DZ3: 125 | EA3: 126 | EB3: 127 | EC3: 128 | ED3: 129 | EE3: 130 | EF3: 131 | EG3: 132 | EH3: 133 | EI3: 134 | EJ3: 135 | EK3: 136 | EL3: 137 | EM3: 138 | EN3: 139 | EO3: 140 | EP3: 141 | EQ3: 142 | ER3: 143 | ES3: 144 | ET3: 145 | EU3: 146 | EV3: 147 | EW3: 148 | EX3: 149 | EY3: 150 | EZ3: 151 | FA3: 152 | FB3: 153 | FC3: 154 | FD3: 155 | FE3: 156 | FF3: 157 | FG3: 158 | FH3: 159 | FI3: 160 | FJ3: 161 | FK3: 162 | FL3: 163 | FM3: 164 | FN3: 165 | FO3: 166 | FP3: 167 | FQ3: 168 | FR3: 169 | FS3: 170 | FT3: 171 | FU3: 172 | FV3: 173 | FW3: 174 | FX3: 175 | FY3: 176 | FZ3: 177 | GA3: 178 | GB3: 179 | GC3: 180 | GD3: 181 | GE3: 182 | GF3: 183 | GG3: 184 | GH3: 185 | GI3: 186 | GJ3: 187 | GK3: 188 | GL3: 189 | GM3: 190 | GN3: 191 | GO3: 192 | GP3: 193 | GQ3: 194 | GR3: 195 | GS3: 196 | GT3: 197 | GU3: 198 | GV3: 199 | GW3: 200 | GX3: 201 | GY3: 202 | GZ3: 203 | HA3: 204 | HB3: 205 | HC3: 206 | HD3: 207 | HE3: 208 | HF3: 209 | HG3: 210 | HH3: 211 | HI3: 212 | HJ3: 213 | HK3: 214 | HL3: 215 | HM3: 216 | HN3: 217 | HO3: 218 | HP3: 219 | HQ3: 220 | HR3: 221 | HS3: 222 | HT3: 223 | HU3: 224 | JM3: 40
A4: Fluxo de Caixa | B4: REALIZADO | M4: REALIZADO | KG4: REALIZADO
